Workbook
Name Refinery: 'Form Sa1'!$A$41:$K$48,'Form Sa1'!$A$61:$K$168
Name Z_808D63CE_AAC2_4BB4_99F0_D9F2ED9063AB_.wvu.PrintArea: 'Form Sa1'!$A$1:$K$1392

Sheet Read Me
A1: 1 | B1: Instruction Sheet | E1: General Information | H1: Form 1 | K1: Form E2 | N1: Form-Sa1
B2: Baseline Parameters | E2: Summary Sheet | H2: Emission Factor & GWP Backup | K2: Annex Addl Eqp List-Env | N2: Annex Project Activites List
B3: NF-1 BQ Bauxite Quality | E3: NF-2 Fuel Quality in CPP | H3: NF-3 PLF | K3: NF-4 Product Mix | N3: NF-5 Power Mix
B4: NF-6 Carbon Anode Production | E4: NF-7 Smelter CU | H4: NF-8 Others
A5: How to use this File
A6: 2 | B6: Please use the General Information sheet Sr No 7 and 8 to fill the data for the selection of No of years as a baseline Year (s). Year needs to be selected from the drop-down list w.r.t Baseline Years and Assessment year
A8: 3 | B8: Based on the selection years of baseline, the avarage data shall be calaculated automatically
A9: 4 | B9: Automatic calculation (to be found in the menu Formula/Calculation options) must be turned on. It is recommended that you go through the file from start to end. There are few functions which will guide you through the form which depend on previous input, such as cells changing colour if any input is not needed ( see colour codes below). However, sometimes it is relevant to first continue data input in another sheet before going on.
A12: 5 | B12: A cell is to be kept empty, if no data is required. The cell will not take 0 value.
A13: 6 | B13: In several fields you can choose from predefined inputs. For selecting from such a "drop-down list" either click with the mouse on the small arrow appearing at the right border of the cell, or press "Alt-CursorDown" when you have selected the cell. Some fields allow you to input your own text even if such a drop-down list exists. This is the case when drop-down lists contain empty list entries.
A16: 7 | B16: Error messages will occur sometimes when data entries are text of zero. However, the non-appearance of error messages is not a guarantee for correct calculations, as not always a data completeness test is possible. If no result appears in a green field, it can be assumed that some data is still missing. Special care must be taken of consistency of data with the units displayed.
A19: 8 | B19: Colour Codes and fonts:
E20: The formulae can be changed
E21: Please leave blank if no data is to be filled
E22: Fomulae Protected, Energy data summary
E23: Data not to be filled
E24: Fomulae protected, Emission data summary
B25: Yes | E25: Select from the list Yes or No
B26: Select | E26: Select from the list Yes or No or Not Applicable
E27: Please do not enter any data
E28: Emission calculation data inputs
B29: Lignite | E29: Selection from the list
A30: 9 | B30: Navigation panels on top of each sheet provide hyperlinks for quick jumps to individual input sectors. The first line ("Table of contents", "Previous sheet", "Next Sheet", "Summary") and the points "Top of Sheet" and "End of Sheet" are the same for all sheet. Depending on the sheet, further menu items are added. If the background colour of one of the hyperlink areas turned red, this indicates that data is missing in the related section (not in all sheet).
A33: 10 | B33: This template has been locked against any data entry except for yellow fields. However, for transparency reasons, no password has been set. This allows for complete viewing of all formulae. When using this file for data entry, it is recommended to keep the protection in force. The sheets should only be unprotected for checking the validity of formulae. It is recommended to do this in a separate file.
A36: 11 | B36: In order to protect formulae against unintended modifications, which usually lead to wrong and misleading results, it is of utmost importance NOT TO USE the CUT & PASTE feature. If you want to mode data, first COPY and PASTE them, and thereafter delete the unwanted data in the old (wrong) place.
A39: 12 | B39: Data fields have not been optimized for numerical and other formats. However, sheet protection has been limited so as to allow you to use your own formats. In particular, you may decide about the number of decimal places displayed. The number of places is in principle independent from the precision of calculation. In principle the option "Precision as displayed" of MS Excel should be deactivated. For more details, consult MS Excel's "Help" function on this topic.
A44: 11 | B44: DISCLAIMER: All formulae have been developed carefully and thoroughly. However, mistakes cannot be fully excluded. As described above, full transparency for checking the validity of calculations is ensured. Neither the authors of this file nor the Bureau of Energy Efficiency can be held liable for eventual damages resulting from wrong or misleading results of the provided calculations. It is the full responsibility of the user of this file (i.e., The Obligated Entity or Verifier to ensure that correct data is reported to the competent authority.

Sheet Instruction Sheet
A1: INSTRUCTION FOR FILLING UP THE FORM-Sa1 (Detail of production and Energy Consumption & CO2eq Emission) | H1: Go down
A2: Sr No | B2: Details | C2: Note | D2: Frequency of record | E2: Primary Documents from where the information can be sourced and to be kept ready for verification by Accredited Energy Auditor | F2: Secondary Documents from where the information can be sourced and to be kept ready for verification by Accredited Energy Auditor
A3: It is mandatory to fill data in all fields of the excel sheet - General Information, Form Sa1, Annex CPP, Annex Addl Eqp List-Env, Annex Project Activities List
A4: Please fill the data as per colour coding provided at the bottom of Form Sa1
A5: A | B5: Production and capacity utilization details
A6: A1 | B6: Refinery Process
A7: i | B7: Please provide total annual Production Capacity of Hydrate Alumina in tonnes | C7: Capacity of all Precipitar Tank | D7: Annual | E7: 1) OEM Document of Section-wise process line 2) Enviromental Consent to establish/operate document | F7: 1) Equipment/Section wise capacity document from OEM 2) Capacity calculation document submitted for Enviromental Consent
A8: ii | B8: Please provide total annual Production Capacity of Calcined Alumina in tonnes | C8: Capacity of Calciner | D8: Annual | E8: 1) OEM Document of Section-wise Process line 2) Enviromental Consent to establish/operate document | F8: 1) Equipment/Section wise capacity document from OEM 2) Capacity calculation document submitted for Enviromental Consent
A9: iii | B9: Please provide total annual Hydrate Alumina Production (including the exported hydrate alumina) in Tonnes | C9: Production of Hydrate Alumina from all Precipitor Tank | D9: Continuous, Hourly, Daily, Monthly | E9: 1) Log Sheet 2) CCR SCADA Report/ Trends 3) DPR 4) MPR 5) SAP Entry in PP/SD module 6) Excise record (ER1) 7) Annual Report | F9: 1)Hydrate Alumina stock Level 2) Weighhfeeders 3) Belt Weigher 4) Solid flow meter 5) Load cells
A10: iv | B10: Please provide total annual Calcined Alumina Production of all calciner (including the exported calcined alumina) in Tonnes | C10: Production of Calcined Alumina from all Calciner | D10: Continouous, Hourly, Daily, Monthly | E10: 1) Log Sheet 2) CCR SCADA Report/ Ternds 3) DPR 4) MPR 5) SAP Entry in PP/SD module 6) Excise record (ER1) 7) Annual Report | F10: 1)Calcined Alumina stock 2) Weighhfeeders 3) Belt Weigher 4) Solid flow meter 5) Load cells
A11: v | B11: Formula protected (Annual production of Hydrate Alumina/ Annual production capacity of Hydrate Alumina)
A12: vi | B12: Formula protected (Annual production of calcined Alummina/annual production capacity of Calcined Alumina)
A13: A2 | B13: Smelter Process
A14: i | B14: Please provide total annual Production Capacity of Molten Aluminium in tonnes | C14: Capacity of all Potline | D14: Annual | E14: 1) OEM Document of potline 2) Enviromental Consent to establish/operate document | F14: 1) Potline wise capacity document from OEM 2) Capacity calculation document submitted for Enviromental Consent
A15: ii | B15: Please provide total annual Production Capacity of cast House in tonnes | C15: Capacity of cast House | D15: Annual | E15: 1) OEM Document of Section-wise Process line 2) Enviromental Consent to establish/operate document | F15: 1) Equipment/Section wise capacity document from OEM 2) Capacity calculation document submitted for Enviromental Consent
A16: iii | B16: Please provide total annual Molten Aluminium Production in Tonnes | C16: Production of Molten Aluminium from all Potline | D16: Continuous, Hourly, Daily, Monthly | E16: 1) Log Sheet 2) CCR SCADA Report/ Ternds 3) DPR 4) MPR 5) SAP Entry in PP/SD module 6) Excise record (ER1) 7) Annual Report | F16: 1) Laddle weighing system 2) Weight of Molten Aluminium
A17: iv | B17: Please provide total annual cast house Production in Tonnes | C17: production of Casted product from Cast House | D17: Continuous, Hourly, Daily, Monthly | E17: 1) Log Sheet 2) CCR SCADA Report/ Ternds 3) DPR 4) MPR 5) SAP Entry in PP/SD module 6) Excise record (ER1) 7) Annual Report | F17: 1) Cast House Products stock register 2) Weigh Bridge
A18: v | B18: Formula protected (Annual production of Molten Aluminium/ Annual production capacity of Molten Aluminium)
A19: vi | B19: Formula protected (Annual production of Cast House/annual production capacity of Cast House)
A20: A3 | B20: Process wise production and performance detail
A21: A3.1 | B21: Refinery Process
A22: a | B22: Hydrate Alumina
A23: i | B23: Please provide the Hydrate Alumina, exported outside plant boundary or sold to any other entity in Tonnes. | D23: Monthly, Yearly | E23: 1) Inventory Report 2) Excise Document (ER1)3) Stores Entry 4) SAP Entry in MM/PP/SD module | F23: 1) Weigh Bridge 2) Stock Register
A24: ii | B24: Please provide the Hydrate Alumina, imported from outside plant boundary or import from any other entity in Tonnes. | D24: Monthly, Yearly | E24: 1) Inventory Report 2) Excise Document (ER1)3) Stores Entry 4) SAP Entry in MM/PP/SD module | F24: 1) Weigh Bridge 2) Stock Register
A25: iii | B25: Please provide opening stock of hydrate alumina in tonnes | C25: Record Opening and Closing stock on daily basis | D25: Daily, Monthly, Yearly | E25: 1) Inventory Report 2) Excise Document (ER1)3) Stores Entry 4) SAP Entry in MM/PP/SD module
A26: iv | B26: Please provide closing stock of hydrate alumina in tonnes | C26: Record Opening and Closing stock on daily basis | D26: Daily, Monthly, Yearly | E26: 1) Inventory Report 2) Excise Document (ER1)3) Stores Entry 4) SAP Entry in MM/PP/SD module
A27: v | B27: Please provide thermal SEC of hydrate alumina (total thermal energy consumed for production of hydrate alumina in kcal /total hydrate alumina production in tonne) | C27: The energy consumed upto making hydrate Alumina needs to be divided by total hydrate production | D27: Daily, Monthly, Yearly | E27: 1) DPR 2) MPR 3) Stocks register 4) Log Book 4) Annual Report 6) Fuel test Certificate (Internal and External) 7) Excise Record | F27: 1)Operator Shift Register 2) Weighfeeder Reading for fuel feeding 3) Weigher Reading
A28: vi | B28: Please provide electrical SEC of hydrate alumina (total electrical energy consumed for production of hydrate alumina in kWh/total hydrate alumina production in tonne) | D28: Daily, Monthly, Yearly | E28: 1) DPR 2) MPR 3) Stocks register 4) Log Book 4) Annual Report 6)Daily Power Report 7) Monthly Power Report 8) Excise Record | F28: 1)Operator Shift Register 2) Weighfeeder Reading for fuel feeding 3) Weigher Reading 4) Energy Meter Reading 5) Energy Management System
A29: vii | B29: Please provide total annual running Hours of plant for producing Hydrate Alumina | D29: Daily, Monthly, Yearly | E29: 1) DPR 2) MPR 3) DCS/CCR Trend | F29: 1) houer Meter Reading
A30: b | B30: Digestion Process Parameter
A31: i | B31: Please provide Type of Digestion Technology used in plant | E31: 1) OEM document | F31: 1) Name Plate Details
A32: ii | B32: Please provide Number of Digestion Units within the plant | E32: 1) CCR/DCS SCADA Screen Shots
A33: iii | B33: Please provide total annual Production Capacity of Digestion Units in tonne | E33: 1) OEM document | F33: 1) Name Plate Details
A34: iv | B34: Please provide Digestion Specific Steam Consumption (total steam consumed in tonne/total alumina production in tonne) | D34: Daily, Monthly, Yearly | E34: 1) DPR 2) MPR 3) CCR/DCS SCADA Trends 4) Log Book 5)Stock Register 6) Stores Receipt | F34: 1) Steam flow Meter 2) Shift Register
A35: v | B35: Please provide Digestion Specific Power Consumption (total power consumed kWh/total alumina production in tonne) | D35: Daily, Monthly, Yearly | E35: 1) DPR 2) MPR 3) CCR/DCS SCADA Trends 4) Log Book 5)Stock Register 6) Stores Receipt 7) Daily Power Report 8) Monthly Power Report | F35: 1) Energy Meter 2) Energy Management System
A36: vi | B36: Please provide Temperature of Low Temperature Digestion Units in oC | D36: Daily, Monthly, Yearly | E36: 1) SCADA Screen Shots 2) OEM Document 3) Log Book | F36: 1 ) RTDs 2) Temperature Meters
A37: vii | B37: Please provide Pressure of Low Temperature Digestion Units in kg/cm2 | D37: Daily, Monthly, Yearly | E37: 1) SCADA Screen Shots 2) OEM Document 3) Log Book | F37: 1 ) RTDs 2) Pressure Meters
A38: viii | B38: Please provide the temperature of High Temperature Digestion Units in oC | D38: Daily, Monthly, Yearly | E38: 1) SCADA Screen Shots 2) OEM Document 3) Log Book | F38: 1 ) RTDs 2) Temperature Meters
A39: ix | B39: Please provide pressure of High Temperature Digestion Units in kg/cm2 | D39: Daily, Monthly, Yearly | E39: 1) SCADA Screen Shots 2) OEM Document 3) Log Book | F39: 1 ) RTDs 2) Pressure Meters
A40: x | B40: Please provide LP Steam Temperature in oC | D40: Daily, Monthly, Yearly | E40: 1) SCADA Screen Shots 2) OEM Document 3) Log Book | F40: 1 ) RTDs 2) Temperature Meters
A41: xi | B41: Please provide LP steam Pressure in kg/cm2 | D41: Daily, Monthly, Yearly | E41: 1) SCADA Screen Shots 2) OEM Document 3) Log Book | F41: 1 ) RTDs 2) Pressure Meters
A42: xii | B42: Please provide LP Steam Enthalpy in kcal/kg | D42: Daily, Monthly, Yearly | E42: 1) Steam Table 2) Steam Chart
A43: xiii | B43: Please provide LP Steam Consumption in Tonne | D43: Daily, Monthly, Yearly | E43: 1) Log book 2) DPR 3) MPR 4) SCADA Screen Shots 4) SCADA Trends | F43: 1) Steam flow Meter 2) Shift Register
A44: xiv | B44: Please provide MP Steam Temperature in oC | D44: Daily, Monthly, Yearly | E44: 1) SCADA Screen Shots 2) OEM Document 3) Log Book | F44: 1 ) RTDs 2) Temperature Meters
A45: xv | B45: Please provide MP steam Pressure in kg/cm2 | D45: Daily, Monthly, Yearly | E45: 1) SCADA Screen Shots 2) OEM Document 3) Log Book | F45: 1 ) RTDs 2) Pressure Meters
A46: xvi | B46: Please provide MP Steam Enthalpy in kcal/kg | D46: Daily, Monthly, Yearly | E46: 1) Steam Table 2) Steam Chart
A47: xvii | B47: Please provide MP Steam Consumption in Tonne | D47: Daily, Monthly, Yearly | E47: 1) Log book 2) DPR 3) MPR 4) SCADA Screen Shots 4) SCADA Trends | F47: 1) Steam flow Meter 2) Shift Register
A48: xviii | B48: Please provide HP Steam Temperature in oC | D48: Daily, Monthly, Yearly | E48: 1) SCADA Screen Shots 2) OEM Document 3) Log Book | F48: 1 ) RTDs 2) Temperature Meters
A49: xix | B49: Please provide HP steam Pressure in kg/cm2 | D49: Daily, Monthly, Yearly | E49: 1) SCADA Screen Shots 2) OEM Document 3) Log Book | F49: 1 ) RTDs 2) Pressure Meters
A50: xx | B50: Please provide HP Steam Enthalpy in kcal/kg | D50: Daily, Monthly, Yearly | E50: 1) Steam Table 2) Steam Chart
A51: xxi | B51: Please provide HP Steam Consumption in Tonne | D51: Daily, Monthly, Yearly | E51: 1) Log book 2) DPR 3) MPR 4) SCADA Screen Shots 4) SCADA Trends | F51: 1) Steam flow Meter 2) Shift Register
A52: xxii | B52: Please provide Specific Steam Consumption for Evaporation (total steam consumed in tonne/total alumina production in tonne) | D52: Daily, Monthly, Yearly | E52: 1) Log book 2) DPR 3) MPR 4) SCADA Screen Shots 4) SCADA Trends | F52: 1) Steam flow Meter 2) Shift Register
A53: xxiii | B53: Please provide Specific Power Consumption for Evaporation (total power consumed in kWh/total alumina production in tonne) | D53: Daily, Monthly, Yearly | E53: 1) Log book 2) DPR 3) MPR 4) SCADA Screen Shots 4) SCADA Trends 5) Daily Power Report | F53: 1) Energy Meter 2) Shift Register 3) Energy Management System
A54: xxiv | B54: Formula protected Weighted average of Enthalpy
A55: c | B55: Calcined Alumina
A56: i | B56: Please provide Opening stock of Calcined alumina in tonne for Integrated Process Only | C56: Record Opening and Closing stock on daily basis | D56: Daily, Monthly | E56: 1) Inventory Report 2) Excise Document (ER1)3) Stores Entry 4) SAP Entry in MM/PP/SD module | F56: 1) Field Inventory
A57: ii | B57: Please provide Closing stock of Calcined alumina in tonne for Integrated Process only | C57: Record Opening and Closing stock on daily basis | D57: Daily, Monthly | E57: 1) Inventory Report 2) Excise Document (ER1)3) Stores Entry 4) SAP Entry in MM/PP/SD module | F57: 1) Field Inventory
A58: iii | B58: Please provide type of Calciner Technology used within plant | E58: 1) OEM document | F58: 1) Name Plate Details
A59: iv | B59: Please provide calcination Temperature in oC | E59: 1) SCADA Screen Shots 2) OEM Document 3) Log Book | F59: 1 ) RTDs 2) Temperature Meters
A60: v | B60: Please provide Specific Power Consumption for calciner (total electrical consumed in kWh/total alumina production in tonne) | C60: Required per ton of product for calciner section | D60: Daily, Monthly, Annually | E60: 1) Log book 2) DPR 3) MPR 4) SCADA Screen Shots 4) SCADA Trends 5) Daily Power Report | F60: 1) Energy Meter 2) Shift Register 3) Energy Management System
A61: vi | B61: Please provide specific Thermal Consumption for calciner (total thermal energy consumed in kcal/total alumina production in tonne) | C61: Required per ton of product for calciner section | D61: Daily, Monthly, Annually | E61: 1) Log book 2) DPR 3) MPR 4) SCADA Screen Shots 4) SCADA Trends | F61: 1) Shift Register 2) Field Inventory
A62: vii | B62: Please provide toal annual running Hours of all calciners | D62: Daily, Monthly, Annually | E62: 1) DPR 2) MPR 3) DCS/CCR Trend | F62: 1) houer Meter Reading
A63: viii | B63: Please provide total calcined Alumina exported (only for Intergated Process) in tonne | D63: Daily, Monthly, Annually | E63: 1) Inventory Report 2) Excise Document (ER1)3) Stores Entry 4) SAP Entry in MM/PP/SD module | F63: 1) Weigh Bridge 2) Stock Register
A64: ix | B64: Please provide total calcined Alumina Imported (only for Intergated Process) in tonne | D64: Daily, Monthly, Annually | E64: 1) Inventory Report 2) Excise Document (ER1)3) Stores Entry 4) SAP Entry in MM/PP/SD module | F64: 1) Weigh Bridge 2) Stock Register
A65: x | B65: Please provide Specific Thermal Energy Consumption of Calcined Alumina (total Thermal energy consumed in kCal/total calcined alumina production in tonne) | C65: Required per ton of product up to making Calcined Alumina | D65: Daily, Monthly, Annually | E65: 1) Log book 2) DPR 3) MPR 4) SCADA Screen Shots 4) SCADA Trends | F65: 1) Shift Register 2) Field Inventory 3) Section wise Thermal Energy Consumption
A66: xi | B66: Please provide Specific Electrical Energy Consumption of Calcined Alumina (total electrical energy consumed in kWh/total calcined alumina production in tonne) | C66: Required per ton of product up to making Calcined Alumina | D66: Daily, Monthly, Annually | E66: 1) Log book 2) DPR 3) MPR 4) SCADA Screen Shots 4) SCADA Trends 5) Daily Power Report | F66: 1) Energy Meter 2) Shift Register 3) Energy Management System 4) Section wise Power consumption
A67: d/e/f | B67: Special Hydrate Course/Microfined/Milled
A68: i | B68: Please provide total annual production capacity of Special hydrate Course/Microfined/Milled in tonne | D68: Daily, Monthly, Annually | E68: 1) OEM Document of Section-wise Process line 2) Enviromental Consent to establish/operate document | F68: 1) Equipment/Section wise capacity document from OEM 2) Capacity calculation document submitted for Enviromental Consent
A69: ii | B69: Please provide total annual production of special hydrate Course/Microfined/Milled in tonne | D69: Daily, Monthly, Annually | E69: 1) Log Sheet 2) CCR SCADA Report/ Trends 3) DPR 4) MPR 5) SAP Entry in PP/SD module 6) Excise record (ER1) 7) Annual Report | F69: 1)Hydrate Alumina stock Level 2) Weighhfeeders 3) Belt Weigher 4) Solid flow meter 5) Load cells
A70: iii | B70: Please provide Thermal Specific Energy Consumption of special hydrate Course/Microfined/Milled (total thermal energy consumed in kcal/total special grade hydrate alumina production in tonne) | D70: Daily, Monthly, Annually | E70: 1) Log book 2) DPR 3) MPR 4) SCADA Screen Shots 4) SCADA Trends 5) Excise Document 6) Energy Totaliser 7) Fuel Stock Register 8) Stores Finshed Product Stock Register | F70: 1) Shift Register 2) Field Inventory 3) Section wise Thermal Energy Consumption 4) Solid flow Meter 5) Liquid Flow Meter 6) Steam Flow Meter 7) Weigh Bridge
A71: iv | B71: Please provide Electrical Specific Energy Consumption of spcial hydrate Course/Microfined/Milled (total electrical energy consumed in kwh/total special grade hydrate alumina production in tonne) | D71: Daily, Monthly, Annually | E71: 1) Log book 2) DPR 3) MPR 4) SCADA Screen Shots 4) SCADA Trends 5) Excise Document 6) Energy Totaliser 7) Daily Power Report 8) Monthly Power Report 9) Stores Finshed Product Stock Register | F71: 1) Energy Meter 2) Shift Register 3) Energy Management System 4) Section wise Power consumption
A72: g/h/i | B72: Special Alumina Course/Microfined/Milled
A73: i | B73: Please provide total annual production capacity of Special Alumina Course/Microfined/Milled in tonne | D73: Daily, Monthly, Annually | E73: 1) OEM Document of Section-wise Process line 2) Enviromental Consent to establish/operate document | F73: 1) Equipment/Section wise capacity document from OEM 2) Capacity calculation document submitted for Enviromental Consent
A74: ii | B74: Please provide total annual production of special Alumina Course/Microfined/Milled in tonne | D74: Daily, Monthly, Annually | E74: 1) Log Sheet 2) CCR SCADA Report/ Trends 3) DPR 4) MPR 5) SAP Entry in PP/SD module 6) Excise record (ER1) 7) Annual Report | F74: 1) stock Level 2) Weighhfeeders 3) Belt Weigher 4) Solid flow meter 5) Load cells
A75: iii | B75: please provide Thermal Specific Energy Consumption of special Alumina Course/Microfined/Milled (total thermal energy consumed in kcal/total special alumina production in tonne) | D75: Daily, Monthly, Annually | E75: 1) Log book 2) DPR 3) MPR 4) SCADA Screen Shots 4) SCADA Trends 5) Excise Document 6) Energy Totaliser 7) Fuel Stock Register 8) Stores Finshed Product Stock Register | F75: 1) Shift Register 2) Field Inventory 3) Section wise Thermal Energy Consumption 4) Solid flow Meter 5) Liquid Flow Meter 6) Steam Flow Meter 7) Weigh Bridge
A76: iv | B76: Please provide Electrical Specific Energy Consumption of spcial Alumina Course/Microfined/Milled (total electrical energy consumed in kwh/total special alumina production in tonne) | D76: Daily, Monthly, Annually | E76: 1) Log book 2) DPR 3) MPR 4) SCADA Screen Shots 4) SCADA Trends 5) Excise Document 6) Energy Totaliser 7) Daily Power Report 8) Monthly Power Report 9) Stores Finshed Product Stock Register | F76: 1) Energy Meter 2) Shift Register 3) Energy Management System 4) Section wise Power consumption
A77: j | B77: Carbon Black Production
A78: i | B78: Please provide total annual production capacity of carbon black in tonne | D78: Daily, Monthly, Annually | E78: 1) OEM Document of Section-wise Process line 2) Enviromental Consent to establish/operate document | F78: 1) Equipment/Section wise capacity document from OEM 2) Capacity calculation document submitted for Enviromental Consent
A79: ii | B79: Please provide total annual production of carbon black in tonne | D79: Daily, Monthly, Annually | E79: 1) Log Sheet 2) CCR SCADA Report/ Trends 3) DPR 4) MPR 5) SAP Entry in PP/SD module 6) Excise record (ER1) 7) Annual Report | F79: 1) stock Level 2) Weighhfeeders 3) Belt Weigher 4) Solid flow meter 5) Load cells
A80: iii | B80: please provide Thermal Specific Energy Consumption of carbon black (total thermal energy consumed in kcal/total carbon black production in tonne) | D80: Daily, Monthly, Annually | E80: 1) Log book 2) DPR 3) MPR 4) SCADA Screen Shots 4) SCADA Trends 5) Excise Document 6) Energy Totaliser 7) Fuel Stock Register 8) Stores Finshed Product Stock Register | F80: 1) Shift Register 2) Field Inventory 3) Section wise Thermal Energy Consumption 4) Solid flow Meter 5) Liquid Flow Meter 6) Steam Flow Meter 7) Weigh Bridge
A81: iv | B81: Please provide Electrical Specific Energy Consumption of carbon black (total electrica energy consumed in kwh/total carbon black production in tonne) | D81: Daily, Monthly, Annually | E81: 1) Log book 2) DPR 3) MPR 4) SCADA Screen Shots 4) SCADA Trends 5) Excise Document 6) Energy Totaliser 7) Daily Power Report 8) Monthly Power Report 9) Stores Finshed Product Stock Register | F81: 1) Energy Meter 2) Shift Register 3) Energy Management System 4) Section wise Power consumption
A82: k | B82: Carbon Paste Production
A83: i | B83: Please provide total annual production capacity of carbon paste in tonne | D83: Daily, Monthly, Annually | E83: 1) OEM Document of Section-wise Process line 2) Enviromental Consent to establish/operate document | F83: 1) Equipment/Section wise capacity document from OEM 2) Capacity calculation document submitted for Enviromental Consent
A84: ii | B84: Please provide total annual production of carbon paste in tonne | D84: Daily, Monthly, Annually | E84: 1) Log Sheet 2) CCR SCADA Report/ Trends 3) DPR 4) MPR 5) SAP Entry in PP/SD module 6) Excise record (ER1) 7) Annual Report | F84: 1) stock Level 2) Weighhfeeders 3) Belt Weigher 4) Solid flow meter 5) Load cells
A85: iii | B85: please provide Thermal Specific Energy Consumption of carbon paste (total thermal energy consumed in kcal/total carbon paste production in tonne) | D85: Daily, Monthly, Annually | E85: 1) Log book 2) DPR 3) MPR 4) SCADA Screen Shots 4) SCADA Trends 5) Excise Document 6) Energy Totaliser 7) Fuel Stock Register 8) Stores Finshed Product Stock Register | F85: 1) Shift Register 2) Field Inventory 3) Section wise Thermal Energy Consumption 4) Solid flow Meter 5) Liquid Flow Meter 6) Steam Flow Meter 7) Weigh Bridge
A86: iv | B86: Please provide Electrical Specific Energy Consumption of carbon paste (total electrica energy consumed in kwh/total carbon paste production in tonne) | D86: Daily, Monthly, Annually | E86: 1) Log book 2) DPR 3) MPR 4) SCADA Screen Shots 4) SCADA Trends 5) Excise Document 6) Energy Totaliser 7) Daily Power Report 8) Monthly Power Report 9) Stores Finshed Product Stock Register | F86: 1) Energy Meter 2) Shift Register 3) Energy Management System 4) Section wise Power consumption
A87: l | B87: Zeolite Production
A88: i | B88: Please provide total annual production capacity of zeolite in tonne | D88: Daily, Monthly, Annually | E88: 1) OEM Document of Section-wise Process line 2) Enviromental Consent to establish/operate document | F88: 1) Equipment/Section wise capacity document from OEM 2) Capacity calculation document submitted for Enviromental Consent
A89: ii | B89: Please provide total annual production of zeolite in tonne | D89: Daily, Monthly, Annually | E89: 1) Log Sheet 2) CCR SCADA Report/ Trends 3) DPR 4) MPR 5) SAP Entry in PP/SD module 6) Excise record (ER1) 7) Annual Report | F89: 1) stock Level 2) Weighhfeeders 3) Belt Weigher 4) Solid flow meter 5) Load cells
A90: iii | B90: please provide Thermal Specific Energy Consumption of zeolite (total thermal energy consumed in kcal/total zeolite production in tonne) | D90: Daily, Monthly, Annually | E90: 1) Log book 2) DPR 3) MPR 4) SCADA Screen Shots 4) SCADA Trends 5) Excise Document 6) Energy Totaliser 7) Fuel Stock Register 8) Stores Finshed Product Stock Register | F90: 1) Shift Register 2) Field Inventory 3) Section wise Thermal Energy Consumption 4) Solid flow Meter 5) Liquid Flow Meter 6) Steam Flow Meter 7) Weigh Bridge
A91: iv | B91: Please provide Electrical Specific Energy Consumption of zeolite (total electrica energy consumed in kwh/total zeolite production in tonne) | D91: Daily, Monthly, Annually | E91: 1) Log book 2) DPR 3) MPR 4) SCADA Screen Shots 4) SCADA Trends 5) Excise Document 6) Energy Totaliser 7) Daily Power Report 8) Monthly Power Report 9) Stores Finshed Product Stock Register | F91: 1) Energy Meter 2) Shift Register 3) Energy Management System 4) Section wise Power consumption
A92: m | B92: Other Production -1
A93: i | B93: Please Provide name of product produced
A94: ii | B94: Please provide total annual production capacity of Product -1 in tonne | D94: Daily, Monthly, Annually | E94: 1) OEM Document of Section-wise Process line 2) Enviromental Consent to establish/operate document | F94: 1) Equipment/Section wise capacity document from OEM 2) Capacity calculation document submitted for Enviromental Consent
A95: iii | B95: Please provide total annual production of Product - 1 in tonne | D95: Daily, Monthly, Annually | E95: 1) Log Sheet 2) CCR SCADA Report/ Trends 3) DPR 4) MPR 5) SAP Entry in PP/SD module 6) Excise record (ER1) 7) Annual Report | F95: 1) stock Level 2) Weighhfeeders 3) Belt Weigher 4) Solid flow meter 5) Load cells
A96: iv | B96: Please provide Thermal Specific Energy Consumption of Product -1 (total thermal energy consumed in kcal/total Product -1 production in tonne) | D96: Daily, Monthly, Annually | E96: 1) Log book 2) DPR 3) MPR 4) SCADA Screen Shots 4) SCADA Trends 5) Excise Document 6) Energy Totaliser 7) Fuel Stock Register 8) Stores Finshed Product Stock Register | F96: 1) Shift Register 2) Field Inventory 3) Section wise Thermal Energy Consumption 4) Solid flow Meter 5) Liquid Flow Meter 6) Steam Flow Meter 7) Weigh Bridge
A97: v | B97: Please provide Electrical Specific Energy Consumption of Product -1 (total electrica energy consumed in kwh/total Product -1 production in tonne) | D97: Daily, Monthly, Annually | E97: 1) Log book 2) DPR 3) MPR 4) SCADA Screen Shots 4) SCADA Trends 5) Excise Document 6) Energy Totaliser 7) Daily Power Report 8) Monthly Power Report 9) Stores Finshed Product Stock Register | F97: 1) Energy Meter 2) Shift Register 3) Energy Management System 4) Section wise Power consumption
A98: n | B98: Major Product (Calciner/Major product) section start/stop
A99: i | B99: Please provide Equivalent major Production during Cold Start per annum in Tonnes | D99: Continuous, Hourly, Daily, Monthly | E99: 1) Log Sheet 2) CCR SCADA Report/ Trends 3) DPR 4) MPR 5) SAP Entry in PP/SD module 6) Excise record (ER1) 7) Annual Report | F99: 1)Major Product stock Level 2) Weighhfeeders 3) Belt Weigher 4) Solid flow meter 5) Load cells
A100: ii | B100: Please provide Calciner Operating Thermal SEC (Up to section product) in kcal/kg equivalent major product | C100: SEC shall be provided up to calcination | D100: Continuous, Hourly, Daily, Monthly | E100: 1) Log book 2) DPR 3) MPR 4) SCADA Screen Shots 4) SCADA Trends 5) Excise Document 6) Energy Totaliser 7) Fuel Stock Register 8) Stores Finshed Product Stock Register | F100: 1) Shift Register 2) Field Inventory 3) Section wise Thermal Energy Consumption 4) Solid flow Meter 5) Liquid Flow Meter 6) Steam Flow Meter 7) Weigh Bridge
...

Sheet General Information
A1: Form-Sa1 (General Information)
A2: Sector - Aluminium Sector
A3: 1 | B3: Name of the Unit | C3: HINDALCO INDUSTRIES LIMITED
A4: 2 | B4: Sub Sector | C4: INTEGRATED | E4: Subsector | G4: =C4 -> INTEGRATED
A5: 3 | B5: Major Product | C5: MOLTEN ALUMINIUM
A6: 4 | B6: i) Year of Establishment | C6: 1962
B7: ii) Registration No (As provided by BEE) | C7: ALM0009UP
A8: 5 | B8: Plant Contact Details & Address
A9: a | B9: City/Town/Village | C9: RENUKOOT
B10: District | C10: SONBHADRA
B11: State | C11: UTTAR PRADESH | E11: Pin | F11: 231217
B12: Telephone | C12: (05446) 252077-79 / 254791-96 | E12: Fax | F12: (05446) 252107 / 252427
A13: b | B13: Plant's Chief Executive Name | C13: Sameer Nayak
B14: Designation | C14: CHIEF OFFICER-OPERATIONS
B15: Telephone | C15: (05446) 252077-79 / 254791-96 | E15: Fax | F15: (05446) 252107 / 252427
B16: Mobile | C16: 8146628220 | D16: E-mail | E16: sameer.nayak@adityabirla.com
A17: 6 | B17: Registered Office
B18: Company's Chief Executive Name | C18: Satish Pai
B19: Designation | C19: M.D
B20: Address | C20: Ahura Center, Ist Floor, B Wing, Mahakali Caves Road, Andheri (East)
B21: City/Town/Village | C21: 91–22– 2422 7586/2436 2516 | E21: P.O.
B22: District | C22: MUMBAI
B23: State | C23: MAHARASTRA | E23: Pin | F23: 400030
B24: Telephone | C24: 91-22-6662 6666 | E24: Fax | F24: 91–22– 2422 7586/2436 2516
A25: 7 | B25: Energy Manager Details
B26: Name | C26: Vivek Agrawal
B27: Designation | C27: Asst. General Manager | E27: Whether EA or EM | G27: EA
B28: EA/EM Registration No. | C28: 27303
B29: Telephone | C29: (05446) 252077-79 / 254791-96 | E29: Fax | F29: (05446) 252107 / 252427
B30: Mobile | C30: 8114005777 | D30: E-mail ID | E30: (05446) 252107 / 252427
B31: Baseline/ Previous Year (FY ) | C31: FY: 2021-22 | D31: Current/Asssesment/Target Year | G31: FY: 2022-23
A32: 8 | B32: Current / Assessment / Target Period Details
B33: ="Current / Assessment / Target Year Corresponds to" -> Current / Assessment / Target Year Corresponds to | C33: 2025-26
A34: 9 | B34: Base Period Details
A35: A | B35: Number of years' data the unit is required to report as 'Base Period Data' | C35: 1
A36: B | B36: =IF(C35=1,"Base Year Corresponds to","First Base Period Year Corresponds to") -> Base Year Corresponds to | C36: 2023-24
B37: =IF(C35=1," ","Second Base Period Year Corresponds to") | C37: 2022-23
B38: =IF(C35=3,"Third Base Period Year Corresponds to"," ") | C38: 2021-22
A40: 10 | B40: Amendment
A41: S.No | B41: Version No | C41: Date | D41: Details
A42: 1 | B42: V1.1 | C42: 45574 | D42: Modified for CCTS Scheme
A43: 2 | B43: V1.2 | C43: 45584 | D43: 1. Cell 383, 384, Source of data and remark columns unlocked, 2. Process emission summary @ cell 1404- Formula corrected & Default values for Process in slope method revised. 3. Oxidation factor Percentage is made 100 and locked.
A44: 3 | B44: V1.3 | C44: 45651 | D44: 1. The formulas for dedicated line renewable energy (RE) and power calculations have been significantly updated. 2. Exported emission factor has been updated & Heat rate of 860 is considered for RE power as per Amended EC act. 3.Summary sheet has been revised accordingly. 4. GWP potential updated
A45: 4 | B45: V1.4 | C45: 45687 | D45: NF-4 Product Mix sheet E99 cell formula revised

Sheet Form 1
A1: Form-1
A2: Details of information regarding Total Energy Consumed and Specific Energy Consumption Per unit of Production
A3: (See Rule 3)
A4: A. | B4: General Details | C4: Description
A5: 1 | B5: Name of the Unit | C5: ='General Information'!C3 -> HINDALCO INDUSTRIES LIMITED
A6: 2. (i) | B6: Year of Establishment | C6: ='General Information'!C6 -> 1962
A7: 2. (ii) | B7: Registration No (As provided by BEE) | C7: ='General Information'!C7 -> ALM0009UP
A8: 3 | B8: Sector and Sub-Sector in which the Designated Consumer falls | C8: Sector | E8: Sub-Sector
C9: ='General Information'!A2 -> Sector - Aluminium Sector | E9: ='General Information'!G4 -> INTEGRATED
A10: 4. (i) | B10: Complete address of DCs Unit location (including Chief Executive's name & designation) with mobile, telephone, fax nos. & e-mail. | C10: ='General Information'!C9&", "&'General Information'!C10&", "&'General Information'!C11&", "&'General Information'!F11&", "&'General Information'!C12&", "&'General Information'!F12&","&'General Information'!C13&", "&'General Information'!C14&", "&'General Information'!C15&", "&'General Information'!C16&", "&'General Information'!F15&", "&'General Information'!F16 -> RENUKOOT, SONBHADRA, UTTAR PRADESH, 231217, (05446) 252077-79 / 254791-96, (05446) 252107 / 252427,Sameer Nayak, CHIEF OFFICER-OPERATIONS , (05446) 252077-79 / 254791-96, 8146628220, (05446) 252107 / 252427,
A11: (ii) | B11: Registered Office address with telephone, fax nos. & e-mail | C11: ='General Information'!C18&", "&'General Information'!C19&", "&'General Information'!C20&","&'General Information'!C21&","&'General Information'!F21&","&'General Information'!C22&", "&'General Information'!C23&", "&'General Information'!F23&", "&'General Information'!C24&", "&'General Information'!F24 -> Satish Pai, M.D, Ahura Center, Ist Floor, B Wing, Mahakali Caves Road, Andheri (East),91–22– 2422 7586/2436 2516,,MUMBAI, MAHARASTRA, 400030, 91-22-6662 6666, 91–22– 2422 7586/2436 2516
A12: (iii) | B12: Energy Manager's Name, designation, Registration No., Address, Mobile, Telephone, Fax nos. & e-mail | C12: ='General Information'!C26&", "&'General Information'!C27&", "&'General Information'!G27&","&'General Information'!C28&","&'General Information'!C29&", "&'General Information'!F29&", "&'General Information'!C30&", "&'General Information'!E30 -> Vivek Agrawal, Asst. General Manager, EA,27303,(05446) 252077-79 / 254791-96, (05446) 252107 / 252427, 8114005777, (05446) 252107 / 252427
A13: B. | B13: Production details
A14: 5 | B14: Manufacturing Industries notified as Designated Consumers
A15: Sr No | B15: Products | C15: Unit | D15: Baseline/Previous Year | E15: Assesment year/ Current Year
D16: ="FY "&'Form Sa1'!H9 -> FY 2023-24 | E16: ="FY "&'Form Sa1'!I9 -> FY 2025-26
A17: (i) | B17: =IF(OR('General Information'!C4="SMELTER", 'General Information'!C4="INTEGRATED"),'Form Sa1'!B54, 'Form Sa1'!B45) -> Total Molten Aluminium Production | C17: Tonne | D17: =IF(OR('General Information'!$C$4="SMELTER", 'General Information'!$C$4="INTEGRATED"), 'Form Sa1'!H54, 'Form Sa1'!H45) -> 410661.74 | E17: =IF(OR('General Information'!$C$4="SMELTER", 'General Information'!$C$4="INTEGRATED"), 'Form Sa1'!I54, 'Form Sa1'!I45) -> 0
A18: (ii) | B18: =IF(OR('General Information'!$C$4="SMELTER", 'General Information'!$C$4="INTEGRATED"), 'Form Sa1'!B55, 'Form Sa1'!B46) -> Total Production- Cast House | C18: Tonne | D18: =IF(OR('General Information'!$C$4="SMELTER", 'General Information'!$C$4="INTEGRATED"), 'Form Sa1'!H55, 'Form Sa1'!H46) -> 381860.33 | E18: =IF(OR('General Information'!$C$4="SMELTER", 'General Information'!$C$4="INTEGRATED"), 'Form Sa1'!I55, 'Form Sa1'!I46) -> 0
A19: (iii) | B19: =IF(OR('General Information'!$C$4="SMELTER", 'General Information'!$C$4="INTEGRATED"), 'Form Sa1'!B384, 'Form Sa1'!B110) -> Actual Carbon Anode Production | C19: Tonne | D19: =IF(OR('General Information'!$C$4="SMELTER", 'General Information'!$C$4="INTEGRATED"), 'Form Sa1'!H384, 'Form Sa1'!H112) -> 219298.18 | E19: =IF(OR('General Information'!$C$4="SMELTER", 'General Information'!$C$4="INTEGRATED"), 'Form Sa1'!I384, 'Form Sa1'!I112) -> 0
A20: (iv) | B20: =IF(OR('General Information'!$C$4="SMELTER", 'General Information'!$C$4="INTEGRATED"), 'Form Sa1'!B394, 'Form Sa1'!B116) -> Billets | C20: Tonne | D20: =IF(OR('General Information'!$C$4="SMELTER", 'General Information'!$C$4="INTEGRATED"), 'Form Sa1'!H396, 'Form Sa1'!H118) -> 58980.666 | E20: =IF(OR('General Information'!$C$4="SMELTER", 'General Information'!$C$4="INTEGRATED"), 'Form Sa1'!I396, 'Form Sa1'!I118) -> 0
A21: (v) | B21: =IF(OR('General Information'!$C$4="SMELTER", 'General Information'!$C$4="INTEGRATED"), 'Form Sa1'!B400, 'Form Sa1'!B122) -> Ingot | C21: Tonne | D21: =IF(OR('General Information'!$C$4="SMELTER", 'General Information'!$C$4="INTEGRATED"), 'Form Sa1'!H402, 'Form Sa1'!H124) -> 210775.16 | E21: =IF(OR('General Information'!$C$4="SMELTER", 'General Information'!$C$4="INTEGRATED"), 'Form Sa1'!I402, 'Form Sa1'!I124) -> 0
A22: (vi) | B22: =IF(OR('General Information'!$C$4="SMELTER", 'General Information'!$C$4="INTEGRATED"), 'Form Sa1'!B406, 'Form Sa1'!B128) -> Bars | C22: Tonne | D22: =IF(OR('General Information'!$C$4="SMELTER", 'General Information'!$C$4="INTEGRATED"), 'Form Sa1'!H408, 'Form Sa1'!H130) -> 0 | E22: =IF(OR('General Information'!$C$4="SMELTER", 'General Information'!$C$4="INTEGRATED"), 'Form Sa1'!I408, 'Form Sa1'!I130) -> 0
A23: (vii) | B23: =IF(OR('General Information'!$C$4="SMELTER", 'General Information'!$C$4="INTEGRATED"), 'Form Sa1'!B412, 'Form Sa1'!B134) -> Primary Foundry Alloys | C23: Tonne | D23: =IF(OR('General Information'!$C$4="SMELTER", 'General Information'!$C$4="INTEGRATED"), 'Form Sa1'!H414, 'Form Sa1'!H136) -> 0 | E23: =IF(OR('General Information'!$C$4="SMELTER", 'General Information'!$C$4="INTEGRATED"), 'Form Sa1'!I414, 'Form Sa1'!I136) -> 0
A24: (viii) | B24: =IF(OR('General Information'!$C$4="SMELTER", 'General Information'!$C$4="INTEGRATED"), 'Form Sa1'!B418, 'Form Sa1'!B140) -> Wire Rod | C24: Tonne | D24: =IF(OR('General Information'!$C$4="SMELTER", 'General Information'!$C$4="INTEGRATED"), 'Form Sa1'!H420, 'Form Sa1'!H142) -> 55481.148 | E24: =IF(OR('General Information'!$C$4="SMELTER", 'General Information'!$C$4="INTEGRATED"), 'Form Sa1'!I420, 'Form Sa1'!I142) -> 0
A25: (ix) | B25: =IF(OR('General Information'!$C$4="SMELTER", 'General Information'!$C$4="INTEGRATED"), 'Form Sa1'!B424, 'Form Sa1'!B146) -> Strips | C25: Tonne | D25: =IF(OR('General Information'!$C$4="SMELTER", 'General Information'!$C$4="INTEGRATED"), 'Form Sa1'!H426, 'Form Sa1'!H148) -> 76567.049 | E25: =IF(OR('General Information'!$C$4="SMELTER", 'General Information'!$C$4="INTEGRATED"), 'Form Sa1'!I426, 'Form Sa1'!I148) -> 0
A26: (x) | B26: =IF(OR('General Information'!$C$4="SMELTER", 'General Information'!$C$4="INTEGRATED"), 'Form Sa1'!B430, 'Form Sa1'!B152) -> Others , if Any | C26: Tonne | D26: =IF(OR('General Information'!$C$4="SMELTER", 'General Information'!$C$4="INTEGRATED"), 'Form Sa1'!H433, 'Form Sa1'!H154) -> 42078.393 | E26: =IF(OR('General Information'!$C$4="SMELTER", 'General Information'!$C$4="INTEGRATED"), 'Form Sa1'!I433, 'Form Sa1'!I154) -> 0
A27: (xi) | B27: =IF(OR('General Information'!$C$4="SMELTER", 'General Information'!$C$4="INTEGRATED"), "-",'Form Sa1'!B158) -> - | C27: Tonne | D27: =IF(OR('General Information'!$C$4="SMELTER", 'General Information'!$C$4="INTEGRATED"), "-", 'Form Sa1'!H160) -> - | E27: =IF(OR('General Information'!$C$4="SMELTER", 'General Information'!$C$4="INTEGRATED"), "-", 'Form Sa1'!I160) -> -
A28: (xii) | B28: =IF(OR('General Information'!$C$4="SMELTER", 'General Information'!$C$4="INTEGRATED"), "-", 'Form Sa1'!B164) -> - | C28: Tonne | D28: =IF(OR('General Information'!$C$4="SMELTER", 'General Information'!$C$4="INTEGRATED"), "-", 'Form Sa1'!H167) -> - | E28: =IF(OR('General Information'!$C$4="SMELTER", 'General Information'!$C$4="INTEGRATED"), "-", 'Form Sa1'!I167) -> -
A29: (xiii) | B29: Product (Please add extra rows in case of additional products) | C29: Tonne
A30: (xiv) | B30: =IF(OR('General Information'!$C$4="SMELTER", 'General Information'!$C$4="INTEGRATED"), 'Baseline Parameter'!B73,'Baseline Parameter'!B70) -> Total Equivalent Molten Aluminum Produced | C30: Tonne | D30: =' Summary Sheet'!E102 -> 423703.51 | E30: =' Summary Sheet'!F102 -> 0
A31: C | B31: Energy Consumption Details of Manufacturing Industries notified as Designated Consumers
A32: Sr No | B32: Item | C32: Unit | D32: Previous Year | E32: Current Year
C33: (1) | D33: (2) | E33: (3)
A34: 6. (i) | B34: Total Electricity Purchased from Grid/Other Source | C34: Million kwh | D34: =('Form Sa1'!H716/10)+('Form Sa1'!H814/10) -> 118.39134 | E34: =('Form Sa1'!I716/10)+('Form Sa1'!I814/10) -> 0
A35: (ii) | B35: Total Electricity Generated | C35: Million kwh | D35: ='Form Sa1'!H839/10 -> 7087.2925 | E35: ='Form Sa1'!I839/10 -> 0
A36: (iii) | B36: Total Electricity Exported | C36: Million kwh | D36: =('Form Sa1'!H841+'Form Sa1'!H842)/10 -> 178.26538 | E36: =('Form Sa1'!I841+'Form Sa1'!I842)/10 -> 0
A37: (iv) | B37: Total Electrical Energy Consumption | C37: Million kwh | D37: ='Form Sa1'!H845/10 -> 7027.4185 | E37: ='Form Sa1'!I845/10 -> 0
A38: (v) | B38: Total Solid Fuel Consumption | C38: Million kCal | D38: ='Form Sa1'!H1012+'Form Sa1'!H1013+'Form Sa1'!H1014 -> 19863268 | E38: ='Form Sa1'!I1012+'Form Sa1'!I1013+'Form Sa1'!I1014 -> 0
A39: (vi) | B39: Total Liquid Fuel Consumption | C39: Million kCal | D39: ='Form Sa1'!H1171+'Form Sa1'!H1172+'Form Sa1'!H1173+'Form Sa1'!H1174 -> 716331.99 | E39: ='Form Sa1'!I1171+'Form Sa1'!I1172+'Form Sa1'!I1173+'Form Sa1'!I1174 -> 0
A40: (vii) | B40: Total Gaseous Fuel Consumption | C40: Million kCal | D40: ='Form Sa1'!H1217+'Form Sa1'!H1218+'Form Sa1'!H1265 -> 5167.7007 | E40: ='Form Sa1'!I1217+'Form Sa1'!I1218+'Form Sa1'!I1265 -> 0
A41: (viii) | B41: Total Thermal Energy Consumption | C41: Million kCal | D41: ='Form Sa1'!H1306 -> 20584768 | E41: ='Form Sa1'!I1306 -> 0
A42: (ix) | B42: Total Normalized Energy Consumption (Thermal + Electrical) | C42: TOE | D42: NA | E42: =' Summary Sheet'!F72 -> #DIV/0!
A43: D | B43: Specific Energy Consumption Details
A44: 7. i | B44: Specific Energy Consumption(Without Normalization) | C44: TOE/Tonne | D44: =IF(OR('General Information'!$C$4="SMELTER", 'General Information'!$C$4="INTEGRATED"),' Summary Sheet'!E58,' Summary Sheet'!E51) -> 4.9270214 | E44: =IF(OR('General Information'!$C$4="SMELTER", 'General Information'!$C$4="INTEGRATED"),' Summary Sheet'!F58,' Summary Sheet'!F51) -> 0
A45: ii | B45: Specific Energy Consumption (Normalized) | C45: TOE/Tonne | D45: NA | E45: =' Summary Sheet'!F73 -> 0
A47: E | B47: Power Plants notified as Designated Consumer
A48: 8. i. | B48: Total Capacity | C48: MW
A49: ii | B49: Unit Configuration | C49: No. of units with their capacity
A50: iii | B50: Annual Gross Generation | C50: MU
A51: iv | B51: Annual Plant Load Factor (PLF) | C51: %
A52: v | B52: Station Gross Design Heat Rate | C52: kcal/kWh
A53: vi | B53: Station Gross Operative Heat Rate | C53: kcal/kWh
A54: vii | B54: Auxiliary Power Consumption | C54: %
A55: viii | B55: Operative Net Heat Rate | C55: kcal/kWh
A56: ix | B56: Operative Net Heat Rate (Normalized) | C56: kcal/kWh
A58: F | B58: Sector-Wise Details
A59: S.No | B59: Name of the Sector | C59: Sub-Sector | D59: Pro-forma in which the details to be furnished
A60: a | B60: Aluminium | C60: Refinery/Smelter | D60: Sa1
C61: Cold Rolling Sheet | D61: Sa2
A62: b | B62: Cement | C62: Cement | D62: Sb
A63: c | B63: Chlor-Alkali | C63: Chlor-Alkali | D63: Sc
A64: d | B64: Fertilizer | C64: Fertilizer | D64: Sd
A65: e | B65: Iron and Steel | C65: Integrated Steel | D65: Se1
C66: Sponge Iron | D66: Se2
A67: f | B67: Pulp and Paper | C67: Pulp and Paper | D67: Sf
A68: g | B68: Textile | C68: Composite | D68: Sg1
C69: Fiber | D69: Sg2
C70: Spinning | D70: Sg3
C71: Processing | D71: Sg4
A72: h | B72: Thermal Power Plant | C72: Thermal Power Plant | D72: Sh
A74: I/we undertake that the information supplied in the Form 1 and pro- forma is accurate to the best of my knowledge and the data furnished in Form 1 has been adhered to the data given in the concerned pro forma.
A76: Authorised Signatory and Seal
D77: Signature:-
D78: Name of Energy Manager:
A79: Name of Authorised Signatory | D79: Registration Number:
A80: Name of the Designated Consumer:
A81: Full Address:-
A84: Seal
A87: Date

Sheet Form PE
A1: S. No | B1: Particulars | C1: Basis/ Calculation | D1: Unit | E1: Year1 (20.... 20...) | F1: Year2 (20.... 20...) | G1: ="Baseline/ Previous Year (FY ) " & 'Form 1'!D11 -> Baseline/ Previous Year (FY ) | H1: =G1 -> Baseline/ Previous Year (FY ) | I1: ="Current/Asssesment/Target Year "&'Form 1'!E11 -> Current/Asssesment/Target Year | J1: Source of Data
A2: A | B2: Tier 1 - calculation for CO2 emisisons from anode consumption
A3: (i) | B3: Molten Aluminium Production | C3: Annual | D3: t | E3: 1 | F3: 1 | G3: 1 | H3: 1 | I3: 1
A4: (ii) | B4: Select Technology | C4: Value | D4: - | E4: Prebake | F4: Prebake | G4: Prebake | H4: Prebake | I4: Prebake
A5: (iii) | B5: Emission Factor for CO2 from process emissions | C5: Default | D5: t CO2/t al | E5: =IF(E4="Soderberg",E56,E55) -> 1.6 | F5: =IF(F4="Soderberg",F56,F55) -> 1.6 | G5: =IF(G4="Soderberg",G56,G55) -> 1.6 | H5: =IF(H4="Soderberg",H56,H55) -> 1.6 | I5: =IF(I4="Soderberg",I56,I55) -> 1.6
A6: (iv) | B6: Process CO2 emissions from Aluminium Production | C6: D (i) x D (iii) | D6: t CO2 | E6: =E5*E3 -> 1.6 | F6: =F5*F3 -> 1.6 | G6: =G5*G3 -> 1.6 | H6: =H5*H3 -> 1.6 | I6: =I5*I3 -> 1.6 | O6: Soderberg
A7: B | B7: Tier 1 - calculation for CO2 emisisons from anode consumption | O7: Prebake
A8: (i) | B8: Select Technology | C8: Value | D8: - | E8: HSS | F8: HSS | G8: CWPB | H8: HSS | I8: HSS
A9: (ii) | B9: Emission Factor for CF4 from process emissions | C9: Default | D9: kg CF4/t al | E9: =IF(E8=$B$58,E58,IF(E8=$B$59,E59,IF(E8=$B$60,E60,IF(E8=$B$61,E61,0)))) -> 0.4 | F9: =IF(F8=$B$58,F58,IF(F8=$B$59,F59,IF(F8=$B$60,F60,IF(F8=$B$61,F61,0)))) -> 0.4 | G9: =IF(G8=$B$58,G58,IF(G8=$B$59,G59,IF(G8=$B$60,G60,IF(G8=$B$61,G61,0)))) -> 0.4 | H9: =IF(H8=$B$58,H58,IF(H8=$B$59,H59,IF(H8=$B$60,H60,IF(H8=$B$61,H61,0)))) -> 0.4 | I9: =IF(I8=$B$58,I58,IF(I8=$B$59,I59,IF(I8=$B$60,I60,IF(I8=$B$61,I61,0)))) -> 0.4 | O9: CWPB
A10: (iii) | B10: Emission Factor for C2F6 from process emissions | C10: Default | D10: kg C2F6/t al | E10: =IF(E8=B63,E63,IF(E8=B64,E64,IF(E8=B65,E65,IF(E8=B66,E66,0)))) -> 0.03 | F10: =IF(F8=C63,F63,IF(F8=C64,F64,IF(F8=C65,F65,IF(F8=C66,F66,0)))) -> 0 | G10: =IF(G8=D63,G63,IF(G8=D64,G64,IF(G8=D65,G65,IF(G8=D66,G66,0)))) -> 0 | H10: =IF(H8=E63,H63,IF(H8=E64,H64,IF(H8=E65,H65,IF(H8=E66,H66,0)))) -> 0 | I10: =IF(I8=F63,I63,IF(I8=F64,I64,IF(I8=F65,I65,IF(I8=F66,I66,0)))) -> 0 | O10: SWPB
A11: (iv) | B11: GWP for CF4 as per BUR 3 | C11: Default | D11: kg CO2/kg CF4 | E11: 6500 | F11: 6500 | G11: 6500 | H11: 6500 | I11: 6500
A12: (v) | B12: GWP for C2F6 as per BUR 3 | C12: Default | D12: kg CO2/kg C2F6 | E12: 9200 | F12: 9200 | G12: 9200 | H12: 9200 | I12: 9200
A13: (vi) | B13: Total CO2 eq emission from anode consumption | C13: (D (i)* E (ii)* E (iv) +D(i) * E(iii) * E(v))/1000 | D13: t CO2 eq | E13: =(E3*E9*E11+E3*E10*E12)/1000 -> 2.876 | F13: =(F3*F9*F11+F3*F10*F12)/1000 -> 2.6 | G13: =(G3*G9*G11+G3*G10*G12)/1000 -> 2.6 | H13: =(H3*H9*H11+H3*H10*H12)/1000 -> 2.6 | I13: =(I3*I9*I11+I3*I10*I12)/1000 -> 2.6
A14: C | B14: TIER 2/3 method for calculating CO2 emissions from prebake anode consumption
A15: (i) | B15: Molten Aluminium Production | C15: Annual | D15: t al
A16: (ii) | B16: Net Anode Consumption | C16: Annual | D16: t/ t Al
A17: (iii) | B17: Sulphur content in baked anodes (default value = 2) | C17: Average | D17: % wt
A18: (iv) | B18: Ash content in baked anodes (default value - 0.4%) | C18: Average | D18: % wt
A19: (v) | B19: Total CO2 emissions from from Anode Consumption | C19: Annual | D19: t CO2 | E19: =(E15*E16*((100-E17-E18)/100))*44/12 -> 0 | F19: =(F15*F16*((100-F17-F18)/100))*44/12 -> 0 | G19: =(G15*G16*((100-G17-G18)/100))*44/12 -> 0 | H19: =(H15*H16*((100-H17-H18)/100))*44/12 -> 0 | I19: =(I15*I16*((100-I17-I18)/100))*44/12 -> 0
A20: D | B20: Tier 2/3 Method for calculating Pitch Volatlie oxidation from pitch volatile combustion
A21: (i) | B21: Weight of Green Anode | C21: Average | D21: t
A22: (ii) | B22: Weight of Baked Anode | C22: Average | D22: t
A23: (iii) | B23: Baked Anode Production | C23: Annual | D23: t
A24: (iv) | B24: Weight of loaded green anodes | C24: Annual | D24: t | E24: =(E21/E22)*E23 -> #DIV/0! | F24: =(F21/F22)*F23 -> #DIV/0! | G24: =(G21/G22)*G23 -> #DIV/0! | H24: =(H21/H22)*H23 -> #DIV/0! | I24: =(I21/I22)*I23 -> #DIV/0!
A25: (v) | B25: Hydrogen content in green anodes (default value 0.5) | C25: Average | D25: %
A26: (vi) | B26: Waste tar collected (Default for riedhammer furnace 0.005 x GA and 0 for others) | C26: Annual | D26: t
A27: (vii) | B27: Annual CO2 emissions from pitch volatie oxidation | C27: Annual | D27: t CO2 | E27: =((E24-((E25*E24)/100)-E23-E26)*44/12) -> #DIV/0! | F27: =((F24-((F25*F24)/100)-F23-F26)*44/12) -> #DIV/0! | G27: =((G24-((G25*G24)/100)-G23-G26)*44/12) -> #DIV/0! | H27: =((H24-((H25*H24)/100)-H23-H26)*44/12) -> #DIV/0! | I27: =((I24-((I25*I24)/100)-I23-I26)*44/12) -> #DIV/0!
A28: E | B28: Tier 2/3 Method for carbon emissions from Packing Coke
A29: (i) | B29: Packing Coke consumed tonnes per tonne of baked anode (Default value 0.015) | C29: Average | D29: t/t | E29: 0.015 | F29: 0.015 | G29: 0.015 | H29: 0.015 | I29: 0.015
A30: (ii) | B30: Baked Anode Production | C30: Annual | D30: t | E30: 1 | F30: 1 | G30: 1 | H30: 1 | I30: 1
A31: (iii) | B31: Sulphur content in packing coke (default value 2) | C31: Average | D31: % | E31: 2 | F31: 2 | G31: 2 | H31: 2 | I31: 2
A32: (iv) | B32: Ash content in packing coke (Default value 2.5) | C32: Average | D32: % | E32: 2.5 | F32: 2.5 | G32: 2.5 | H32: 2.5 | I32: 2.5
A33: (v) | B33: Annual CO2 emission from packing coke | C33: Annual | D33: t CO2 | E33: =(E29*E30*(100-E31-E32)/100)*44/12 -> 0.052525 | F33: =(F29*F30*(100-F31-F32)/100)*44/12 -> 0.052525 | G33: =(G29*G30*(100-G31-G32)/100)*44/12 -> 0.052525 | H33: =(H29*H30*(100-H31-H32)/100)*44/12 -> 0.052525 | I33: =(I29*I30*(100-I31-I32)/100)*44/12 -> 0.052525
A34: F | B34: Tier 2 Method for CF4 and C2F6 per tonne aluminum using Anode Effect Minutes per cell day (Slope Method)
A35: (i) | B35: Select Technology | C35: - | D35: - | E35: SWPB | F35: SWPB | G35: SWPB | H35: SWPB | I35: SWPB
A36: (ii) | B36: Slope Coefficient | C36: Default | D36: (kg CF4/t al)/ (AE-Mins/cell-day) | E36: =IF(E35=$B$68,E68,IF(E35=$B$69,E69,IF(E35=$B$70,E70,IF(E35=$B$71,E71)*0))) -> 0.272 | F36: =IF(F35=$B$68,F68,IF(F35=$B$69,F69,IF(F35=$B$70,F70,IF(F35=$B$71,F71)*0))) -> 0.272 | G36: =IF(G35=$B$68,G68,IF(G35=$B$69,G69,IF(G35=$B$70,G70,IF(G35=$B$71,G71)*0))) -> 0.272 | H36: =IF(H35=$B$68,H68,IF(H35=$B$69,H69,IF(H35=$B$70,H70,IF(H35=$B$71,H71)*0))) -> 0.272 | I36: =IF(I35=$B$68,I68,IF(I35=$B$69,I69,IF(I35=$B$70,I70,IF(I35=$B$71,I71)*0))) -> 0.272
A37: (iii) | B37: Weight Fraction C2F6/CF4 | C37: Default | D37: Weigh Fraction C2F6/CF4 | E37: =IF(E35=$B$78,E78,IF(E35=$B$79,E79,IF(E35=$B$80,E80,IF(E35=$B$81,E81,0)))) -> 0.252 | F37: =IF(F35=$B$78,F78,IF(F35=$B$79,F79,IF(F35=$B$80,F80,IF(F35=$B$81,F81,0)))) -> 0.252 | G37: =IF(G35=$B$78,G78,IF(G35=$B$79,G79,IF(G35=$B$80,G80,IF(G35=$B$81,G81,0)))) -> 0.252 | H37: =IF(H35=$B$78,H78,IF(H35=$B$79,H79,IF(H35=$B$80,H80,IF(H35=$B$81,H81,0)))) -> 0.252 | I37: =IF(I35=$B$78,I78,IF(I35=$B$79,I79,IF(I35=$B$80,I80,IF(I35=$B$81,I81,0)))) -> 0.252
A38: (iv) | B38: Anode Effect mintues per cell day | C38: Average | D38: AE-m/cell-day
A39: (v) | B39: Emission rate for CF4 | C39: Average | D39: kg CF4/t al | E39: =E38*E36 -> 0 | F39: =F38*F36 -> 0 | G39: =G38*G36 -> 0 | H39: =H38*H36 -> 0 | I39: =I38*I36 -> 0
A40: (vi) | B40: Emission rate for C2F6 | C40: Average | D40: kg C2F6/t al | E40: =E39*E37 -> 0 | F40: =F39*F37 -> 0 | G40: =G39*G37 -> 0 | H40: =H39*H37 -> 0 | I40: =I39*I37 -> 0
A41: (vii) | B41: Emission of tetraflouromethane | C41: Annual | D41: kg CF4 | E41: =E39*E3 -> 0 | F41: =F39*F3 -> 0 | G41: =G39*G3 -> 0 | H41: =H39*H3 -> 0 | I41: =I39*I3 -> 0
A42: (viii) | B42: Emission of Hexaflouroethane | C42: Annual | D42: kg C2F6 | E42: =E40*E3 -> 0 | F42: =F40*F3 -> 0 | G42: =G40*G3 -> 0 | H42: =H40*H3 -> 0 | I42: =I40*I3 -> 0
A43: (ix) | B43: GHG Emission (equivalent) | C43: Annual | D43: t CO2 eq | E43: =(E41*E83+E42*E84)/1000 -> 0 | F43: =(F41*F83+F42*F84)/1000 -> 0 | G43: =(G41*G83+G42*G84)/1000 -> 0 | H43: =(H41*H83+H42*H84)/1000 -> 0 | I43: =(I41*I83+I42*I84)/1000 -> 0
A44: G | B44: Emissions from Soda Ash use associated with Aluminium production
A45: (i) | B45: Soda Ash Consumed | C45: Annual | D45: t | E45: 1 | F45: 1 | G45: 1 | H45: 1 | I45: 1
A46: (ii) | B46: Purity of Soda Ash consumed (deafult value 0.95) | C46: Average | D46: fraction | E46: 0.95 | F46: 0.95 | G46: 0.95 | H46: 0.95 | I46: 0.95
A47: (iii) | B47: Annual CO2 emissions from soda ash | C47: Annual | D47: t CO2 | E47: =E45*E46*(44/106) -> 0.39433962 | F47: =F45*F46*(44/106) -> 0.39433962 | G47: =G45*G46*(44/106) -> 0.39433962 | H47: =H45*H46*(44/106) -> 0.39433962 | I47: =I45*I46*(44/106) -> 0.39433962
A48: H | B48: Emissions from lime production associated with Aluminium production
A49: (i) | B49: Quantity of Quick Lime produced | C49: Annual | D49: t | E49: 1 | F49: 1 | G49: 1 | H49: 1 | I49: 1
A50: (ii) | B50: Purity of Quick Lime produced (deafult value 0.95) | C50: Average | D50: fraction | E50: 0.95 | F50: 0.95 | G50: 0.95 | H50: 0.95 | I50: 0.95
A51: (iii) | B51: Quantity of Slack Lime produced | C51: Annual | D51: t CO2 | E51: 1 | F51: 1 | G51: 1 | H51: 1 | I51: 1
A52: (iv) | B52: Purity of Slack lime produced (deafult value 0.95) | C52: Average | D52: fraction | E52: 0.95 | F52: 0.95 | G52: 0.95 | H52: 0.95 | I52: 0.95
A53: (v) | B53: Annual CO2 emissions | C53: Average | D53: t CO2 | E53: =(E49*E50*44/56)+(E51*E52*44/74) -> 1.3112934 | F53: =(F49*F50*44/56)+(F51*F52*44/74) -> 1.3112934 | G53: =(G49*G50*44/56)+(G51*G52*44/74) -> 1.3112934 | H53: =(H49*H50*44/56)+(H51*H52*44/74) -> 1.3112934 | I53: =(I49*I50*44/56)+(I51*I52*44/74) -> 1.3112934
A54: I | B54: Tier 1 Method Emission Factors -CO2 from process emissions
A55: (i) | B55: Process Emissions (CO2) from anode consumption - Prebake Technology | C55: Default | D55: t CO2/t al | E55: 1.6 | F55: 1.6 | G55: 1.6 | H55: 1.6 | I55: 1.6
A56: (ii) | B56: Process Emissions (CO2) from anode consumption - Soderberg Technology | C56: Default | D56: t CO2/t al | E56: 1.7 | F56: 1.7 | G56: 1.7 | H56: 1.7 | I56: 1.7
A57: J | B57: Tier 1 Method Emission Factors - CF4
A58: (i) | B58: CWPB | C58: Default | D58: kg CF4/t al | E58: 0.4 | F58: 0.4 | G58: 0.4 | H58: 0.4 | I58: 0.4
A59: (ii) | B59: SWPB | C59: Default | D59: kg CF4/t al | E59: 1.6 | F59: 1.6 | G59: 1.6 | H59: 1.6 | I59: 1.6
A60: (iii) | B60: VSS | C60: Default | D60: kg CF4/t al | E60: 0.8 | F60: 0.8 | G60: 0.8 | H60: 0.8 | I60: 0.8
A61: (iv) | B61: HSS | C61: Default | D61: kg CF4/t al | E61: 0.4 | F61: 0.4 | G61: 0.4 | H61: 0.4 | I61: 0.4
A62: K | B62: Tier 1 Method Emission Factors - C2F6
A63: (i) | B63: CWPB | C63: Default | D63: kg C2F6/t al | E63: 0.04 | F63: 0.04 | G63: 0.04 | H63: 0.04 | I63: 0.04
A64: (ii) | B64: SWPB | C64: Default | D64: kg C2F6/t al | E64: 0.4 | F64: 0.4 | G64: 0.4 | H64: 0.4 | I64: 0.4
A65: (iii) | B65: VSS | C65: Default | D65: kg C2F6/t al | E65: 0.04 | F65: 0.04 | G65: 0.04 | H65: 0.04 | I65: 0.04
A66: (iv) | B66: HSS | C66: Default | D66: kg C2F6/t al | E66: 0.03 | F66: 0.03 | G66: 0.03 | H66: 0.03 | I66: 0.03
A67: L | B67: Tier 2 Method Default Values for Slope Coefficient (SCF4)
A68: (i) | B68: CWPB | C68: Default | D68: (kg CF4/t al)/ (AE-Mins/cell-day) | E68: 0.143 | F68: 0.143 | G68: 0.143 | H68: 0.143 | I68: 0.143
A69: (ii) | B69: SWPB | C69: Default | D69: (kg CF4/t al)/ (AE-Mins/cell-day) | E69: 0.272 | F69: 0.272 | G69: 0.272 | H69: 0.272 | I69: 0.272
A70: (iii) | B70: VSS | C70: Default | D70: (kg CF4/t al)/ (AE-Mins/cell-day) | E70: 0.092 | F70: 0.092 | G70: 0.092 | H70: 0.092 | I70: 0.092
A71: (iv) | B71: HSS | C71: Default | D71: (kg CF4/t al)/ (AE-Mins/cell-day) | E71: 0.099 | F71: 0.099 | G71: 0.099 | H71: 0.099 | I71: 0.099
A72: M | B72: Tier 2 Method Default Values for Overvoltage Coefficient (OVC)
A73: (i) | B73: CWPB | C73: Default | D73: (kg CF4/t al)/(mV) | E73: 1.16 | F73: 1.16 | G73: 1.16 | H73: 1.16 | I73: 1.16
A74: (ii) | B74: SWPB | C74: Default | D74: (kg CF4/t al)/(mV) | E74: 3.65 | F74: 3.65 | G74: 3.65 | H74: 3.65 | I74: 3.65
A75: (iii) | B75: VSS | C75: Default | D75: (kg CF4/t al)/(mV) | E75: 0 | F75: 0 | G75: 0 | H75: 0 | I75: 0
A76: (iv) | B76: HSS | C76: Default | D76: (kg CF4/t al)/(mV) | E76: 0 | F76: 0 | G76: 0 | H76: 0 | I76: 0
A77: N | B77: Tier 2 Method Default Values for Weight Fraction (C2F6/CF4)
A78: (i) | B78: CWPB | C78: Default | D78: F C2F6/CF4 | E78: 0.121 | F78: 0.121 | G78: 0.121 | H78: 0.121 | I78: 0.121
A79: (ii) | B79: SWPB | C79: Default | D79: F C2F6/CF4 | E79: 0.252 | F79: 0.252 | G79: 0.252 | H79: 0.252 | I79: 0.252
A80: (iii) | B80: VSS | C80: Default | D80: F C2F6/CF4 | E80: 0.053 | F80: 0.053 | G80: 0.053 | H80: 0.053 | I80: 0.053
A81: (iv) | B81: HSS | C81: Default | D81: F C2F6/CF4 | E81: 0.085 | F81: 0.085 | G81: 0.085 | H81: 0.085 | I81: 0.085
A82: O | B82: GWP of CF4 and C2F6
A83: (i) | B83: GWP for CF4 as per BUR 3 | C83: Default | D83: kg CO2/kg CF4 | E83: 6500 | F83: 6500 | G83: 6500 | H83: 6500 | I83: 6500
A84: (ii) | B84: GWP for C2F6 as per BUR 3 | C84: Default | D84: kg CO2/kg C2F6 | E84: 9200 | F84: 9200 | G84: 9200 | H84: 9200 | I84: 9200

Sheet Form E2
A1: Form-E2
A2: Energy and Emission Form
A3: Section-A: General Details
A4: Sr No | B4: Details | C4: Description
A5: A1 | B5: Registration No | C5: ='General Information'!C7 -> ALM0009UP
A6: A2 | B6: Obligated Entity Name | C6: ='General Information'!C3 -> HINDALCO INDUSTRIES LIMITED
A7: A3 | B7: Sector and Sub-Sector in which the Designated Consumer falls | C7: Sector | E7: Sub-Sector
C8: ='General Information'!A2 -> Sector - Aluminium Sector | E8: ='General Information'!G4 -> INTEGRATED
A9: A4 | B9: Year of Establishment | C9: ='General Information'!C6 -> 1962
A10: A5 | B10: Complete address of DCs Unit location (including Chief Executive's name & designation) with mobile, telephone, fax nos. & e-mail. | C10: ='General Information'!C9&", "&'General Information'!C10&", "&'General Information'!C11&", "&'General Information'!F11&", "&'General Information'!C12&", "&'General Information'!F12&","&'General Information'!C13&", "&'General Information'!C14&", "&'General Information'!C15&", "&'General Information'!C16&", "&'General Information'!F15&", "&'General Information'!F16 -> RENUKOOT, SONBHADRA, UTTAR PRADESH, 231217, (05446) 252077-79 / 254791-96, (05446) 252107 / 252427,Sameer Nayak, CHIEF OFFICER-OPERATIONS , (05446) 252077-79 / 254791-96, 8146628220, (05446) 252107 / 252427,
A11: A6 | B11: Registered Office address with telephone, fax nos. & e-mail | C11: ='General Information'!C18&", "&'General Information'!C19&", "&'General Information'!C20&","&'General Information'!C21&","&'General Information'!F21&","&'General Information'!C22&", "&'General Information'!C23&", "&'General Information'!F23&", "&'General Information'!C24&", "&'General Information'!F24 -> Satish Pai, M.D, Ahura Center, Ist Floor, B Wing, Mahakali Caves Road, Andheri (East),91–22– 2422 7586/2436 2516,,MUMBAI, MAHARASTRA, 400030, 91-22-6662 6666, 91–22– 2422 7586/2436 2516
A12: A7 | B12: Energy Manager's Name, designation, Registration No., Address, Mobile, Telephone, Fax nos. & e-mail | C12: ='General Information'!C26&", "&'General Information'!C27&", "&'General Information'!G27&","&'General Information'!C28&","&'General Information'!C29&", "&'General Information'!F29&", "&'General Information'!C30&", "&'General Information'!E30 -> Vivek Agrawal, Asst. General Manager, EA,27303,(05446) 252077-79 / 254791-96, (05446) 252107 / 252427, 8114005777, (05446) 252107 / 252427
A13: B. Production, Energy Consumption and Emission Details
A14: B1 | B14: Production Details
A15: Sr No | B15: Products | C15: Unit | D15: Baseline/Previous Year | E15: Assesment year/ Current Year
D16: ='Form 1'!D16 -> FY 2023-24 | E16: ='Form 1'!E16 -> FY 2025-26
A17: (i) | B17: =IF(OR('General Information'!C4="SMELTER", 'General Information'!C4="INTEGRATED"),'Form Sa1'!B54, 'Form Sa1'!B45) -> Total Molten Aluminium Production | C17: Tonne | D17: =IF(OR('General Information'!$C$4="SMELTER", 'General Information'!$C$4="INTEGRATED"), 'Form Sa1'!H54, 'Form Sa1'!H45) -> 410661.74 | E17: =IF(OR('General Information'!$C$4="SMELTER", 'General Information'!$C$4="INTEGRATED"), 'Form Sa1'!I54, 'Form Sa1'!I45) -> 0
A18: (ii) | B18: =IF(OR('General Information'!$C$4="SMELTER", 'General Information'!$C$4="INTEGRATED"), 'Form Sa1'!B55, 'Form Sa1'!B46) -> Total Production- Cast House | C18: Tonne | D18: =IF(OR('General Information'!$C$4="SMELTER", 'General Information'!$C$4="INTEGRATED"), 'Form Sa1'!H55, 'Form Sa1'!H46) -> 381860.33 | E18: =IF(OR('General Information'!$C$4="SMELTER", 'General Information'!$C$4="INTEGRATED"), 'Form Sa1'!I55, 'Form Sa1'!I46) -> 0
A19: (iii) | B19: =IF(OR('General Information'!$C$4="SMELTER", 'General Information'!$C$4="INTEGRATED"), 'Form Sa1'!B384, 'Form Sa1'!B110) -> Actual Carbon Anode Production | C19: Tonne | D19: =IF(OR('General Information'!$C$4="SMELTER", 'General Information'!$C$4="INTEGRATED"), 'Form Sa1'!H384, 'Form Sa1'!H112) -> 219298.18 | E19: =IF(OR('General Information'!$C$4="SMELTER", 'General Information'!$C$4="INTEGRATED"), 'Form Sa1'!I384, 'Form Sa1'!I112) -> 0
A20: (iv) | B20: =IF(OR('General Information'!$C$4="SMELTER", 'General Information'!$C$4="INTEGRATED"), 'Form Sa1'!B394, 'Form Sa1'!B116) -> Billets | C20: Tonne | D20: =IF(OR('General Information'!$C$4="SMELTER", 'General Information'!$C$4="INTEGRATED"), 'Form Sa1'!H396, 'Form Sa1'!H118) -> 58980.666 | E20: =IF(OR('General Information'!$C$4="SMELTER", 'General Information'!$C$4="INTEGRATED"), 'Form Sa1'!I396, 'Form Sa1'!I118) -> 0
A21: (v) | B21: =IF(OR('General Information'!$C$4="SMELTER", 'General Information'!$C$4="INTEGRATED"), 'Form Sa1'!B400, 'Form Sa1'!B122) -> Ingot | C21: Tonne | D21: =IF(OR('General Information'!$C$4="SMELTER", 'General Information'!$C$4="INTEGRATED"), 'Form Sa1'!H402, 'Form Sa1'!H124) -> 210775.16 | E21: =IF(OR('General Information'!$C$4="SMELTER", 'General Information'!$C$4="INTEGRATED"), 'Form Sa1'!I402, 'Form Sa1'!I124) -> 0
A22: (vi) | B22: =IF(OR('General Information'!$C$4="SMELTER", 'General Information'!$C$4="INTEGRATED"), 'Form Sa1'!B406, 'Form Sa1'!B128) -> Bars | C22: Tonne | D22: =IF(OR('General Information'!$C$4="SMELTER", 'General Information'!$C$4="INTEGRATED"), 'Form Sa1'!H408, 'Form Sa1'!H130) -> 0 | E22: =IF(OR('General Information'!$C$4="SMELTER", 'General Information'!$C$4="INTEGRATED"), 'Form Sa1'!I408, 'Form Sa1'!I130) -> 0
A23: (vii) | B23: =IF(OR('General Information'!$C$4="SMELTER", 'General Information'!$C$4="INTEGRATED"), 'Form Sa1'!B412, 'Form Sa1'!B134) -> Primary Foundry Alloys | C23: Tonne | D23: =IF(OR('General Information'!$C$4="SMELTER", 'General Information'!$C$4="INTEGRATED"), 'Form Sa1'!H414, 'Form Sa1'!H136) -> 0 | E23: =IF(OR('General Information'!$C$4="SMELTER", 'General Information'!$C$4="INTEGRATED"), 'Form Sa1'!I414, 'Form Sa1'!I136) -> 0
A24: (viii) | B24: =IF(OR('General Information'!$C$4="SMELTER", 'General Information'!$C$4="INTEGRATED"), 'Form Sa1'!B418, 'Form Sa1'!B140) -> Wire Rod | C24: Tonne | D24: =IF(OR('General Information'!$C$4="SMELTER", 'General Information'!$C$4="INTEGRATED"), 'Form Sa1'!H420, 'Form Sa1'!H142) -> 55481.148 | E24: =IF(OR('General Information'!$C$4="SMELTER", 'General Information'!$C$4="INTEGRATED"), 'Form Sa1'!I420, 'Form Sa1'!I142) -> 0
A25: (ix) | B25: =IF(OR('General Information'!$C$4="SMELTER", 'General Information'!$C$4="INTEGRATED"), 'Form Sa1'!B424, 'Form Sa1'!B146) -> Strips | C25: Tonne | D25: =IF(OR('General Information'!$C$4="SMELTER", 'General Information'!$C$4="INTEGRATED"), 'Form Sa1'!H426, 'Form Sa1'!H148) -> 76567.049 | E25: =IF(OR('General Information'!$C$4="SMELTER", 'General Information'!$C$4="INTEGRATED"), 'Form Sa1'!I426, 'Form Sa1'!I148) -> 0
A26: (x) | B26: =IF(OR('General Information'!$C$4="SMELTER", 'General Information'!$C$4="INTEGRATED"), 'Form Sa1'!B430, 'Form Sa1'!B152) -> Others , if Any | C26: Tonne | D26: =IF(OR('General Information'!$C$4="SMELTER", 'General Information'!$C$4="INTEGRATED"), 'Form Sa1'!H433, 'Form Sa1'!H154) -> 42078.393 | E26: =IF(OR('General Information'!$C$4="SMELTER", 'General Information'!$C$4="INTEGRATED"), 'Form Sa1'!I433, 'Form Sa1'!I154) -> 0
A27: (xi) | B27: =IF(OR('General Information'!$C$4="SMELTER", 'General Information'!$C$4="INTEGRATED"), "-",'Form Sa1'!B158) -> - | C27: Tonne | D27: =IF(OR('General Information'!$C$4="SMELTER", 'General Information'!$C$4="INTEGRATED"), "-", 'Form Sa1'!H160) -> - | E27: =IF(OR('General Information'!$C$4="SMELTER", 'General Information'!$C$4="INTEGRATED"), "-", 'Form Sa1'!I160) -> -
A28: (xii) | B28: =IF(OR('General Information'!$C$4="SMELTER", 'General Information'!$C$4="INTEGRATED"), "-", 'Form Sa1'!B164) -> - | C28: Tonne | D28: =IF(OR('General Information'!$C$4="SMELTER", 'General Information'!$C$4="INTEGRATED"), "-", 'Form Sa1'!H167) -> - | E28: =IF(OR('General Information'!$C$4="SMELTER", 'General Information'!$C$4="INTEGRATED"), "-", 'Form Sa1'!I167) -> -
A29: (xiii) | B29: Product (Please add extra rows in case of additional products) | C29: Tonne
A30: (xiv) | B30: =IF(OR('General Information'!$C$4="SMELTER", 'General Information'!$C$4="INTEGRATED"), 'Baseline Parameter'!B73,'Baseline Parameter'!B70) -> Total Equivalent Molten Aluminum Produced | C30: Tonne | D30: =' Summary Sheet'!E102 -> 423703.51 | E30: =' Summary Sheet'!F102 -> 0
A31: B2 | B31: Energy Consumption and GHG Emissions Details
A32: Sr No | B32: Item | C32: Unit | D32: Previous Year | E32: Current Year
C33: (1) | D33: (2) | E33: (3)
A34: (i) | B34: Total Electricity Purchased from Grid/Other Source | C34: Million kwh | D34: =('Form Sa1'!H716/10)+('Form Sa1'!H814/10) -> 118.39134 | E34: =('Form Sa1'!I716/10)+('Form Sa1'!I814/10) -> 0
A35: (ii) | B35: Total Electricity Generated | C35: Million kwh | D35: ='Form Sa1'!H839/10 -> 7087.2925 | E35: ='Form Sa1'!I839/10 -> 0
A36: (iii) | B36: Total Electricity Exported | C36: Million kwh | D36: =('Form Sa1'!H841+'Form Sa1'!H842)/10 -> 178.26538 | E36: =('Form Sa1'!I841+'Form Sa1'!I842)/10 -> 0
A37: (iv) | B37: Total Electrical Energy Consumption | C37: Million kwh | D37: ='Form Sa1'!H845/10 -> 7027.4185 | E37: ='Form Sa1'!I845/10 -> 0
A38: (v) | B38: Total Solid Fuel Consumption | C38: Million kCal | D38: ='Form Sa1'!H1012+'Form Sa1'!H1013+'Form Sa1'!H1014 -> 19863268 | E38: ='Form Sa1'!I1012+'Form Sa1'!I1013+'Form Sa1'!I1014 -> 0
A39: (vi) | B39: Total Liquid Fuel Consumption | C39: Million kCal | D39: ='Form Sa1'!H1171+'Form Sa1'!H1172+'Form Sa1'!H1173+'Form Sa1'!H1174 -> 716331.99 | E39: ='Form Sa1'!I1171+'Form Sa1'!I1172+'Form Sa1'!I1173+'Form Sa1'!I1174 -> 0
A40: (vii) | B40: Total Gaseous Fuel Consumption | C40: Million kCal | D40: ='Form Sa1'!H1217+'Form Sa1'!H1218+'Form Sa1'!H1265 -> 5167.7007 | E40: ='Form Sa1'!I1217+'Form Sa1'!I1218+'Form Sa1'!I1265 -> 0
A41: (viii) | B41: Total Thermal Energy Consumption | C41: Million kCal | D41: ='Form Sa1'!H1306 -> 20584768 | E41: ='Form Sa1'!I1306 -> 0
A42: (ix) | B42: Total Energy Consumption (Thermal + Electrical) | C42: TOE | D42: =' Summary Sheet'!E57 -> 2086083.4 | E42: =' Summary Sheet'!F57 -> #DIV/0!
A43: (x) | B43: Direct GHG Emissions (Energy related) | C43: t CO2 eq | D43: =' Summary Sheet'!E119-' Summary Sheet'!E113 -> 7809145.9 | E43: =' Summary Sheet'!F119-' Summary Sheet'!F113 -> 0
A44: (xi) | B44: Indirect GHG Emissions (Energy related) | C44: t CO2 eq | D44: =' Summary Sheet'!E127 -> 159898.78 | E44: =' Summary Sheet'!F127 -> #DIV/0!
A45: (xii) | B45: Direct GHG Emissions (Process related) | C45: t CO2 eq | D45: =' Summary Sheet'!E113 -> 740123.14 | E45: =' Summary Sheet'!F113 -> 0
A46: (xiii) | B46: Total Direct & Indirect Emissions | C46: t CO2 eq | D46: =' Summary Sheet'!E129 -> 8709167.8 | E46: =' Summary Sheet'!F129 -> #DIV/0!
A47: B3 | B47: Specific Energy Consumption and Specific GHG Emission Details
A48: i | B48: Specific Energy Consumption(Without Normalization) | C48: TOE/Tonne | D48: =IF(OR('General Information'!$C$4="SMELTER", 'General Information'!$C$4="INTEGRATED"),' Summary Sheet'!E58,' Summary Sheet'!E51) -> 4.9270214 | E48: =IF(OR('General Information'!$C$4="SMELTER", 'General Information'!$C$4="INTEGRATED"),' Summary Sheet'!F58,' Summary Sheet'!F51) -> 0
A49: ii | B49: Specific Energy Consumption (Normalized) | C49: TOE/Tonne | D49: NA | E49: =' Summary Sheet'!F73 -> 0
A50: iii | B50: GHG Emissions Intensity (GEI) | C50: t CO2eq/Tonne | D50: =' Summary Sheet'!E130 -> 20.554863 | E50: =' Summary Sheet'!F130 -> 0
A52: E | B52: Power Plants notified as Designated Consumer
A53: 8. i. | B53: Total Capacity | C53: MW
A54: ii | B54: Unit Configuration | C54: No. of units with their capacity
A55: iii | B55: Annual Gross Generation | C55: MU
A56: iv | B56: Annual Plant Load Factor (PLF) | C56: %
A57: v | B57: Station Gross Design Heat Rate | C57: kcal/kWh
A58: vi | B58: Station Gross Operative Heat Rate | C58: kcal/kWh
A59: vii | B59: Auxiliary Power Consumption | C59: %
A60: viii | B60: Operative Net Heat Rate | C60: kcal/kWh
A61: ix | B61: Operative Net Heat Rate (Normalized) | C61: kcal/kWh
A63: F | B63: Sector-Wise Details
A64: S.No | B64: Name of the Sector | C64: Sub-Sector | D64: Pro-forma in which the details to be furnished
A65: a | B65: Aluminium | C65: Refinery/Smelter | D65: Sa1
C66: Cold Rolling Sheet | D66: Sa2
A67: b | B67: Cement | C67: Cement | D67: Sb
A68: c | B68: Chlor-Alkali | C68: Chlor-Alkali | D68: Sc
A69: d | B69: Fertilizer | C69: Fertilizer | D69: Sd
A70: e | B70: Iron and Steel | C70: Integrated Steel | D70: Se1
C71: Sponge Iron | D71: Se2
A72: f | B72: Pulp and Paper | C72: Pulp and Paper | D72: Sf
A73: g | B73: Textile | C73: Composite | D73: Sg1
C74: Fiber | D74: Sg2
C75: Spinning | D75: Sg3
C76: Processing | D76: Sg4
A77: h | B77: Thermal Power Plant | C77: Thermal Power Plant | D77: Sh
A79: I/we undertake that the information supplied in the Energy and Emission Form and Sector Specific Pro-forma is accurate to the best of my knowledge and the data furnished in Form E2 has been adhered to the data given in the concerned Sector Specific Pro-forma
A81: Authorised Signatory and Seal
D82: Signature:-
D83: Name of Energy Manager:
A84: Name of Authorised Signatory | D84: Registration Number:
A85: Name of the Obligated Entity:
A86: Full Address:-
A89: Seal
A92: Date

Sheet Form Sa1
A1: FORM-Sa1 (Details of Production and Energy Consumption)
A2: Sector: Aluminium Sector
A3: Name of the Unit | C3: ='General Information'!C3 &" "& 'General Information'!C8 -> HINDALCO INDUSTRIES LIMITED
A4: Sub Sector | C4: ='General Information'!C4 &" "& 'General Information'!C8 -> INTEGRATED
A5: Major Product | C5: ='General Information'!C5:G5 -> MOLTEN ALUMINIUM
A6: Section Links are available here | C6: Production Data | D6: Smelter Process | E6: Boiler Details | F6: Own Generation | G6: Solid Fuel | H6: Gaseous Fuel | I6: Chilled WaterImp/Exp | J6: Energy savings and Investmements
C7: Refinery Process | D7: Anode & Cast House Production | E7: Electricity Consumption | F7: Renewables In-Pant | G7: Liquid Fuel | H7: Steam Imp/Exp | I7: Miscelleneous Data | J7: Process Emissions
A8: S. No | B8: Particulars | C8: Basis/ Calculation | D8: Unit | E8: =IF(K9=1,"Baseline Year","Year 1 (Baseline)") -> Baseline Year | F8: =IF($K$9=1,"Do not Enter any Data","Year 2 (Baseline)") -> Do not Enter any Data | G8: =IF($K$9=3,"Year 3 (Baseline)","Do not Enter any Data") -> Do not Enter any Data | H8: Baseline Year(s) | I8: Current/Assessment /Target Year | J8: Source of Data | K8: Remarks
E9: ='General Information'!C36 -> 2023-24 | F9: =IF('General Information'!C35=1,"",'General Information'!C37) | G9: =IF('General Information'!C35=3,'General Information'!C38," ") | H9: =IF(K9=1,E9,IF(K9=2,E9&" , "&F9,E9&" , "&F9&" , "&G9)) -> 2023-24 | I9: ='General Information'!C33 -> 2025-26 | K9: ='General Information'!C35 -> 1
A10: I | B10: Boundary Coverage for GHG emissions
A11: (a) | B11: Mining & Raw Material Transportation (Quarring, Mining) | C11: Yes/No/Not Applicable
A12: (b) | B12: Fuel and Additives Preparatioin | C12: Yes/No/Not Applicable
A13: (c) | B13: Bauxite/Limestone Crusher and raw material preparation | C13: Yes/No/Not Applicable
A14: (d) | B14: Caustic Soda Production | C14: Yes/No/Not Applicable | H14: Yes
A15: (e) | B15: Clacined Lime Production | C15: Yes/No/Not Applicable
A16: (f) | B16: Red Mud Handling System | C16: Yes/No/Not Applicable
A17: (g) | B17: Rotary Kiln or Fluidized Bed Calciner | C17: Yes/No/Not Applicable
A18: (h) | B18: Aluminium Floride Production | C18: Yes/No/Not Applicable
A19: (i) | B19: Soda Ash Production | C19: Yes/No/Not Applicable
A20: (j) | B20: Anode/Cathode Production | C20: Yes/No/Not Applicable
A21: (k) | B21: Petroleum Coke Production | C21: Yes/No/Not Applicable
A22: (l) | B22: Molten Aluminium Handling and Ingot casting | C22: Yes/No/Not Applicable
A23: (m) | B23: Scrap Recycling | C23: Yes/No/Not Applicable
A24: (n) | B24: Internal Transportation (Process and Material) | C24: Yes/No/Not Applicable
A25: (o) | B25: On Site Power generation | C25: Yes/No/Not Applicable
A26: (p) | B26: Admin Buildings | C26: Yes/No/Not Applicable
A27: II | B27: Emissions Source Coverage
A28: (a) | B28: Solid Fuel Combustion in CPP/CHP | C28: Yes/No/Not Applicable
A29: (b) | B29: Liquid Fuel Combustion in CPP/CHP | C29: Yes/No/Not Applicable
A30: (c) | B30: Gaseous Fuel Combustion in CPP/CHP | C30: Yes/No/Not Applicable
A31: (d) | B31: Solid Fuel Combustion in Process (Refinery/Smelting) | C31: Yes/No/Not Applicable
A32: (e) | B32: Liquid Fuel Combustion in Process (Refinery/Smelting) | C32: Yes/No/Not Applicable
A33: (f) | B33: Gaseous Fuel Combustion in Process (Refinery/Smelting) | C33: Yes/No/Not Applicable
A34: (g) | B34: Aluminium Smelting Process CO2 emissions | C34: Yes/No/Not Applicable
A35: (h) | B35: PFC Emissions from Smelting | C35: Yes/No/Not Applicable
A36: (i) | B36: Emissions from Coke Production | C36: Yes/No/Not Applicable
A37: (j) | B37: Emission from melting and holding | C37: Yes/No/Not Applicable
A38: (k) | B38: Emissions resulting from Soda Ash Use | C38: Yes/No/Not Applicable
A39: (l) | B39: Emissions from Lime Production | C39: Yes/No/Not Applicable
A40: (m) | B40: Emission from Purchased Electricity | C40: Yes/No/Not Applicable
A41: A | B41: Production and capacity utilization details
A42: A1 | B42: Refinery Process
A43: i | B43: Production Capacity (Hydrate Alumina) | C43: Annual Installed Capacity | D43: Tonne | H43: =IF(K$9=1,E43,IF(K$9=2,(E43+F43)/2,(E43+F43+G43)/3)) -> 700000
A44: ii | B44: Production Capacity (Calcined Alumina) | C44: Annual Installed Capacity | D44: Tonne | H44: =IF(K$9=1,E44,IF(K$9=2,(E44+F44)/2,(E44+F44+G44)/3)) -> 685150
A45: iii | B45: Total Hydrate Alumina Production | C45: Annual | D45: Tonne | H45: =IF(K$9=1,E45,IF(K$9=2,(E45+F45)/2,(E45+F45+G45)/3)) -> 565600
A46: iv | B46: Total Calcined Alumina Production | C46: Annual | D46: Tonne | H46: =IF(K$9=1,E46,IF(K$9=2,(E46+F46)/2,(E46+F46+G46)/3)) -> 561459
A47: v | B47: Red Mud Production (Waste Product) | C47: Annual | D47: Tonne | H47: =IF(K$9=1,E47,IF(K$9=2,(E47+F47)/2,(E47+F47+G47)/3)) -> 1077335
A48: vi | B48: Capacity Utilization (Hydrate Alumina) | C48: [A1(iii) / A1(i)] X 100 | D48: % | E48: =IF(E43=0, 0, (E45/E43)*100) -> 80.8 | F48: =IF(F43=0, 0, (F45/F43)*100) -> 0 | G48: =IF(G43=0, 0, (G45/G43)*100) -> 0 | H48: =IF(H43=0, 0, (H45/H43)*100) -> 80.8 | I48: =IF(I43=0, 0, (I45/I43)*100) -> 0
A49: vii | B49: Capacity Utilization (Calcined Alumina) | C49: [A1(iv) / A1(ii)] X 100 | D49: % | E49: =IF(E44=0, 0, (E46/E44)*100) -> 81.946873 | F49: =IF(F44=0, 0, (F46/F44)*100) -> 0 | G49: =IF(G44=0, 0, (G46/G44)*100) -> 0 | H49: =IF(H44=0, 0, (H46/H44)*100) -> 81.946873 | I49: =IF(I44=0, 0, (I46/I44)*100) -> 0
A51: A2 | B51: Smelter Process
A52: i | B52: Production Capacity (Molten Aluminium) | C52: Annual Installed Capacity | D52: Tonne | H52: =IF(K$9=1,E52,IF(K$9=2,(E52+F52)/2,(E52+F52+G52)/3)) -> 345000
A53: ii | B53: Production Capacity - Cast House | C53: Annual Installed Capacity | D53: Tonne | H53: =IF(K$9=1,E53,IF(K$9=2,(E53+F53)/2,(E53+F53+G53)/3)) -> 278300
A54: iii | B54: Total Molten Aluminium Production | C54: Annual | D54: Tonne | H54: =IF(K$9=1,E54,IF(K$9=2,(E54+F54)/2,(E54+F54+G54)/3)) -> 410661.74
A55: iv | B55: Total Production- Cast House | C55: Annual | D55: Tonne | H55: =IF(K$9=1,E55,IF(K$9=2,(E55+F55)/2,(E55+F55+G55)/3)) -> 381860.33
A56: v | B56: Dross Production (Waste Product) | C56: Annual | D56: Tonne | H56: =IF(K$9=1,E56,IF(K$9=2,(E56+F56)/2,(E56+F56+G56)/3)) -> 5742.05
A57: vi | B57: Spent Liners Production (Waste Product) | C57: Annual | D57: Tonne | H57: =IF(K$9=1,E57,IF(K$9=2,(E57+F57)/2,(E57+F57+G57)/3)) -> 6981.481
A58: vii | B58: Capacity Utilization (Molten Aluminium) | C58: [A2(iii) / A2(i)] X 100 | D58: % | E58: =IF(E52=0, 0, (E54/E52)*100) -> 119.03239 | F58: =IF(F52=0, 0, (F54/F52)*100) -> 0 | G58: =IF(G52=0, 0, (G54/G52)*100) -> 0 | H58: =IF(H52=0, 0, (H54/H52)*100) -> 119.03239 | I58: =IF(I52=0, 0, (I54/I52)*100) -> 0
A59: viii | B59: Capacity Utillization (Cast House) | C59: [A2(iv) / A2(ii)] X 100 | D59: % | E59: =IF(E53=0, 0, (E55/E53)*100) -> 137.21176 | F59: =IF(F53=0, 0, (F55/F53)*100) -> 0 | G59: =IF(G53=0, 0, (G55/G53)*100) -> 0 | H59: =IF(H53=0, 0, (H55/H53)*100) -> 137.21176 | I59: =IF(I53=0, 0, (I55/I53)*100) -> 0
A61: A3 | B61: Process wise production and performance detail
A62: A3.1 | B62: Refinery Process
A63: a | B63: Hydrate Alumina
A64: i | B64: Total Hydrated Alumina sold to Market (Export) | C64: Annual | D64: Tonne | H64: =IF(K$9=1,E64,IF(K$9=2,(E64+F64)/2,(E64+F64+G64)/3)) -> 0
A65: ii | B65: Total Hydrated Alumina purchased from Market for Calcined Alumina (Import) | C65: Annual | D65: Tonne | H65: =IF(K$9=1,E65,IF(K$9=2,(E65+F65)/2,(E65+F65+G65)/3)) -> 0
A66: iii | B66: Opening stock of Hydrated alumina | C66: Annual | D66: Tonne | H66: =IF(K$9=1,E66,IF(K$9=2,(E66+F66)/2,(E66+F66+G66)/3)) -> 30580.066
A67: iv | B67: Closing stock of Hydrated alumina | C67: Annual | D67: Tonne | H67: =IF(K$9=1,E67,IF(K$9=2,(E67+F67)/2,(E67+F67+G67)/3)) -> 34626.579
A68: v | B68: Thermal SEC of Hydrated Alumina | C68: Annual | D68: Mkcal/Tonne | H68: =IF(K$9=1,E68,IF(K$9=2,(E68+F68)/2,(E68+F68+G68)/3)) -> 2.0367461
A69: vi | B69: Electrical SEC of Hydrated Alumina | C69: Annual | D69: kWh/Tonne | H69: =IF(K$9=1,E69,IF(K$9=2,(E69+F69)/2,(E69+F69+G69)/3)) -> 0 | J69: 273.80135
A70: vii | B70: Running Hours | C70: Annual | D70: Hours | H70: =IF(K$9=1,E70,IF(K$9=2,(E70+F70)/2,(E70+F70+G70)/3)) -> 8602.3646
A72: b | B72: Digestion Process Parameter
A73: i | B73: Type of Digestion Technology | C73: Annual | D73: Single/Double
A74: ii | B74: Number of Digestion Units | C74: Annual | D74: No. | H74: =IF(K$9=1,E74,IF(K$9=2,(E74+F74)/2,(E74+F74+G74)/3)) -> 2
A75: iii | B75: Production Capacity of Digestion Units | C75: Annual | D75: Tonne | H75: =IF(K$9=1,E75,IF(K$9=2,(E75+F75)/2,(E75+F75+G75)/3)) -> 700000
A76: iv | B76: Specific Steam Consumption for Digestion | C76: Annual | D76: Tonne of Steam/ Tonne of Hydrate Alumina | H76: =IF(K$9=1,E76,IF(K$9=2,(E76+F76)/2,(E76+F76+G76)/3)) -> 1.3770575
A77: v | B77: Specific Power Consumption for Digestion | C77: Annual | D77: kWh/Tonne | H77: =IF(K$9=1,E77,IF(K$9=2,(E77+F77)/2,(E77+F77+G77)/3)) -> 24.753898
A78: vi | B78: Temperature of Low Temperature Digestion Units | C78: Annual | D78: Deg C | H78: =IF(K$9=1,E78,IF(K$9=2,(E78+F78)/2,(E78+F78+G78)/3)) -> 142.14017
A79: vii | B79: Pressure of Low Temperature Digestion Units | C79: Annual | D79: Kg/cm2 | H79: =IF(K$9=1,E79,IF(K$9=2,(E79+F79)/2,(E79+F79+G79)/3)) -> 4.2249875
A80: viii | B80: Temperature of High Temperature Digestion Units | C80: Annual | D80: oC | H80: =IF(K$9=1,E80,IF(K$9=2,(E80+F80)/2,(E80+F80+G80)/3)) -> 241.17296
A81: ix | B81: Pressure of High Temperature Digestion Units | C81: Annual | D81: Kg/cm2 | H81: =IF(K$9=1,E81,IF(K$9=2,(E81+F81)/2,(E81+F81+G81)/3)) -> 34.767
A82: x | B82: LP Steam Temperature | C82: Annual | D82: oC | H82: =IF(K$9=1,E82,IF(K$9=2,(E82+F82)/2,(E82+F82+G82)/3)) -> 301.09109
A83: xi | B83: LP steam Pressure | C83: Annual | D83: Kg/cm2 | H83: =IF(K$9=1,E83,IF(K$9=2,(E83+F83)/2,(E83+F83+G83)/3)) -> 5.6995671
A84: xii | B84: LP Steam Enthalpy | C84: Annual | D84: kcal/kg | H84: =IF(K$9=1,E84,IF(K$9=2,(E84+F84)/2,(E84+F84+G84)/3)) -> 732.06341
A85: xiii | B85: LP Steam Consumption | C85: Annual | D85: Tonne | H85: =IF(K$9=1,E85,IF(K$9=2,(E85+F85)/2,(E85+F85+G85)/3)) -> 867227.45
... A95: xxiii | B95: Specific Power Consumption for Evaporation | C95: Annual | D95: kWh/Tonne of hydrate Alumina | H95: =IF(K$9=1,E95,IF(K$9=2,(E95+F95)/2,(E95+F95+G95)/3)) -> 24.571024
A96: xxiv | B96: Weighted average of Enthalpy | C96: Annual | D96: kcal/kg | E96: =IFERROR((E93*E92+E89*E88+E85*E84)/(E93+E89+E85),0) -> 747.01439 | F96: =IFERROR((F93*F92+F89*F88+F85*F84)/(F93+F89+F85),0) -> 0 | G96: =IFERROR((G93*G92+G89*G88+G85*G84)/(G93+G89+G85),0) -> 0 | H96: =IFERROR((H93*H92+H89*H88+H85*H84)/(H93+H89+H85),0) -> 747.01439 | I96: =IFERROR((I93*I92+I89*I88+I85*I84)/(I93+I89+I85),0) -> 0
A97: c | B97: Calcined Alumina
A98: i | B98: Opening stock of Calcined alumina (Integrated Process) | C98: Annual | D98: Tonne | H98: =IF(K$9=1,E98,IF(K$9=2,(E98+F98)/2,(E98+F98+G98)/3)) -> 44543.327
A99: ii | B99: Closing stock of Calcined alumina (Integrated Process) | C99: Annual | D99: Tonne | H99: =IF(K$9=1,E99,IF(K$9=2,(E99+F99)/2,(E99+F99+G99)/3)) -> 49464.495
A100: iii | B100: Type of Calciner Technology | C100: Annual | D100: Techonolgy | H100: =E100 -> Gas Suspension
A101: iv | B101: Calcination Temperature | C101: Annual | D101: Deg C | H101: =IF(K$9=1,E101,IF(K$9=2,(E101+F101)/2,(E101+F101+G101)/3)) -> 1051.1
A102: v | B102: Specific Power Consumption for calciner | C102: Annual | D102: kWh/T | H102: =IF(K$9=1,E102,IF(K$9=2,(E102+F102)/2,(E102+F102+G102)/3)) -> 34.426058
A103: vi | B103: Specific Thermal Consumption for calciner | C103: Annual | D103: kcal/T | H103: =IF(K$9=1,E103,IF(K$9=2,(E103+F103)/2,(E103+F103+G103)/3)) -> 746742.89
A104: vii | B104: Running Hours | C104: Annual | D104: Hours | H104: =IF(K$9=1,E104,IF(K$9=2,(E104+F104)/2,(E104+F104+G104)/3)) -> 8087.4757
A105: viii | B105: Calcined Alumina Exported (Integrated Process) | C105: Annual | D105: Tonne | H105: =IF(K$9=1,E105,IF(K$9=2,(E105+F105)/2,(E105+F105+G105)/3)) -> 0
A106: ix | B106: Calcined Alumina Imported (Intergated Process) | C106: Annual | D106: Tonne | H106: =IF(K$9=1,E106,IF(K$9=2,(E106+F106)/2,(E106+F106+G106)/3)) -> 244856.09
A107: x | B107: Specific Thermal Energy Consumption of Calcined Alumina (Up to) | C107: Annual | D107: Mkcal/Tonne | H107: =IF(K$9=1,E107,IF(K$9=2,(E107+F107)/2,(E107+F107+G107)/3)) -> 2.7985109
A108: xi | B108: Specific Electrical Energy Consumption of Calcined Alumina (Up to) | C108: Annual | D108: kwh/Tonne | H108: =IF(K$9=1,E108,IF(K$9=2,(E108+F108)/2,(E108+F108+G108)/3)) -> 0
A110: d | B110: Special Hydrate (Course)
A111: i | B111: Installed Capacity | C111: Annual | D111: Tonne | H111: =IF(K$9=1,E111,IF(K$9=2,(E111+F111)/2,(E111+F111+G111)/3)) -> 0
A112: ii | B112: Actual Production | C112: Annual | D112: Tonne | H112: =IF(K$9=1,E112,IF(K$9=2,(E112+F112)/2,(E112+F112+G112)/3)) -> 0
A113: iii | B113: Thermal SEC | C113: Annual | D113: Mkcal/Tonne | H113: =IF(K$9=1,E113,IF(K$9=2,(E113+F113)/2,(E113+F113+G113)/3)) -> 0
...

Sheet Annex CPP
A1: Form- Sa1 Captive Power Plant Details
A2: Name of the Unit | C2: ='Form Sa1'!C3:K3 -> HINDALCO INDUSTRIES LIMITED
A3: 1 | B3: OEM Curve / HBD data
A4: 1.a | B4: Units | C4: Design Capacity | D4: As Provided by Original Equipment Manaufacturer (OEM) | G4: Curve Equation/ (R2) | L4: Load Vs Heat Rate or HBD Curve (at 100% Load) | N4: Source of Data | Q4: Remarks
D5: Boiler Efficiency | E5: Turbine Heat Rate | F5: Unit Heat Rate * | G5: OEM Curve OR HBD data curve | I5: Constant 1 | J5: Constant 2 | K5: Constant 3 | L5: Turbine Heat Rate
C6: MW | D6: % | E6: kcal/kwh | F6: kcal/kwh | G6: y=ax2-bx+c | H6: R2 | I6: a | J6: b | K6: c | L6: kcal/kwh
A7: i | B7: Unit-1 | F7: =IFERROR(E7*100/D7,0) -> 2679.5181
A8: ii | B8: Unit-2 | F8: =IFERROR(E8*100/D8,0) -> 2679.5181
A9: iii. | B9: Unit-3 | F9: =IFERROR(E9*100/D9,0) -> 2544.5783
A10: iv. | B10: Unit-4 | F10: =IFERROR(E10*100/D10,0) -> 2544.5783
A11: v | B11: Unit-5 | F11: =IFERROR(E11*100/D11,0) -> 2547.3054
A12: vi | B12: Unit-6 | F12: =IFERROR(E12*100/D12,0) -> 2606.6066
A13: vii | B13: Unit-7 | F13: =IFERROR(E13*100/D13,0) -> 2606.6066
A14: viii | B14: Unit-8 | F14: =IFERROR(E14*100/D14,0) -> 2661.8619
A15: ix | B15: Unit-9 | F15: =IFERROR(E15*100/D15,0) -> 2572.5845
A16: x | B16: Unit-10 | F16: =IFERROR(E16*100/D16,0) -> 2572.5845
A17: 1.b | B17: Station Design Data Details *** | C17: =SUM(C7:C16) -> 829.58 | D17: =IF(SUM(C7:C16)=0,0,(D7*C7+D8*C8+D9*C9+D10*C10+D11*C11+D12*C12+D13*C13+D14*C14+D15*C15+D16*C16)/SUM(C7:C16)) -> 83.338702 | E17: =(E7*C7+E8*C8+E9*C9+E10*C10+E11*C11+E12*C12+E13*C13+E14*C14+E15*C15+E16*C16)/SUM(C7:C16) -> 2167.7201 | F17: =IFERROR((F7*C7+F8*C8+F9*C9+F10*C10+F11*C11+F12*C12+F13*C13+F14*C14+F15*C15+F16*C16)/SUM(C7:C16),0) -> 2601.1802
B18: *** Station Design Heat Rate = [(DGHR 1 x Capacity 1 + DGHR 2 x Capacity2 + -----------) / (Total Capacity of Station)]
B19: ** To be indicated only if OEM certified design or PG Test report is available and the same can be produced as documentry proof, whenever required. If gas/liquid fuel is used, the Design/PG value for gas/liquied fuel may be given separately.
B20: * Unit Heat Rate (kcal/kWh) = [ Turbine Heat Rate (kcal/kWh) / Boiler Efficiency (%) ]
A21: 2 | B21: Unit wise Operating Data Details
A22: 2.a | B22: Units | C22: ='NF - 5 Power Mix'!E4 -> Baseline/Previous Year 2023-24 | K22: ='NF - 5 Power Mix'!F4 -> Assesment year/ Current Year FY 2025-26 | S22: Source of Data
C23: Operating Load | E23: ULF | G23: Gross Generation | I23: Unit Gross Heat Rate # | K23: Operating Load | M23: ULF | O23: Gross Generation | Q23: Unit Gross Heat Rate #
C24: MW | E24: % | G24: Lakh Units | I24: kcal/kwh | K24: MW | M24: % | O24: Lakh Units | Q24: kcal/kwh
A25: i | B25: Unit-1
A26: ii | B26: Unit-2
A27: iii. | B27: Unit-3
A28: iv. | B28: Unit-4
A29: v | B29: Unit-5
A30: vi | B30: Unit-6
A31: vii | B31: Unit-7
A32: viii | B32: Unit-8
A33: ix | B33: Unit-9
A34: x | B34: Unit-10
A35: 2.b | B35: Station Operating Data Details ## | C35: =SUM(C25:D34) -> 755.397 | E35: =IFERROR((E25*G25+E26*G26+E27*G27+E28*G28+E29*G29+E30*G30+E31*G31+E32*G32+E33*G33+E34*G34)/G35,0) -> 0.91627028 | G35: =SUM(G25:H34) -> 66354.072 | I35: =IFERROR(((G25*I25+G26*I26+G27*I27+G28*I28+G29*I29+G30*I30+G31*I31+G32*I32+G33*I33+G34*I34)/G35),0) -> 2584 | K35: =SUM(K25:L34) -> 0 | M35: =IFERROR((M25*O25+M26*O26+M27*O27+M28*O28+M29*O29+M30*O30+M31*O31+M32*O32+M33*O33+M34*O34)/O35,0) -> 0 | O35: =SUM(O25:P34) -> 0 | Q35: =IFERROR((O25*Q25+O26*Q26+O27*Q27+O28*Q28+O29*Q29+O30*Q30+O31*Q31+O32*Q32+O33*Q33+O34*Q34)/O35,0) -> 0
A37: 2.c | B37: Station Auxillary Power Consumption
B38: # Unit Heat Rate (kcal/kWh) = [ Turbine Heat Rate (kcal/kWh) / Boiler Efficiency (%) ]
B39: ## Station Operating Gross Heat Rate = [(OGHR 1 x Generation 1 + OGHR 2 x Generation 2 + -----------) / (Total Generation of Station)]
A40: 3 | B40: Plant Load Factor Details
A41: 3.a | B41: Loss of PLF due to non-availability of fuel/schedule/backing down/any external factor/Unforeseen factors
A42: 3.a.1 | B42: Units | C42: =C22 -> Baseline/Previous Year 2023-24 | K42: =K22 -> Assesment year/ Current Year FY 2025-26
C43: Average Operating Load (MW) caused by low ULF due to Coal Unavailability @ | E43: Average Operating Load (MW) caused by low ULF due to Scheduling @ | G43: Average Operating Load (MW) caused by low ULF due to backing down@ | I43: Average Operating Load (MW) caused by low ULF due to any other external factor@ | K43: Average Operating Load (MW) caused by low ULF due to Coal Unavailability @ | M43: Average Operating Load (MW) caused by low ULF due to Scheduling @ | O43: Average Operating Load (MW) caused by low ULF due to backing down@ | Q43: Average Operating Load (MW) caused by low ULF due to any other extranal factor@ | S43: Source of Data
C44: MW | D44: Operating Hours | E44: MW | F44: Operating Hours | G44: MW | H44: Operating Hours | I44: MW | J44: Operating Hours | K44: MW | L44: Operating Hours | M44: MW | N44: Operating Hours | O44: MW | P44: Operating Hours | Q44: MW | R44: Operating Hours
A45: i | B45: Unit-1
A46: ii | B46: Unit-2
A47: iii. | B47: Unit-3
A48: iv. | B48: Unit-4
A49: v | B49: Unit-5
A50: vi | B50: Unit-6
A51: vii | B51: Unit-7
A52: viii | B52: Unit-8
A53: ix | B53: Unit-9
A54: x | B54: Unit-10
A55: 3.a.2 | B55: Total | C55: =SUM(C45:C54) -> 0 | D55: =(C45*D45+C46*D46+C47*D47+C48*D48+C49*D49+C50*D50+C51*D51+C52*D52+C53*D53+C54*D54)/C55 -> #DIV/0! | E55: =SUM(E45:E54) -> 0 | F55: =SUM(F45:F54) -> 0 | G55: =SUM(G45:G54) -> 0 | H55: =SUM(H45:H54) -> 0 | K55: =SUM(K45:K54) -> 0 | L55: =(K45*L45+K46*L46+K47*L47+K48*L48+K49*L49+K50*L50+K51*L51+K52*L52+K53*L53+K54*L54)/K55 -> #DIV/0! | M55: =SUM(M45:M54) -> 0 | N55: =SUM(N45:N54) -> 0 | O55: =SUM(O45:O54) -> 0 | P55: =SUM(P45:P54) -> 0
C56: @ External Factors:Non-Avaialability of fuel/schedule/backing down/any other external factor/Unforeseen factors
A57: 3.b | B57: Loss of PLF due to non-availability of fuel/schedule/backing down/any external factor/Unforeseen factors/Internal Factor
A58: 3.b.1 | B58: Units | C58: =C22 -> Baseline/Previous Year 2023-24 | K58: =K22 -> Assesment year/ Current Year FY 2025-26
C59: Capacity | D59: Forced Outage/ Unavailability | E59: Planned Maintenance Outage/ Planned Unavailability | F59: Unit Availability Factor | G59: Average Operating Load (MW) caused by low ULF due to Internal factor | H59: Operating hours | I59: Average Operating Load (MW) caused by low ULF due to external factor @ | J59: Average Operating hours at Low ULF | K59: Capacity | L59: Forced Outage/ Unavailability | M59: Planned Maintenance Outage/Planned Unavailability | N59: Unit Avaialability Factor | O59: Average Operating Load (MW) caused by low ULF due to Internal factor | P59: Operating hours | Q59: Average Operating Load (MW) caused by low ULF due to external factor @ | R59: Average Operating hours at Low ULF | S59: Source of Data
C60: MW | D60: Hrs | E60: Hrs | G60: MW | H60: Hrs/annum | I60: MW | J60: Hrs/annum | K60: MW | L60: Hrs | M60: Hrs | O60: MW | P60: Hrs/annum | Q60: MW | R60: Hrs/annum
A61: i | B61: Unit-1 | C61: =C7 -> 81.75 | F61: =(8760-(D61+E61))/8760 -> 1 | I61: =IFERROR((C45*D45+E45*F45+G45*H45+I45*J45)/(D45+F45+H45+J45),0) -> 4.2770893 | J61: =D45+F45+H45+J45 -> 459.57128 | K61: =C61 -> 81.75 | N61: =(8760-(L61+M61))/8760 -> 1 | Q61: =IFERROR((K45*L45+M45*N45+O45*P45+Q45*R45)/(L45+N45+P45+R45),0) -> 0 | R61: =L45+N45+P45+R45 -> 0
A62: ii | B62: Unit-2 | C62: =C8 -> 81.75 | F62: =(8760-(D62+E62))/8760 -> 0.95121955 | I62: =IFERROR((C46*D46+E46*F46+G46*H46+I46*J46)/(D46+F46+H46+J46),0) -> 4.6274672 | J62: =D46+F46+H46+J46 -> 497.21923 | K62: =C62 -> 81.75 | N62: =(8760-(L62+M62))/8760 -> 1 | Q62: =IFERROR((K46*L46+M46*N46+O46*P46+Q46*R46)/(L46+N46+P46+R46),0) -> 0 | R62: =L46+N46+P46+R46 -> 0
A63: iii. | B63: Unit-3 | C63: =C9 -> 84 | F63: =(8760-(D63+E63))/8760 -> 0.95711094 | I63: =IFERROR((C47*D47+E47*F47+G47*H47+I47*J47)/(D47+F47+H47+J47),0) -> 2.6366011 | J63: =D47+F47+H47+J47 -> 275.71314 | K63: =C63 -> 84 | N63: =(8760-(L63+M63))/8760 -> 1 | Q63: =IFERROR((K47*L47+M47*N47+O47*P47+Q47*R47)/(L47+N47+P47+R47),0) -> 0 | R63: =L47+N47+P47+R47 -> 0
A64: iv. | B64: Unit-4 | C64: =C10 -> 84 | F64: =(8760-(D64+E64))/8760 -> 0.9924697 | I64: =IFERROR((C48*D48+E48*F48+G48*H48+I48*J48)/(D48+F48+H48+J48),0) -> 0.58774226 | J64: =D48+F48+H48+J48 -> 61.461048 | K64: =C64 -> 84 | N64: =(8760-(L64+M64))/8760 -> 1 | Q64: =IFERROR((K48*L48+M48*N48+O48*P48+Q48*R48)/(L48+N48+P48+R48),0) -> 0 | R64: =L48+N48+P48+R48 -> 0
A65: v | B65: Unit-5 | C65: =C11 -> 76 | F65: =(8760-(D65+E65))/8760 -> 0.95444054 | I65: =IFERROR((C49*D49+E49*F49+G49*H49+I49*J49)/(D49+F49+H49+J49),0) -> 1.5714809 | J65: =D49+F49+H49+J49 -> 181.63011 | K65: =C65 -> 76 | N65: =(8760-(L65+M65))/8760 -> 1 | Q65: =IFERROR((K49*L49+M49*N49+O49*P49+Q49*R49)/(L49+N49+P49+R49),0) -> 0 | R65: =L49+N49+P49+R49 -> 0
A66: vi | B66: Unit-6 | C66: =C12 -> 84 | F66: =(8760-(D66+E66))/8760 -> 0.8109815 | I66: =IFERROR((C50*D50+E50*F50+G50*H50+I50*J50)/(D50+F50+H50+J50),0) -> 2.0307778 | J66: =D50+F50+H50+J50 -> 212.36133 | K66: =C66 -> 84 | N66: =(8760-(L66+M66))/8760 -> 1 | Q66: =IFERROR((K50*L50+M50*N50+O50*P50+Q50*R50)/(L50+N50+P50+R50),0) -> 0 | R66: =L50+N50+P50+R50 -> 0
A67: vii | B67: Unit-7 | C67: =C13 -> 84 | F67: =(8760-(D67+E67))/8760 -> 0.97741891 | I67: =IFERROR((C51*D51+E51*F51+G51*H51+I51*J51)/(D51+F51+H51+J51),0) -> 3.4915346 | J67: =D51+F51+H51+J51 -> 365.11476 | K67: =C67 -> 84 | N67: =(8760-(L67+M67))/8760 -> 1 | Q67: =IFERROR((K51*L51+M51*N51+O51*P51+Q51*R51)/(L51+N51+P51+R51),0) -> 0 | R67: =L51+N51+P51+R51 -> 0
A68: viii | B68: Unit-8 | C68: =C14 -> 80.08 | F68: =(8760-(D68+E68))/8760 -> 0.99120791 | I68: =IFERROR((C52*D52+E52*F52+G52*H52+I52*J52)/(D52+F52+H52+J52),0) -> 0.43350273 | J68: =D52+F52+H52+J52 -> 47.551049 | K68: =C68 -> 80.08 | N68: =(8760-(L68+M68))/8760 -> 1 | Q68: =IFERROR((K52*L52+M52*N52+O52*P52+Q52*R52)/(L52+N52+P52+R52),0) -> 0 | R68: =L52+N52+P52+R52 -> 0
A69: ix | B69: Unit-9 | C69: =C15 -> 87 | F69: =(8760-(D69+E69))/8760 -> 0.95790899 | I69: =IFERROR((C53*D53+E53*F53+G53*H53+I53*J53)/(D53+F53+H53+J53),0) -> 0.82753552 | J69: =D53+F53+H53+J53 -> 83.552552 | K69: =C69 -> 87 | N69: =(8760-(L69+M69))/8760 -> 1 | Q69: =IFERROR((K53*L53+M53*N53+O53*P53+Q53*R53)/(L53+N53+P53+R53),0) -> 0 | R69: =L53+N53+P53+R53 -> 0
A70: x | B70: Unit-10 | C70: =C16 -> 87 | F70: =(8760-(D70+E70))/8760 -> 0.9749599 | I70: =IFERROR((C54*D54+E54*F54+G54*H54+I54*J54)/(D54+F54+H54+J54),0) -> 17.706063 | J70: =D54+F54+H54+J54 -> 1787.7018 | K70: =C70 -> 87 | N70: =(8760-(L70+M70))/8760 -> 1 | Q70: =IFERROR((K54*L54+M54*N54+O54*P54+Q54*R54)/(L54+N54+P54+R54),0) -> 0 | R70: =L54+N54+P54+R54 -> 0
A71: 3.b.2 | B71: Total | C71: =SUM(C61:C70) -> 829.58 | D71: =(C61*D61+C62*D62+C63*D63+C64*D64+C65*D65+C66*D66+C67*D67+C68*D68+C69*D69+C70*D70)/(C71*8760) -> 0.0051022782 | E71: =(E61*C61+E62*C62+E63*C63+E64*C64+E65*C65+E66*C66+E67*C67+E68*C68+E69*C69+E70*C70)/(C71*8760) -> 0.038298467 | F71: =1-D71-E71 -> 0.95659926 | G71: =SUM(G61:G70) -> 0.45331694 | H71: =(G61*H61+G62*H62+G63*H63+G64*H64+G65*H65+G66*H66+G67*H67+G68*H68+G69*H69+G70*H70)/SUM(G61:G70) -> 7.8633883 | I71: =SUM(I61:I70) -> 38.189794 | J71: =(I61*J61+I62*J62+I63*J63+I64*J64+I65*J65+I66*J66+I67*J67+I68*J68+I69*J69+I70*J70)/I71 -> 1015.035 | K71: =SUM(K61:K70) -> 829.58 | L71: =(K61*L61+K62*L62+K63*L63+K64*L64+K65*L65+K66*L66+K67*L67+K68*L68+K69*L69+K70*L70)/(K71*8760) -> 0 | M71: =(M61*K61+M62*K62+M63*K63+M64*K64+M65*K65+M66*K66+M67*K67+M68*K68+M69*K69+M70*K70)/(K71*8760) -> 0 | N71: =1-L71-M71 -> 1 | O71: =SUM(O61:O70) -> 0 | P71: =(O61*P61+O62*P62+O63*P63+O64*P64+O65*P65+O66*P66+O67*P67+O68*P68+O69*P69+O70*P70)/SUM(O61:O70) -> #DIV/0! | Q71: =SUM(Q61:Q70) -> 0 | R71: =(Q61*R61+Q62*R62+Q63*R63+Q64*R64+Q65*R65+Q66*R66+Q67*R67+Q68*R68+Q69*R69+Q70*R70)/SUM(Q61:Q70) -> #DIV/0!
B72: @ External Factors:Non-Avaialability of fuel/schedule/backing down/any other external factor
B73: Documents Required
B74: i. Characteristics Curve of Unit Turbine Heat Rate Vs Load, from Original Equipment Manaufacturer (OEM)
B75: ii. Unit wise HBD or Curve from Original Equipment Manufacturer (OEM) at various loads
B76: iii. In case of non-availability of HBD or Curve, data from the similar Unit will be considered
B77: iv. Design/PG Test Turbine Heat Rate documents
A78: 4 | B78: Unitwise Fuel Analysis Details (As Fired Basis)@
A79: 4.a | B79: Unit | C79: Capacity | D79: =C22 -> Baseline/Previous Year 2023-24 | K79: =K22 -> Assesment year/ Current Year FY 2025-26
D80: Volatile Matter | E80: Total Moisture | F80: Ash | G80: GCV | H80: Hydrogen | I80: Sulphur | J80: Nitrogen | K80: Volatile Matter | L80: Total Moisture | M80: Ash | N80: GCV | O80: Hydrogen | P80: Sulphur | Q80: Nitrogen | R80: Source of Data | S80: Remarks
C81: MW | D81: % | E81: % | F81: % | G81: kcal/kg | H81: % | I81: % | J81: % | K81: % | L81: % | M81: % | N81: kcal/kg | O81: % | P81: % | Q81: %
A82: i | B82: Unit-1 | C82: =C7 -> 81.75
A83: ii | B83: Unit-2 | C83: =C8 -> 81.75
A84: iii. | B84: Unit-3 | C84: =C9 -> 84
A85: iv. | B85: Unit-4 | C85: =C10 -> 84
A86: v | B86: Unit-5 | C86: =C11 -> 76
A87: vi | B87: Unit-6 | C87: =C12 -> 84
A88: vii | B88: Unit-7 | C88: =C13 -> 84
A89: viii | B89: Unit-8 | C89: =C14 -> 80.08
A90: ix | B90: Unit-9 | C90: =C15 -> 87
A91: x | B91: Unit-10 | C91: =C16 -> 87
B93: Note: If Ultimate Analysis value is not available with DCs, Conversion from Proximate to Ultimate will be applied conversion farmula. %C = 0.97C+ 0.7(VM+0.1A) - M(0.6-0.01M) %H2= 0.036C + 0.086 (VM -0.1xA) - 0.0035M2(1-0.02M) %N2= 2.10 -0.020 VM Where: C= % of fixed carbon , A= % of ash ,VM= % of volatile matter, M= % of moisture
B94: In case of differnce in Design Coal Quality for differnent units, Coal analysis to be given unit wise
B95: @ Attach all necessary Documents -
B96: A. Coal Analysis:
B97: i. Operating Coal Quality- Monthly average of the lots (As Fired Basis),Test Certificate for Coal Analysis including Proximate and Ultimate analysis (Minimum of 4 Samples Test from Government Lab for cross verification- Quarterly)
B98: ii. Performance Guarantee Test (PG Test) report from Original Equipment Manufacturer (OEM)
B99: iii. Design Coal Analysis Document as per OEM
B100: B. Boiler Efficiency
B101: i. Design Boiler Efficiency Document from Original Equipment Manufacturer (OEM)
B102: @@ For Weighted Average for the year, the sum of the tested coal of each lot as fired multiplied with the quantity of each lot , to be devided by the total fuel quantity during the year.

Sheet  Summary Sheet
A1: Form-Sa1 (Summary Sheet )
A2: Sector: Aluminum Sector
B3: Sub-Sector | C3: ='General Information'!G4 -> INTEGRATED
A4: S. No | B4: Particulars | C4: Basis/Formula | D4: Unit | E4: ='Form Sa1'!H8 -> Baseline Year(s) | F4: Current/Target Year
E5: ='Form Sa1'!H9 -> 2023-24 | F5: ='Form Sa1'!I9 -> 2025-26
B6: Details of Production
A7: A1 | B7: Refinery
A8: A1.1 | B8: Production and Capacity Utilization
A9: i | B9: Total Hydrate Aluminia Production | C9: Baseline Parameter'! (A1 (i) ) | D9: Tonne | E9: ='Baseline Parameter'!E8 -> 565600 | F9: ='Baseline Parameter'!F8 -> 0
A10: ii | B10: Total Calcined Alumina Production | C10: Baseline Parameter'! (A1 (ii) ) | D10: Tonne | E10: ='Baseline Parameter'!E9 -> 561459 | F10: ='Baseline Parameter'!F9 -> 0
A11: iii | B11: Capacity Utilization (Hydrate Alumina) | C11: Form Sa1'! {A1(v)} | D11: % | E11: ='Form Sa1'!H48 -> 80.8 | F11: ='Form Sa1'!I48 -> 0
A12: iv | B12: Capacity Utilization (Calcined Alumina) | C12: Form Sa1'! {A1(vi)} | D12: % | E12: ='Form Sa1'!H49 -> 81.946873 | F12: ='Form Sa1'!I49 -> 0
A13: A1.2 | B13: Hydrate Alumina (Intermediary product for Reinery)
A14: i | B14: Hydrate Alumina Opening Stock | C14: Form Sa1'! {A3.1.a.(iii)} | D14: Tonne | E14: ='Form Sa1'!H66 -> 30580.066 | F14: ='Form Sa1'!I66 -> 0
A15: ii | B15: Hydrate Alumina Closing stock | C15: Form Sa1'! {A3.1.a.(iv)} | D15: Tonne | E15: ='Form Sa1'!H67 -> 34626.579 | F15: ='Form Sa1'!I67 -> 0
A16: iii | B16: Hydrate Alumina Stock | C16: A1.2 (ii)-A1.2(i) | D16: Tonne | E16: =E15-E14 -> 4046.513 | F16: =F15-F14 -> 0
A17: iv | B17: Hydrate Alumina Exported | C17: Baseline Parameter'!{A1.1.(xii)} | D17: Tonne | E17: ='Baseline Parameter'!E25 -> 0 | F17: ='Baseline Parameter'!F25 -> 0
A18: v | B18: Hydrate Alumina Imported | C18: Baseline Parameter'!{A1.1.(xiii)} | D18: Tonne | E18: ='Baseline Parameter'!E26 -> 0 | F18: ='Baseline Parameter'!F26 -> 0
A19: vi | B19: Total Hydrate Aluminia Export | C19: A1.2(iv)+A1.2(iii) | D19: Tonne | E19: =IF(E16>0, (E17+E16), (E17)) -> 4046.513 | F19: =IF(F16>0, (F17+F16), (F17)) -> 0
A20: vii | B20: Total Hydrate Aluminia Import | C20: A1.2(v)-A1.2(iii) | D20: Tonne | E20: =IF(E16<0,E18-E16, (E18)) -> 0 | F20: =IF(F16<0,F18-F16, (F18)) -> 0 | G20: =IF(G16<0,G18-G16, (G18)) -> 0 | H20: =IF(H16<0,H18-H16, (H18)) -> 0 | I20: =IF(I16<0,I18-I16, (I18)) -> 0 | J20: =IF(J16<0,J18-J16, (J18)) -> 0 | K20: =IF(K16<0,K18-K16, (K18)) -> 0 | L20: =IF(L16<0,L18-L16, (L18)) -> 0 | ... IU20: =IF(IU16<0,IU18-IU16, (IU18)) -> 0
A21: A1.3 | B21: Calicined Alumina (Intermediary Product for Integrated Process)
A22: i | B22: Calcined Alumina opening stock (Integrated Process) | C22: Form Sa1'! {c(i)} | D22: Tonne | E22: ='Form Sa1'!H98 -> 44543.327 | F22: ='Form Sa1'!I98 -> 0
A23: ii | B23: Calcined Alumina Closing stock (Integrated Process) | C23: Form Sa1'! {c(ii)} | D23: Tonne | E23: ='Form Sa1'!H99 -> 49464.495 | F23: ='Form Sa1'!I99 -> 0
A24: iii | B24: Calcined Alumina Stock (Integrated Process) | C24: A1.3 (ii)-A1.3(i) | D24: Tonne | E24: =E23-E22 -> 4921.168 | F24: =F23-F22 -> 0
A25: iv | B25: Calcined Alumina Exported (Integrated Process) | C25: Baseline Parameter'! {A1.1.(xiv)} | D25: Tonne | E25: ='Baseline Parameter'!E27 -> 0 | F25: ='Baseline Parameter'!F27 -> 0
A26: v | B26: Calcined Alumina Imported (Intergated Process) | C26: Baseline Parameter'! {A1.1.(xv)} | D26: Tonne | E26: ='Baseline Parameter'!E28 -> 244856.09 | F26: ='Baseline Parameter'!F28 -> 0
A27: vi | B27: Total Calcined Alumina Export (Integrated Process) | C27: A1.3(iv)+A1.3(iii) | D27: Tonne | E27: =IF(E24>0, (E25+E24), (E25)) -> 4921.168 | F27: =IF(F24>0, (F25+F24), (F25)) -> 0
A28: vii | B28: Total Calcined Alumina Import (Intergated Process) | C28: A1.3(v)-A1.3(iii) | D28: Tonne | E28: =IF(E24<0, E26-E24, (E26)) -> 244856.09 | F28: =IF(F24<0, F26-F24, (F26)) -> 0
A30: A2 | B30: Smelter Process
A31: A2.1 | B31: Production and Capacity Utilization
A32: i | B32: Total Molten Aluminium Production | C32: Baseline Parameter'! {A2(i)} | D32: Tonne | E32: ='Baseline Parameter'!E31 -> 410661.74 | F32: ='Baseline Parameter'!F31 -> 0
A33: ii | B33: Total Cast House Production | C33: Baseline Parameter'! {A2(ii)} | D33: Tonne | E33: ='Baseline Parameter'!E32 -> 381860.33 | F33: ='Baseline Parameter'!F32 -> 0
A34: iii | B34: Capacity Utilization (Molten Aluminum) | C34: Form Sa1'! {A2 (v)} | D34: % | E34: ='Form Sa1'!H58 -> 119.03239 | F34: ='Form Sa1'!I58 -> 0
A35: iv | B35: Capacity Utilization (Cast House) | C35: Form Sa1'! {A2 (vi)} | D35: % | E35: ='Form Sa1'!H59 -> 137.21176 | F35: ='Form Sa1'!I59 -> 0
B37: Details of Energy Consumption
A38: B | B38: Total Thermal Energy Consumption | C38: [Fuel Consumed (Lakh Tonnene) X GCV of Fuel (Kcal/Kg)] X 100 - 'Baseline Parameter'! (H) | D38: Million kcal | E38: ='Baseline Parameter'!E124 -> 20584768 | F38: ='Baseline Parameter'!F124 -> 0
A39: C | B39: Total Electricity consumed within the plant | C39: {(Electricity Generated through CPP+Electricity generation through DG Set + Electricity generation through WHR+ Electricity Purchased from Grid) - Electricity exported to Grid} -'Baseline Parameter'!(F4) | D39: Lakh kWh | E39: ='NF - 5 Power Mix'!E24 -> 70274.185 | F39: ='NF - 5 Power Mix'!F24 -> 0
A40: D | B40: Electricity Purchased from Grid | C40: Average of year 2007-08, 2008-09 and 2009-10 -'Baseline Parameter'!(D 1 (i)) | D40: Lakh kWh | E40: ='NF - 5 Power Mix'!E6 -> 1144.79 | F40: ='NF - 5 Power Mix'!F6 -> 0
A41: E | B41: Electricity Exported to Grid/Colony/Others from CPP | C41: Average of year 2007-08, 2008-09 and 2009-10 -'Baseline Parameter'! (F2) | D41: Lakh kWh | E41: ='Form Sa1'!H841+'Form Sa1'!H842 -> 1782.6538 | F41: ='Form Sa1'!I841+'Form Sa1'!I842 -> 0
A42: F | B42: Total Energy Consumed (Thermal+Electrical) | C42: [Total Thermal Energy (Million kcal)+{(Total Electricity purchased from grid (Lakh kWh) X 860)-Electricity exported (Lakh kWh) X weighted generation net heat reate- 'NF-5 Power mix'!E33 kcal/kWh}/10] ----[(B)+{(D)*860/10}-{(E)*2717/10}] | D42: Million kcal | E42: =E38+((E40+'NF - 5 Power Mix'!E14+'NF - 5 Power Mix'!E15)*860/10)+((('Form Sa1'!H835)*860)/10)+('Form Sa1'!H814*'Form Sa1'!H816/10)-'NF - 5 Power Mix'!E21-'NF - 5 Power Mix'!E22 -> 20189374 | F42: =F38+((F40+'NF - 5 Power Mix'!F14+'NF - 5 Power Mix'!F15)*860/10)+((('Form Sa1'!I835)*860)/10)+('Form Sa1'!I814*'Form Sa1'!I816/10)-'NF - 5 Power Mix'!F21-'NF - 5 Power Mix'!F22 -> #DIV/0! | G42: =G38+((G40+'NF - 5 Power Mix'!G14+'NF - 5 Power Mix'!G15)*860/10)+((('Form Sa1'!J835)*860)/10)+('Form Sa1'!J814*'Form Sa1'!J816/10)-'NF - 5 Power Mix'!G21-'NF - 5 Power Mix'!G22 -> 0 | H42: =H38+((H40+'NF - 5 Power Mix'!H14+'NF - 5 Power Mix'!H15)*860/10)+((('Form Sa1'!K835)*860)/10)+('Form Sa1'!K814*'Form Sa1'!K816/10)-'NF - 5 Power Mix'!H21-'NF - 5 Power Mix'!H22 -> 0 | I42: =I38+((I40+'NF - 5 Power Mix'!I14+'NF - 5 Power Mix'!I15)*860/10)+((('Form Sa1'!L835)*860)/10)+('Form Sa1'!L814*'Form Sa1'!L816/10)-'NF - 5 Power Mix'!I21-'NF - 5 Power Mix'!I22 -> 0 | J42: =J38+((J40+'NF - 5 Power Mix'!J14+'NF - 5 Power Mix'!J15)*860/10)+((('Form Sa1'!M835)*860)/10)+('Form Sa1'!M814*'Form Sa1'!M816/10)-'NF - 5 Power Mix'!J21-'NF - 5 Power Mix'!J22 -> 0 | K42: =K38+((K40+'NF - 5 Power Mix'!K14+'NF - 5 Power Mix'!K15)*860/10)+((('Form Sa1'!N835)*860)/10)+('Form Sa1'!N814*'Form Sa1'!N816/10)-'NF - 5 Power Mix'!K21-'NF - 5 Power Mix'!K22 -> 0 | L42: =L38+((L40+'NF - 5 Power Mix'!L14+'NF - 5 Power Mix'!L15)*860/10)+((('Form Sa1'!O835)*860)/10)+('Form Sa1'!O814*'Form Sa1'!O816/10)-'NF - 5 Power Mix'!L21-'NF - 5 Power Mix'!L22 -> 0 | ... XFA42: =XFA38+((XFA40+'NF - 5 Power Mix'!XFA14+'NF - 5 Power Mix'!XFA15)*860/10)+((('Form Sa1'!XFD835)*860)/10)+('Form Sa1'!XFD814*'Form Sa1'!XFD816/10)-'NF - 5 Power Mix'!XFA21-'NF - 5 Power Mix'!XFA22 -> 0 | XFB42: =XFB38+((XFB40+'NF - 5 Power Mix'!XFB14+'NF - 5 Power Mix'!XFB15)*860/10)+((('Form Sa1'!#REF!)*860)/10)+('Form Sa1'!#REF!*'Form Sa1'!#REF!/10)-'NF - 5 Power Mix'!XFB21-'NF - 5 Power Mix'!XFB22 -> #REF! | XFC42: =XFC38+((XFC40+'NF - 5 Power Mix'!XFC14+'NF - 5 Power Mix'!XFC15)*860/10)+((('Form Sa1'!#REF!)*860)/10)+('Form Sa1'!#REF!*'Form Sa1'!#REF!/10)-'NF - 5 Power Mix'!XFC21-'NF - 5 Power Mix'!XFC22 -> #REF!
A44: G | B44: Gate to Gate Specific Energy Consumption
A45: G.1 | B45: Refinery Process
A46: i | B46: Total Equivalent Calcined Alumina Production | C46: A.10(iii)*A.10(i)+A.6(i) - 'Baseline Parameter'!(C1(i)) | D46: Tonne | E46: ='Baseline Parameter'!E70 -> 561459 | F46: ='Baseline Parameter'!F70 -> 0
A47: ii | B47: Notional Energy exported Hydrate Alumina | C47: Total hydrate Alumina Exported * SEC of Hydrate Alumina -[(A1(viii))*'Baseline Parameter'!B1 (ii)] | D47: Million kcal | E47: =E19*'Baseline Parameter'!E44 -> 8241.7197 | F47: =F19*'Baseline Parameter'!F44 -> #DIV/0!
A48: iii | B48: Notional Energy Imported Hydrate Alumina | C48: Total hydrate Alumina Imported * SEC of Hydrate Alumina - [(A1(ix))*'Baseline Parameter'!B1 (ii)] | D48: Million kcal | E48: =E20*'Baseline Parameter'!E44 -> 0 | F48: =F20*'Baseline Parameter'!F44 -> #DIV/0!
A49: iv | B49: Total Energy Consumed by By-Products | C49: Baseline Parameter'!(b1.1(i))+'Baseline Parameter'!(B1.1.(ii))+'Baseline Parameter'! (B1.1.(iii))+'Baseline Parameter'!(B1.1.(iv)) | D49: Million kcal | E49: ='Baseline Parameter'!E52+'Baseline Parameter'!E53+'Baseline Parameter'!E54+'Baseline Parameter'!E55 -> 0 | F49: ='Baseline Parameter'!F52+'Baseline Parameter'!F53+'Baseline Parameter'!F54+'Baseline Parameter'!F55 -> #DIV/0!
A50: v | B50: Total Notional Energy Consumed | C50: {(F)/10}-{G1(ii)/10}+{G1(iii)/10}-{G1(iv)/10} | D50: TOE | E50: =(E42/10)-(E47/10)+(E48/10)-(E49/10) -> 2018113.2 | F50: =(F42/10)-(F47/10)+(F48/10)-(F49/10) -> #DIV/0!
A51: v | B51: Gate to Gate SEC of Equivalent Calcined Alumina | C51: Total Energy Consumed / Total Equivalent Calcined Alumina Production -[(G1 (v)) / (G1(i))] | D51: TOE/Tonne | E51: =IF('General Information'!C4="REFINERY",(IFERROR(E50/E46,0)),"Not Applicable") -> Not Applicable | F51: =IF('General Information'!C4="REFINERY",(IFERROR(F50/F46,0)),"Not Applicable") -> Not Applicable
A53: G.2 | B53: Smelter Process
A54: i | B54: Total Equivalent Molten Aluminum Produced | C54: A10(i+ii+iii+iv+v+vi+vii)+ A8(i) - 'Baseline Parameter'!(c2(i)) | D54: Tonne | E54: ='Baseline Parameter'!E73 -> 423396.46 | F54: ='Baseline Parameter'!F73 -> 0
A55: ii | B55: Notional Energy Exported Calcined Alumina (Integrated Process) | C55: Total Calcined Alumina Exported * SEC of Calcined Alumina (A1(xv) *Baseline Parameter'!(B1.(i)) | D55: Million kcal | E55: =E27*'Baseline Parameter'!E43 -> 13771.942 | F55: =F27*'Baseline Parameter'!F43 -> #DIV/0!
A56: iii | B56: Notional Energy Imported Calcined Alumina (Integrated Process) | C56: Total Calcined Alumina Imported * SEC of Calcined Alumina (A1(xvi) *Baseline Parameter'!(B1.(i)) | D56: Million kcal | E56: =E28*'Baseline Parameter'!E43 -> 685232.43 | F56: =F28*'Baseline Parameter'!F43 -> #DIV/0!
A57: iv | B57: Total Notional Energy Consumed | C57: [(F)-{G2(ii)}+{(G2 (iii)}] | D57: TOE | E57: =(E42/10)-(E55/10)+(E56/10) -> 2086083.4 | F57: =(F42/10)-(F55/10)+(F56/10) -> #DIV/0!
A58: v | B58: Gate to Gate SEC of Equivalent Molten Aluminum | C58: Total Energy Consumed / Total Equivalent Molten Aluminum Production | D58: TOE/Tonne | E58: =IF(OR('General Information'!C4="SMELTER", 'General Information'!C4="INTEGRATED"),(IFERROR((E57/E54),0)),"Not Applicable") -> 4.9270214 | F58: =IF(OR('General Information'!C4="SMELTER", 'General Information'!C4="INTEGRATED"),(IFERROR((F57/F54),0)),"Not Applicable") -> 0
A59: H | B59: Normalization Factors | C59: Unit | E59: Baseline Year | F59: Assessment Year
A60: i | B60: Notional Energy for Bauxite Quality | C60: NF-1 Bauxite quality calculation sheet - 'N1-BQ Bauxite Quality'!(18)/10 | D60: TOE | F60: ='N1-BQ Bauxite Quality'!F23/10 -> 0
A61: ii | B61: Notional Energy for fuel quality in CPP & Co-Gen | C61: NF-2 Fuel Quality in CPP & Co-Gen Calculation Sheet-'NF - 2 Fuel Quality CPP & Cogen'!(16)/10 | D61: TOE | F61: ='NF - 2 Fuel Quality CPP & Cogen'!F47/10 -> 0
A62: iii | B62: Notional Energy for PLF in CPP | C62: NF-3 PLF Calculation Sheet-'NF - 3 PLF'!(20)/10 | D62: TOE | F62: ='NF - 3 PLF'!E25/10 -> 0
A63: iv | B63: Notional Energy for Power Mix | C63: NF-4 Power Mix Calculation Sheet-'NF - 5 Power Mix'!(33)/10 | D63: TOE | F63: ='NF - 5 Power Mix'!F69/10 -> 0
A64: v | B64: Notional Energy for Carbon Anode production | C64: NF-6 Carbon Anode Calculation sheet-'NF-6 Carbon Anode Production'!(14)/10 | D64: TOE | F64: ='NF-6 Carbon Anode Production'!F18/10 -> #DIV/0!
A65: vi | B65: Notional Energy for Smelter capacity utilization | C65: NF-7 Smelter Capacity Utilization Calculation Sheet-'NF-7 Smelter CU'!(16)/10 | D65: TOE | F65: ='NF-7 Smelter CU'!E22/10 -> #DIV/0!
A66: vii | B66: Notional Energy for other Factors | C66: NF-8 Others Normalisation-'NF-8 Others'!(21)/10 | D66: TOE | F66: ='NF-8 Others'!F30/10 -> #DIV/0!
A67: viii | B67: Gate to Gate Energy Consumption | C67: Annual | D67: TOE | E67: =IF(C3="Refinery",E50,E57) -> 2086083.4 | F67: =IF(C3="Refinery",F50-F60-F61-F62-F63-F65-F64-F66,F57-F60-F61-F62-F63-F65-F64-F66) -> #DIV/0!
A68: I | B68: Normalized Gate to Gate SEC | C68: IF('General Information'!(2)="REFINERY",(IFERROR{(H(viii))/(G.1(i))},0)),IFERROR({(H(viii))/(G2(i))},0)) | D68: TOE/Tonne | E68: =IF('General Information'!C4="REFINERY",(IFERROR((E67/E46),0)),IFERROR((E67/E54),0)) -> 4.9270214 | F68: =IF('General Information'!C4="REFINERY",(IFERROR((F67/F46),0)),IFERROR((F67/F54),0)) -> 0
A69: J | B69: Notified Specific Energy Consumption | D69: TOE/Tonne | E69: ='Form Sa1'!H712 -> 0
A70: K | B70: Baseline Normalisation | D70: TOE/Tonne | E70: =E68-E69 -> 4.9270214
A71: L | B71: Renewable Energy Certificates Compliance under PAT Scheme | C71: NF-8 Others'!(29) | D71: TOE | F71: ='NF-8 Others'!F39 -> 0
A72: i | B72: Gate to Gate Energy Consumption after REC compliance | C72: (J )+(H(viii)AY | D72: TOE | F72: =(F71+F67) -> #DIV/0!
A73: M | B73: Normalized Gate to Gate Specific Energy Consumption of Calcined Alumina after REC compliance | C73: Annual | D73: TOE/Tonne | F73: =IFERROR(IF(C3="Refinery",((F72/F46)-E70),((F72/F54)-E70)),0) -> 0
A75: 13 | B75: Power Source Analysis
A76: 13.1 | B76: Generation & Electricity Imports
A77: a | B77: Electricity imported from Grid | C77: Form Sa1'!B1(i) | D77: Lakh kWh | E77: ='Form Sa1'!H693 -> 1144.79 | F77: ='Form Sa1'!I693 -> 0
A78: b | B78: Electricity generated from DG | C78: NF - 5 Power Mix'!{1.b} | D78: Lakh kWh | E78: ='NF - 5 Power Mix'!E7 -> 0 | F78: ='NF - 5 Power Mix'!F7 -> 0
A79: c | B79: Electricity generated from Steam Turbine | C79: NF - 5 Power Mix'!{1.c} | D79: Lakh kWh | E79: ='NF - 5 Power Mix'!E8 -> 66354.072 | F79: ='NF - 5 Power Mix'!F8 -> 0
A80: d | B80: Electricity generated from Gas Turbine | C80: NF - 5 Power Mix'!{1.d} | D80: Lakh kWh | E80: ='NF - 5 Power Mix'!E9 -> 0 | F80: ='NF - 5 Power Mix'!F9 -> 0
A81: e | B81: Electricity generated from Co-Gen (Extraction/back pressure ) | C81: NF - 5 Power Mix'!{1.e} | D81: Lakh kWh | E81: ='NF - 5 Power Mix'!E10 -> 779.51468 | F81: ='NF - 5 Power Mix'!F10 -> 0
A82: f | B82: Electricity generated from Co-Gen(Extraction cum condensing) | C82: NF - 5 Power Mix'!{1.f} | D82: Lakh kWh | E82: ='NF - 5 Power Mix'!E11 -> 3739.3381 | F82: ='NF - 5 Power Mix'!F11 -> 0
A83: g | B83: Electricity generated from WHR | C83: NF - 5 Power Mix'!{1.g} | D83: Lakh kWh | E83: ='NF - 5 Power Mix'!E12 -> 0 | F83: ='NF - 5 Power Mix'!F12 -> 0
A84: h | B84: Electricity generated through renewable sources (InPlant) | C84: NF - 5 Power Mix'!{1.h} | D84: Lakh kWh | E84: ='NF - 5 Power Mix'!E13 -> 0 | F84: ='NF - 5 Power Mix'!F13 -> 0
A85: i | B85: Electricity through dedicated Line from Captive Power Plant (CPP) | C85: NF - 5 Power Mix'!{1.l} | D85: Lakh kWh | E85: ='NF - 5 Power Mix'!E17 -> 0 | F85: ='NF - 5 Power Mix'!F17 -> 0
A86: j | B86: Electricity imported through wheeling from IPP | C86: NF - 5 Power Mix'!{1.k} | D86: Lakh kWh | E86: ='NF - 5 Power Mix'!E16 -> 0 | F86: ='NF - 5 Power Mix'!F16 -> 0
A87: k | B87: Renewable Electricty through dedicated line | C87: NF - 5 Power Mix'!{1.j} | D87: Lakh kWh | E87: ='NF - 5 Power Mix'!E15 -> 0 | F87: ='NF - 5 Power Mix'!F15 -> 0
A88: l | B88: Renewable Energy purchased from Grid (Through wheeling) | C88: NF - 5 Power Mix'!{1.i} | D88: Lakh kWh | E88: ='NF - 5 Power Mix'!E14 -> 39.123359 | F88: ='NF - 5 Power Mix'!F14 -> 0
A89: m | B89: Total Electricity Consumption Avaialbility | C89: Sum{13.1(a) to 13.1(l)} | D89: Lakh kWh | E89: =SUM(E77:E88) -> 72056.838 | F89: =SUM(F77:F88) -> 0
A90: 13.2 | B90: Share of Electricity
A91: a | B91: % Captive Fossil | C91: (13.1(b)+13.1(c)+13.1(d)+13.1(e)+13.1(f)+13.1(i)+13.1(j))/13.1(m) | D91: % | E91: =IFERROR((E78+E79+E80+E81+E82+E85+E86)/E89,0) -> 0.98356973 | F91: =IFERROR((F78+F79+F80+F81+F82+F85+F86)/F89,0) -> 0
A92: b | B92: % Grid Discom | C92: 13.1(a)/13.1(m) | D92: % | E92: =IFERROR(E77/E89,0) -> 0.015887319 | F92: =IFERROR(F77/F89,0) -> 0
A93: c | B93: % Total RE | C93: (13.1(h)+13.1(k)+13.1(l))/13.1(m) | D93: % | E93: =IFERROR((E84+E87+E88)/E89,0) -> 0.00054295137 | F93: =IFERROR((F84+F87+F88)/F89,0) -> 0
A94: d | B94: % WHRS | C94: 13.1(g)/13.1(m) | D94: % | E94: =IFERROR(E83/E89,0) -> 0 | F94: =IFERROR(F83/F89,0) -> 0
A95: e | B95: Total composition | C95: 13.2(a)+13.2(b)+13.2(c)+13.2(d) | D95: % | E95: =SUM(E91:E94) -> 1 | F95: =SUM(F91:F94) -> 0
A96: a.1 | B96: % Power Plant (Outside- Dedicated and Wheeling) | C96: (13.1(i)+13.1(j))/13.1(m) | D96: % | E96: =IFERROR((E85+E86)/E89,0) -> 0 | F96: =IFERROR((F85+F86)/F89,0) -> 0
A97: c.1 | B97: % Captive RE (In Plant) | C97: 13.1(h)/13.1(m) | D97: % | E97: =IFERROR(E84/E89,0) -> 0 | F97: =IFERROR(F84/F89,0) -> 0
A98: c.2 | B98: % Outside RE | C98: (13.1(k)+13.1(l))/13.1(m) | D98: % | E98: =IFERROR((E87+E88)/E89,0) -> 0.00054295137 | F98: =IFERROR((F87+F88)/F89,0) -> 0
A99: c.3 | B99: % RE/overall Energy (ToE/ToE) | C99: (13.1(h)+13.1(k)+13.1(l))*860*10^5/(H(viii)*10^7) | D99: % | E99: =IFERROR((E84+E87+E88)*860*10^5/(E67*10^7),0) -> 0.00016128832 | F99: =IFERROR((F84+F87+F88)*860*10^5/(F67*10^7),0) -> 0
A100: 14 | B100: Emission Analysis
A102: N | B102: Total Equivalent Product for GHG Emission Intensity | C102: Total equivalent production | D102: Tons | E102: =IF('General Information'!C4="REFINERY",'NF - 4 Product Mix'!E102+E46,'NF - 4 Product Mix'!E114+E54) -> 423703.51 | F102: =IF('General Information'!D4="REFINERY",'NF - 4 Product Mix'!F102+F46,'NF - 4 Product Mix'!F114+F54) -> 0
A103: O | B103: Direct Emission (Scope 1)
A104: (i) | B104: Solid Fossil Fuel consumption | C104: Form Sa1'!(c.17) | D104: tCO2 eq | E104: ='Form Sa1'!H1021 -> 7588795.7 | F104: ='Form Sa1'!I1021 -> 0
A105: a | B105: Direct Emission generation related (Energy) | C105: Form Sa1'!(c.11)+Form Sa1'!(c.12) | D105: tCO2 eq | E105: ='Form Sa1'!H1015+'Form Sa1'!H1016 -> 7034588.3 | F105: ='Form Sa1'!I1015+'Form Sa1'!I1016 -> 0
A106: b | B106: Direct Emission Process related (Energy) | C106: Form Sa1'!(c.13) | D106: tCO2 eq | E106: ='Form Sa1'!H1017 -> 554207.4 | F106: ='Form Sa1'!I1017 -> 0
...

Sheet NF - 5 Power Mix
A1: Normalization Factor for Power Mix
A2: Name of the Unit | C2: ='Form Sa1'!C3:K3 -> HINDALCO INDUSTRIES LIMITED
A3: Document Available for Normalisation | D3: Yes/No | E3: ='Form Sa1'!H1377 -> Yes | F3: ='Form Sa1'!I1377 -> Yes
A4: S.No. | B4: Description | C4: Basis/ Calculation | D4: Units | E4: ='Form 1'!D15 & ' Summary Sheet'!E5 -> Baseline/Previous Year 2023-24 | F4: ='Form 1'!E15 &" "& 'Form 1'!E16 -> Assesment year/ Current Year FY 2025-26
A5: 1 | B5: Total Electricity Availability | C5: {(1.a)+(1.b)+(1.c)+(1.d)+(1.e)} | D5: Lakh kWh | E5: =SUM(E6:E17) -> 72056.838 | F5: =SUM(F6:F17) -> 0
A6: 1.a | B6: Electricity imported from Grid | C6: Form Sa1'! b.1.(xvii) | D6: Lakh kWh | E6: ='Form Sa1'!H693 -> 1144.79 | F6: ='Form Sa1'!I693 -> 0
A7: 1.b | B7: Electricity generated from DG | C7: Form Sa1'! b.2.1.(iii) | D7: Lakh kWh | E7: ='Form Sa1'!H729 -> 0 | F7: ='Form Sa1'!I729 -> 0
A8: 1.c | B8: Electricity generated from Steam Turbine | C8: Form Sa1'! b.2.2.(iii) | D8: Lakh kWh | E8: ='Form Sa1'!H740 -> 66354.072 | F8: ='Form Sa1'!I740 -> 0
A9: 1.d | B9: Electricity generated from Gas Turbine/Gas Generator | C9: Form Sa1'! b.2.3.(iii) | D9: Lakh kWh | E9: ='Form Sa1'!H748 -> 0 | F9: ='Form Sa1'!I748 -> 0
A10: 1.e | B10: Electricity generated from Cogen (Extraction/Back Pressure) | C10: Form Sa1'! b.2.5.(iii) | D10: Lakh kWh | E10: ='Form Sa1'!H762 -> 779.51468 | F10: ='Form Sa1'!I762 -> 0
A11: 1.f | B11: Electricity generated from Cogen (Condensing) | C11: Form Sa1'! b.2.6.(iii) | D11: Lakh kWh | E11: ='Form Sa1'!H789 -> 3739.3381 | F11: ='Form Sa1'!I789 -> 0
A12: 1.g | B12: Electricity generated from WHR | C12: Form Sa1'! b.2.4.(ii) | D12: Lakh kWh | E12: ='Form Sa1'!H756 -> 0 | F12: ='Form Sa1'!I756 -> 0
A13: 1.h | B13: Electricity generated from Renewables (In-Plant) | C13: Form Sa1'!{b2.8.2(vi)} | D13: Lakh kWh | E13: ='Form Sa1'!H835 -> 0 | F13: ='Form Sa1'!I835 -> 0
A14: 1.i | B14: Electricity Wheeled from Renewable Sources | C14: Form Sa1'!{b.1((xxvii)} | D14: Lakh kWh | E14: ='Form Sa1'!H720 -> 39.123359 | F14: ='Form Sa1'!I720 -> 0
A15: 1.j | B15: Electricity wheeled from Renewable sources through dedicated line | C15: Form Sa1'!{b.1((vi)} | D15: Lakh kWh | E15: ='Form Sa1'!H698 -> 0 | F15: ='Form Sa1'!I698 -> 0
A16: 1.k | B16: Electricity imported through wheeling from IPP | C16: Form Sa1'!{b.1((vii)} | D16: Lakh kWh | E16: ='Form Sa1'!H699 -> 0 | F16: ='Form Sa1'!I699 -> 0
A17: 1.l | B17: Electricity wheeled from CPP through dedicated line | C17: Form Sa1'!{b2.7(ii)} | D17: Lakh kWh | E17: ='Form Sa1'!H814 -> 0 | F17: ='Form Sa1'!I814 -> 0 | XFD17: =SUM(E6:E17)-E19-E20 -> 70274.185
A19: 2.1 | B19: Electricity exported to grid | C19: Form Sa1'! b.4 | D19: Lakh kWh | E19: ='Form Sa1'!H841 -> 1293.4464 | F19: ='Form Sa1'!I841 -> 0
A20: 2.2 | B20: Electricity exported to colony | C20: Form Sa1'! b.5 | D20: Lakh kWh | E20: ='Form Sa1'!H842 -> 489.20741 | F20: ='Form Sa1'!I842 -> 0
A21: 2.3 | B21: Total energy exported to grid | C21: (2.1)*(35)/10 | D21: Million kcal | E21: =(E19*E71)/10 -> 360762.71 | F21: =(F19*F71)/10 -> #DIV/0!
A22: 2.4 | B22: Total energy exported to colony | C22: (2.2)*(36)/10 | D22: Million kcal | E22: =(E20*E71)/10 -> 136447.7 | F22: =(F20*F71)/10 -> #DIV/0!
A24: 3 | B24: Total Electricity Consumption With in plant | C24: Form Sa1'! b.8. | D24: Lakh kWh | E24: ='Form Sa1'!H845 -> 70274.185 | F24: ='Form Sa1'!I845 -> 0
A25: 3.a | B25: Electricity imported from Grid | C25: (1.a) | D25: Lakh kWh | E25: =E6 -> 1144.79 | F25: =F6 -> 0
A26: 3.b | B26: Electricity generated from DG | C26: (1.b) -(2) | D26: Lakh kWh | E26: =IF(AND(E7>E8,E7>E9,E7>E10,E7>E11,E7>E12),E7-E19,E7) -> 0 | F26: =IF(AND(F7>F8,F7>F9,F7>F10,F7>F11,F7>F12),F7-F19,F7) -> 0
A27: 3.c | B27: Steam Turbine generated Electricity Consumption | C27: {(1.c)-(2)} | D27: Lakh kWh | E27: =IF(AND(E8>E7,E8>E9,E8>E10,E8>E11,E8>E12),E8-E19,E8) -> 65060.626 | F27: =IF(AND(F8>F7,F8>F9,F8>F10,F8>F11,F8>F12),F8-F19,F8) -> 0
A28: 3.d | B28: Gas Turbine/GG generated Electricity Consumption | C28: {(1.d)-(2)} | D28: Lakh kWh | E28: =IF(AND(E9>E7,E9>E8,E9>E10,E9>E11,E9>E12),E9-E19,E9) -> 0 | F28: =IF(AND(F9>F7,F9>F8,F9>F10,F9>F11,F9>F12),F9-F19,F9) -> 0
A29: 3.e | B29: Cogen generated Electricity Consumption(Extraction/Back Pressure) | C29: {(1.e.)-(2)} | D29: Lakh kWh | E29: =IF(AND(E10>E7,E10>E8,E10>E9,E10>E11,E10>E12),E10-E19,E10) -> 779.51468 | F29: =IF(AND(F10>F7,F10>F8,F10>F9,F10>F11,F10>F12),F10-F19,F10) -> 0
A30: 3.f | B30: Cogen generated Electricity Consumption (Condensing) | C30: {(1.f)-(2)} | D30: Lakh kWh | E30: =IF(AND(E11>E7,E11>E8,E11>E9,E11>E10,E11>E12),E11-E19,E11) -> 3739.3381 | F30: =IF(AND(F11>F7,F11>F8,F11>F9,F11>F10,F11>F12),F11-F19,F11) -> 0
A31: 3.g | B31: WHR generated Electricity Consumption | C31: {(1.g)-(2)} | D31: Lakh kWh | E31: =IF(AND(E12>E7,E12>E8,E12>E9,E12>E10,E12>E11),E12-E19,E12) -> 0 | F31: =IF(AND(F12>F7,F12>F8,F12>F9,F12>F10,F12>F11),F12-F19,F12) -> 0
A33: 4 | B33: Total Electricity Consumption With in plant exculding WHR | C33: {(3)-(3.e)} | D33: Lakh kWh | E33: =E24-E31 -> 70274.185 | F33: =F24-F31 -> 0
A35: 5 | B35: Grid Heat Rate | C35: 860 | D35: kcal/kWh | E35: 860 | F35: 860
A36: 6 | B36: DG Heat Rate | C36: Form Sa1'! (H.1) | D36: kcal/kWh | E36: ='Form Sa1'!H1312 -> 0 | F36: ='Form Sa1'!I1312 -> 0
A37: 7 | B37: Steam Turbine Gross Heat Rate | C37: Form Sa1'! (H.2) | D37: kcal/kWh | E37: ='Form Sa1'!H1313 -> 2564.5708 | F37: ='Form Sa1'!I1313 -> 0
A38: 8 | B38: Gas Turbine/GG Gross Heat Rate | C38: Form Sa1'! (H.3) | D38: kcal/kWh | E38: ='Form Sa1'!H1314 -> 0 | F38: ='Form Sa1'!I1314 -> 0
A39: 9 | B39: Cogen (Extraction/Back Pressure) Gross Heat Rate | C39: Form Sa1'! (H5 BY) | D39: kcal/kWh | E39: ='Form Sa1'!H1316 -> 936.81013 | F39: ='Form Sa1'!I1316 -> 0
A40: 10 | B40: Cogen (Condensing) Gross Heat Rate | C40: Form Sa1'! (H4 BY) | D40: kcal/kWh | E40: ='Form Sa1'!H1315 -> 3636.0936 | F40: ='Form Sa1'!I1315 -> 0
A41: 11 | B41: Exported Power Heat Rate | C41: -4.22 | D41: kcal/kWh | E41: =E54 -> 2821.3846 | F41: =F54 -> 0
A43: 12 | B43: APC of DG | C43: Form Sa1'! (b.2.1.(vi) BY) | D43: % | E43: ='Form Sa1'!H732 -> 0 | F43: ='Form Sa1'!I732 -> 0
A44: 13 | B44: APC of Steam Turbine | C44: Form Sa1'! {b.2.2.(iv)} | D44: % | E44: ='Form Sa1'!H741 -> 8.33 | F44: ='Form Sa1'!I741 -> 0
A45: 14 | B45: APC of Gas Turbine | C45: Form Sa1'! {b.2.3.(v)} | D45: % | E45: ='Form Sa1'!H750 -> 0 | F45: ='Form Sa1'!I750 -> 0
A46: 15 | B46: APC of Cogen (Extraction/Back Pressure) | C46: Form Sa1'! (b.2.5.(iv) BY) | D46: % | E46: ='Form Sa1'!H763 -> 0 | F46: ='Form Sa1'!I763 -> 0
A47: 16 | B47: APC of Cogen (Condensing) | C47: Form Sa1'! (b.2.6.(iv) BY) | D47: % | E47: ='Form Sa1'!H790 -> 0 | F47: ='Form Sa1'!I790 -> 0
A49: 17 | B49: DG Net Heat Rate | C49: [(6)/{1-(12)/100}] | D49: kcal/kWh | E49: =E36/(1-E43/100) -> 0 | F49: =F36/(1-F43/100) -> 0
A50: 18 | B50: Steam Turbine Net Heat Rate | C50: [(7)/{1-(10)/100}] | D50: kcal/kWh | E50: =E37/(1-E44/100) -> 2797.6119 | F50: =F37/(1-F44/100) -> 0
A51: 19 | B51: Gas Turbine Net Heat Rate | C51: [(8)/{1-(11)/100}] | D51: kcal/kWh | E51: =E38/(1-E45/100) -> 0 | F51: =F38/(1-F45/100) -> 0
A52: 20 | B52: Cogen (Extraction/Back Pressure) Net Heat Rate | C52: [(9)/{1-(15)/100}] | D52: kcal/kWh | E52: =E39/(1-E46/100) -> 936.81013 | F52: =F39/(1-F46/100) -> 0
A53: 21 | B53: Cogen (Condensing) Net Heat Rate | C53: [(10)/{1-(16)/100}] | D53: kcal/kWh | E53: =E40/(1-E47/100) -> 3636.0936 | F53: =F40/(1-F47/100) -> 0
A54: 22 | B54: Weighted Generation Net Heat Raate | C54: {(17)*(1.b)+(18)*(1.c)+(19)*(1.d)+(20)*(1.e)+(21)*(1.f)} | D54: kcal/kWh | E54: =IFERROR((E49*E7+E8*E50+E51*E9+E52*E10+E11*E53)/SUM(E7:E11),0) -> 2821.3846 | F54: =IFERROR((F49*F7+F8*F50+F51*F9+F52*F10+F11*F53)/SUM(F7:F11),0) -> 0
A55: 22.1 | B55: Net Heat Rate CPP located outside from plant boundary (Through Wheeling) | C55: Form Sa1'!{b.1(viii)} | D55: kcal/kWh | E55: ='Form Sa1'!H700 -> 0 | F55: ='Form Sa1'!I700 -> 0
A56: 22.3 | B56: Dedicated Line CPP Net Heat Rate | C56: Form Sa1'!{b2.7(ii)} | D56: kcal/kWh | E56: ='Form Sa1'!H816 -> 0 | F56: ='Form Sa1'!I816 -> 0
A58: 23 | B58: % share of Grid | C58: (3.a)*100/(4) | D58: % | E58: =IFERROR(E25*100/$E$33,0) -> 1.6290335 | F58: =IFERROR(F25*100/$F$33,0) -> 0
A59: 24 | B59: % share of DG | C59: (3.b)*100/(4) | D59: % | E59: =IFERROR(E26*100/$E$33,0) -> 0 | F59: =IFERROR(F26*100/$F$33,0) -> 0
A60: 25 | B60: % share of Steam Turbine | C60: (3.c)*100/(4) | D60: % | E60: =IFERROR(E27*100/$E$33,0) -> 92.581118 | F60: =IFERROR(F27*100/$F$33,0) -> 0
A61: 26 | B61: % share of Gas Turbine | C61: (3.d)*100/(4) | D61: % | E61: =IFERROR(E28*100/$E$33,0) -> 0 | F61: =IFERROR(F28*100/$F$33,0) -> 0
A62: 27 | B62: % share of Cogen (Extraction/Back Pressure) | C62: (3.e) *100/(4) | D62: % | E62: =IFERROR(E29*100/$E$33,0) -> 1.1092476 | F62: =IFERROR(F29*100/$F$33,0) -> 0
A63: 28 | B63: % share of Cogen (Condensing) | C63: (3.f) *100/(4) | D63: % | E63: =IFERROR(E30*100/$E$33,0) -> 5.3210694 | F63: =IFERROR(F30*100/$F$33,0) -> 0
A65: 29 | B65: Wt. Heat Rate of Plant | C65: [(3.a)*(5)+(3.b)*(6)+(3.c)*(7)+(3.d)*(8)]/(4) | D65: kcal/kWh | E65: =IFERROR((E25*E35+E26*E36+E27*E37+E28*E38+E29*E39+E30*E40)/E33,0) -> 2592.1886 | F65: =IFERROR((F25*F35+F26*F36+F27*F37+F28*F38+F29*F39+F30*F40)/F33,0) -> 0
A66: 30 | B66: Normalized Wt. Heat Rate | C66: [(5)AY*(14)BY+(6)AY*(15)BY+(7)AY*(16)BY+(8)AY*(17)BY]/100 | D66: kcal/kWh | F66: =(F35*$E$58+F36*$E$59+F37*$E$60+F38*$E$61+F39*$E$62+F40*$E$63)/100 -> 14.009688
A67: 31 | B67: Notional Energy for All Power Source | C67: [(4)AY]*[(18)AY-(19)AY]/10 | D67: Million kcal | F67: =F33*(F65-F66)/10 -> 0
A68: 32 | B68: Notional Energy for Exported Power | C68: [(2)AY-(2)BY]*[(12)-(9)AY] | D68: Million kcal | F68: =(F19-E19)*(F54-F41)/10 -> 0
A69: 33 | B69: Total Notional Energy for Power Mix | C69: (20)+(21) | D69: Million kcal | F69: =(F67+F68) -> 0
A70: 35 | B70: Weighted Generation Net Heat Rate including CPP located outside of the plant (for grid export) | C70: [(1.b)*(17)+(1.c)*(18)+(1.d)*(19)+(1.e)*(20)+(1.f)*(21)]/[(1.b)+(1.c)+(1.d)+(1.e)+(1.f)] | D70: kcal/kwh | E70: =IFERROR((E7*E49+E8*E50+E9*E51+E10*E52+E11*E53+E12*860)/SUM(E7:E12),0) -> 2821.3846 | F70: =IFERROR((F7*F49+F8*F50+F9*F51+F10*F52+F11*F53+F12*860)/SUM(F7:F12),0) -> 0
A71: 36 | B71: Weighted Net Heat Rate including renewable | C71: [(((1.a)+(1.g)+(1.h)+(1.i)+(1.j))*860)+(1.b)*(17)+(1.c)*(18)+(1.d)*(19)+(1.e)*(20)+(1.f)*(21)+(1.k)*(22.1)+(1.l)*(22.3)]/[sum(1.a) to (1.l)] | D71: kcal/kWh | E71: =((E6+E12+E13+E14+E15)*860+E16*E55+E17*E56+E7*E49+E8*E50+E9*E51+E10*E52+E11*E53)/(SUM(E6:E17)) -> 2789.1586 | F71: =((F6+F12+F13+F14+F15)*860+F16*F55+F17*F56+F7*F49+F8*F50+F9*F51+F10*F52+F11*F53)/(SUM(F6:F17)) -> #DIV/0! | G71: =((G6+G12+G13+G14+G15)*860+G16*G55+G17*G56+G7*G49+G8*G50+G9*G51+G10*G52+G11*G53)/(SUM(G6:G17)) -> #DIV/0! | H71: =((H6+H12+H13+H14+H15)*860+H16*H55+H17*H56+H7*H49+H8*H50+H9*H51+H10*H52+H11*H53)/(SUM(H6:H17)) -> #DIV/0! | I71: =((I6+I12+I13+I14+I15)*860+I16*I55+I17*I56+I7*I49+I8*I50+I9*I51+I10*I52+I11*I53)/(SUM(I6:I17)) -> #DIV/0! | J71: =((J6+J12+J13+J14+J15)*860+J16*J55+J17*J56+J7*J49+J8*J50+J9*J51+J10*J52+J11*J53)/(SUM(J6:J17)) -> #DIV/0! | K71: =((K6+K12+K13+K14+K15)*860+K16*K55+K17*K56+K7*K49+K8*K50+K9*K51+K10*K52+K11*K53)/(SUM(K6:K17)) -> #DIV/0! | L71: =((L6+L12+L13+L14+L15)*860+L16*L55+L17*L56+L7*L49+L8*L50+L9*L51+L10*L52+L11*L53)/(SUM(L6:L17)) -> #DIV/0! | ... XFD71: =((XFD6+XFD12+XFD13+XFD14+XFD15)*860+XFD16*XFD55+XFD17*XFD56+XFD7*XFD49+XFD8*XFD50+XFD9*XFD51+XFD10*XFD52+XFD11*XFD53)/(SUM(XFD6:XFD17)) -> 0

Sheet Emission Factor & GWP Backup
A1: Reference Value for Emission Factors and GWP
A2: Sr. No | B2: Fuel | C2: Carbon Dioxide (CO2) | F2: Methane (CH4) | I2: Nitrous Oxide (N2O) | N2: 1TJ | O2: 2.388459e+08 | P2: kcal | S2: 1 GJ | T2: =O2/1000 -> 238845.9 | U2: kcal
C3: t CO2/TJ | D3: t CO2/toe | E3: g CO2/kcal | F3: kg CH4/TJ | G3: gm CH4/kcal | H3: gm CO2eq/kcal | I3: kg N2O/TJ | J3: gm N2O/kcal | K3: gmCO2eq/kcal | S3: 1 GJ | T3: =T2/(1000*10000) -> 0.02388459 | U3: toe
A4: 1 | B4: Crude Oil | C4: 73.3 | D4: =C4/$O$11 -> 3.0689244 | E4: =C4*1000*1000/$O$2 -> 0.30689244 | F4: 3 | G4: =F4*1000/($O$2) -> 1.25604e-05 | H4: =G4*$E$61 -> 0.0003516912 | I4: 0.6 | J4: =I4*1000/$O$2 -> 2.51208e-06 | K4: =J4*$E$62 -> 0.0006657012 | N4: Item | O4: Qty | P4: Unit
A5: 2 | B5: Orimulsion | C5: 77 | D5: =C5/$O$11 -> 3.223836 | E5: =C5*1000*1000/$O$2 -> 0.3223836 | F5: 3 | G5: =F5*1000/($O$2) -> 1.25604e-05 | H5: =G5*$E$61 -> 0.0003516912 | I5: 0.6 | J5: =I5*1000/$O$2 -> 2.51208e-06 | K5: =J5*$E$62 -> 0.0006657012 | N5: =N6 -> Other Bituminous Coal | O5: =C28 -> 94.6 | P5: tCO2/TJ
A6: 3 | B6: Natural Gas Liquids | C6: 64.2 | D6: =C6/$O$11 -> 2.6879256 | E6: =C6*1000*1000/$O$2 -> 0.26879256 | F6: 3 | G6: =F6*1000/($O$2) -> 1.25604e-05 | H6: =G6*$E$61 -> 0.0003516912 | I6: 0.6 | J6: =I6*1000/$O$2 -> 2.51208e-06 | K6: =J6*$E$62 -> 0.0006657012 | N6: =B28 -> Other Bituminous Coal | O6: =10^6*O5/O2 -> 0.39607128 | P6: gm CO2/kcal
A7: 4 | B7: Motor Gasoline | C7: 69.3 | D7: =C7/$O$11 -> 2.9014524 | E7: =C7*1000*1000/$O$2 -> 0.29014524 | F7: 3 | G7: =F7*1000/($O$2) -> 1.25604e-05 | H7: =G7*$E$61 -> 0.0003516912 | I7: 0.6 | J7: =I7*1000/$O$2 -> 2.51208e-06 | K7: =J7*$E$62 -> 0.0006657012 | N7: =N5 -> Other Bituminous Coal | O7: 4500 | P7: kcal/kg
A8: 5 | B8: Aviation Gasoline | C8: 70 | D8: =C8/$O$11 -> 2.93076 | E8: =C8*1000*1000/$O$2 -> 0.293076 | F8: 3 | G8: =F8*1000/($O$2) -> 1.25604e-05 | H8: =G8*$E$61 -> 0.0003516912 | I8: 0.6 | J8: =I8*1000/$O$2 -> 2.51208e-06 | K8: =J8*$E$62 -> 0.0006657012 | N8: =N7 -> Other Bituminous Coal | O8: =O6*O7 -> 1782.3208 | P8: gm CO2/kg
A9: 6 | B9: Jet Gasoline | C9: 70 | D9: =C9/$O$11 -> 2.93076 | E9: =C9*1000*1000/$O$2 -> 0.293076 | F9: 3 | G9: =F9*1000/($O$2) -> 1.25604e-05 | H9: =G9*$E$61 -> 0.0003516912 | I9: 0.6 | J9: =I9*1000/$O$2 -> 2.51208e-06 | K9: =J9*$E$62 -> 0.0006657012 | N9: =N8 -> Other Bituminous Coal | O9: =O8/1000 -> 1.7823208 | P9: kg CO2/kg
A10: 7 | B10: Jet Kerosene | C10: 71.5 | D10: =C10/$O$11 -> 2.993562 | E10: =C10*1000*1000/$O$2 -> 0.2993562 | F10: 3 | G10: =F10*1000/($O$2) -> 1.25604e-05 | H10: =G10*$E$61 -> 0.0003516912 | I10: 0.6 | J10: =I10*1000/$O$2 -> 2.51208e-06 | K10: =J10*$E$62 -> 0.0006657012
A11: 8 | B11: Other Kerosene | C11: 71.9 | D11: =C11/$O$11 -> 3.0103092 | E11: =C11*1000*1000/$O$2 -> 0.30103092 | F11: 3 | G11: =F11*1000/($O$2) -> 1.25604e-05 | H11: =G11*$E$61 -> 0.0003516912 | I11: 0.6 | J11: =I11*1000/$O$2 -> 2.51208e-06 | K11: =J11*$E$62 -> 0.0006657012 | N11: 1TJ | O11: =O2/10000/1000 -> 23.88459 | P11: toe
A12: 9 | B12: Shale Oil | C12: 73.3 | D12: =C12/$O$11 -> 3.0689244 | E12: =C12*1000*1000/$O$2 -> 0.30689244 | F12: 3 | G12: =F12*1000/($O$2) -> 1.25604e-05 | H12: =G12*$E$61 -> 0.0003516912 | I12: 0.6 | J12: =I12*1000/$O$2 -> 2.51208e-06 | K12: =J12*$E$62 -> 0.0006657012 | N12: 1TJ
A13: 10 | B13: Gas/Diesel Oil | C13: 74.1 | D13: =C13/$O$11 -> 3.1024188 | E13: =C13*1000*1000/$O$2 -> 0.31024188 | F13: 3 | G13: =F13*1000/($O$2) -> 1.25604e-05 | H13: =G13*$E$61 -> 0.0003516912 | I13: 0.6 | J13: =I13*1000/$O$2 -> 2.51208e-06 | K13: =J13*$E$62 -> 0.0006657012 | N13: 1TJ | O13: =O2/(10^6*10000) -> 0.02388459
A14: 11 | B14: Residual Fuel Oil | C14: 77.4 | D14: =C14/$O$11 -> 3.2405832 | E14: =C14*1000*1000/$O$2 -> 0.32405832 | F14: 3 | G14: =F14*1000/($O$2) -> 1.25604e-05 | H14: =G14*$E$61 -> 0.0003516912 | I14: 0.6 | J14: =I14*1000/$O$2 -> 2.51208e-06 | K14: =J14*$E$62 -> 0.0006657012 | N14: 40000000 | O14: =O13*N14 -> 955383.59
A15: 12 | B15: Liquefied Petroleum Gas | C15: 63.1 | D15: =C15/$O$11 -> 2.6418708 | E15: =C15*1000*1000/$O$2 -> 0.26418708 | F15: 3 | G15: =F15*1000/($O$2) -> 1.25604e-05 | H15: =G15*$E$61 -> 0.0003516912 | I15: 0.6 | J15: =I15*1000/$O$2 -> 2.51208e-06 | K15: =J15*$E$62 -> 0.0006657012
A16: 13 | B16: Ethane | C16: 61.6 | D16: =C16/$O$11 -> 2.5790688 | E16: =C16*1000*1000/$O$2 -> 0.25790688 | F16: 3 | G16: =F16*1000/($O$2) -> 1.25604e-05 | H16: =G16*$E$61 -> 0.0003516912 | I16: 0.6 | J16: =I16*1000/$O$2 -> 2.51208e-06 | K16: =J16*$E$62 -> 0.0006657012
A17: 14 | B17: Naptha | C17: 73.3 | D17: =C17/$O$11 -> 3.0689244 | E17: =C17*1000*1000/$O$2 -> 0.30689244 | F17: 3 | G17: =F17*1000/($O$2) -> 1.25604e-05 | H17: =G17*$E$61 -> 0.0003516912 | I17: 0.6 | J17: =I17*1000/$O$2 -> 2.51208e-06 | K17: =J17*$E$62 -> 0.0006657012 | O17: =13/O14/1000 -> 1.36071e-08
A18: 15 | B18: Bitumen | C18: 80.7 | D18: =C18/$O$11 -> 3.3787476 | E18: =C18*1000*1000/$O$2 -> 0.33787476 | F18: 3 | G18: =F18*1000/($O$2) -> 1.25604e-05 | H18: =G18*$E$61 -> 0.0003516912 | I18: 0.6 | J18: =I18*1000/$O$2 -> 2.51208e-06 | K18: =J18*$E$62 -> 0.0006657012
A19: 16 | B19: Lubricants | C19: 73.3 | D19: =C19/$O$11 -> 3.0689244 | E19: =C19*1000*1000/$O$2 -> 0.30689244 | F19: 3 | G19: =F19*1000/($O$2) -> 1.25604e-05 | H19: =G19*$E$61 -> 0.0003516912 | I19: 0.6 | J19: =I19*1000/$O$2 -> 2.51208e-06 | K19: =J19*$E$62 -> 0.0006657012
A20: 17 | B20: Petroleum Coke | C20: 97.5 | D20: =C20/$O$11 -> 4.08213 | E20: =C20*1000*1000/$O$2 -> 0.408213 | F20: 3 | G20: =F20*1000/($O$2) -> 1.25604e-05 | H20: =G20*$E$61 -> 0.0003516912 | I20: 0.6 | J20: =I20*1000/$O$2 -> 2.51208e-06 | K20: =J20*$E$62 -> 0.0006657012
A21: 18 | B21: Refinery Feedstock | C21: 73.3 | D21: =C21/$O$11 -> 3.0689244 | E21: =C21*1000*1000/$O$2 -> 0.30689244 | F21: 3 | G21: =F21*1000/($O$2) -> 1.25604e-05 | H21: =G21*$E$61 -> 0.0003516912 | I21: 0.6 | J21: =I21*1000/$O$2 -> 2.51208e-06 | K21: =J21*$E$62 -> 0.0006657012
A22: 19 | B22: Refinery Gas | C22: 57.6 | D22: =C22/$O$11 -> 2.4115968 | E22: =C22*1000*1000/$O$2 -> 0.24115968 | F22: 3 | G22: =F22*1000/($O$2) -> 1.25604e-05 | H22: =G22*$E$61 -> 0.0003516912 | I22: 0.6 | J22: =I22*1000/$O$2 -> 2.51208e-06 | K22: =J22*$E$62 -> 0.0006657012
A23: 20 | B23: Paraffin Waxes | C23: 73.3 | D23: =C23/$O$11 -> 3.0689244 | E23: =C23*1000*1000/$O$2 -> 0.30689244 | F23: 3 | G23: =F23*1000/($O$2) -> 1.25604e-05 | H23: =G23*$E$61 -> 0.0003516912 | I23: 0.6 | J23: =I23*1000/$O$2 -> 2.51208e-06 | K23: =J23*$E$62 -> 0.0006657012
A24: 21 | B24: White Spirit and SBP | C24: 73.3 | D24: =C24/$O$11 -> 3.0689244 | E24: =C24*1000*1000/$O$2 -> 0.30689244 | F24: 3 | G24: =F24*1000/($O$2) -> 1.25604e-05 | H24: =G24*$E$61 -> 0.0003516912 | I24: 0.6 | J24: =I24*1000/$O$2 -> 2.51208e-06 | K24: =J24*$E$62 -> 0.0006657012
A25: 22 | B25: Other Petroleum Products | C25: 73.3 | D25: =C25/$O$11 -> 3.0689244 | E25: =C25*1000*1000/$O$2 -> 0.30689244 | F25: 3 | G25: =F25*1000/($O$2) -> 1.25604e-05 | H25: =G25*$E$61 -> 0.0003516912 | I25: 0.6 | J25: =I25*1000/$O$2 -> 2.51208e-06 | K25: =J25*$E$62 -> 0.0006657012
A26: 23 | B26: Anthracite | C26: 98.3 | D26: =C26/$O$11 -> 4.1156244 | E26: =C26*1000*1000/$O$2 -> 0.41156244 | F26: 1 | G26: =F26*1000/($O$2) -> 4.1868e-06 | H26: =G26*$E$61 -> 0.0001172304 | I26: 1.5 | J26: =I26*1000/$O$2 -> 6.2802e-06 | K26: =J26*$E$62 -> 0.001664253
A27: 24 | B27: Coking Coal | C27: 94.6 | D27: =C27/$O$11 -> 3.9607128 | E27: =C27*1000*1000/$O$2 -> 0.39607128 | F27: 1 | G27: =F27*1000/($O$2) -> 4.1868e-06 | H27: =G27*$E$61 -> 0.0001172304 | I27: 1.5 | J27: =I27*1000/$O$2 -> 6.2802e-06 | K27: =J27*$E$62 -> 0.001664253
A28: 25 | B28: Other Bituminous Coal | C28: 94.6 | D28: =C28/$O$11 -> 3.9607128 | E28: =C28*1000*1000/$O$2 -> 0.39607128 | F28: 1 | G28: =F28*1000/($O$2) -> 4.1868e-06 | H28: =G28*$E$61 -> 0.0001172304 | I28: 1.5 | J28: =I28*1000/$O$2 -> 6.2802e-06 | K28: =J28*$E$62 -> 0.001664253
A29: 26 | B29: Sub Bituminous Coal | C29: 96.1 | D29: =C29/$O$11 -> 4.0235148 | E29: =C29*1000*1000/$O$2 -> 0.40235148 | F29: 1 | G29: =F29*1000/($O$2) -> 4.1868e-06 | H29: =G29*$E$61 -> 0.0001172304 | I29: 1.5 | J29: =I29*1000/$O$2 -> 6.2802e-06 | K29: =J29*$E$62 -> 0.001664253
... A56: 53 | B56: Municipal Waste (Biomass fraction) | C56: 100 | D56: =C56/$O$11 -> 4.1868 | E56: =C56*1000*1000/$O$2 -> 0.41868 | F56: 30 | G56: =F56*1000/($O$2) -> 0.000125604 | H56: =G56*$E$61 -> 0.003516912 | I56: 4 | J56: =I56*1000/$O$2 -> 1.67472e-05 | K56: =J56*$E$62 -> 0.004438008
A58: Global Warming Potential Values
A59: Sr. No | B59: Gas | E59: GWP as BUR 3
A60: 1 | B60: Carbon Dioxide (CO2) | E60: 1
A61: 2 | B61: Methane (CH4) | E61: 28
A62: 3 | B62: Nitrous Oxide (N2O) | E62: 265
A63: 4 | B63: CF4 | E63: 6630
A64: 5 | B64: C2F6 | E64: 11100
A66: Default Process Emission Factor and Parameters
A67: Sr. No | B67: Sector | C67: Unit | D67: Value | E67: Details
A68: 1 | B68: Clinker production | C68: t CO2/t clinker | D68: 0.5292
A69: 2 | B69: Aluminium - Prebaked | C69: kg C2F6/t aluminium | D69: 0.44
A70: 3 | B70: Aluminium - Soderberg | C70: kg C2F6/t aluminium | D70: 0.07
A71: 4 | B71: Aluminium CF4 (CWPB) | C71: kg CF4/t al | D71: 0.4
A72: 5 | B72: Aluminium CF4 (SWPB) | C72: kg CF4/t al | D72: 1.6
A73: 6 | B73: Aluminium CF4 (VSS) | C73: kg CF4/t al | D73: 0.8
A74: 7 | B74: Aluminium CF4 (HSS) | C74: kg CF4/t al | D74: 0.4
A75: 8 | B75: Aluminium C2F6 (CWPB) | C75: kg C2F6/t al | D75: 0.04
A76: 9 | B76: Aluminium C2F6 (SWPB) | C76: kg C2F6/t al | D76: 0.4
A77: 10 | B77: Aluminium C2F6 (VSS) | C77: kg C2F6/t al | D77: 0.04
A78: 11 | B78: Aluminium C2F6 (HSS) | C78: kg C2F6/t al | D78: 0.03
A79: 2 | B79: Slope Coefficient (PFPBL) | C79: kg CF4/tonne Al)/(AE-Mins/cell-day | D79: 0.122 | E79: Legacy Point-Fed Prebake (PFPBL) – older cell designs with line currents of less than 350kA.
A80: 3 | B80: Slope Coefficient (PFPBM) | C80: kg CF4/tonne Al)/(AE-Mins/cell-day | D80: 0.104 | E80: Modern Point-Fed Prebake (PFPBM) – new cell technologies that operate at line currents in excess of 350kA including: AP3X/AP4X, APXe/AP60, EGA DX and DX+ | M80: Return to Process Emission at Form Sa1
A81: 4 | B81: Slope Coefficient (SWPB) | C81: kg CF4/tonne Al)/(AE-Mins/cell-day | D81: 0.233 | E81: Side-Worked Prebake (SWPB) technology
A82: 5 | B82: Slope Coefficient (VSS) | C82: kg CF4/tonne Al)/(AE-Mins/cell-day | D82: 0.058 | E82: Vertical Stud Søderberg (VSS) technology
A83: 6 | B83: Slope Coefficient (HSS) | C83: kg CF4/tonne Al)/(AE-Mins/cell-day | D83: 0.165 | E83: Horizontal Stud Søderberg (HSS) technology
A84: 7 | B84: Weight Fraction C2F6/CF4 (PFPBL) | C84: F C2F6/CF4 | D84: 0.097
A85: 8 | B85: Weight Fraction C2F6/CF4 (PFPBM) | C85: F C2F6/CF4 | D85: 0.057
A86: 9 | B86: Weight Fraction C2F6/CF4 (SWPB) | C86: F C2F6/CF4 | D86: 0.28
A87: 10 | B87: Weight Fraction C2F6/CF4 (VSS) | C87: F C2F6/CF4 | D87: 0.086
A88: 11 | B88: Weight Fraction C2F6/CF4 (HSS) | C88: F C2F6/CF4 | D88: 0.077
A91: Carbonates use emissions
A92: Sr.No | B92: Material | C92: Unit | E92: Value
A93: 1 | B93: CaCO3 | C93: t CO2/t material | E93: 0.44
A94: 2 | B94: MgCO3 | C94: t CO2/t material | E94: 0.522
A95: 3 | B95: Na2CO3 | C95: t CO2/t material | E95: 0.415
A96: 4 | B96: BaCO3 | C96: t CO2/t material | E96: 0.223
A97: 5 | B97: Li2CO3 | C97: t CO2/t material | E97: 0.596
A98: 6 | B98: K2CO3 | C98: t CO2/t material | E98: 0.318
A99: 7 | B99: SrCO3 | C99: t CO2/t material | E99: 0.298
A100: 8 | B100: NaHCO3 | C100: t CO2/t material | E100: 0.524
A101: 9 | B101: FeCO3 | C101: t CO2/t material | E101: 0.38
A102: 10 | B102: Urea | C102: t CO2/t material | E102: 0.7328

Sheet NF - 4 Product Mix
A1: Normalization Factor for Product Mix
A2: Name of the Unit | C2: ='Form Sa1'!C3:K3 -> HINDALCO INDUSTRIES LIMITED
A3: Document Available for Normalisation | D3: Yes/No | E3: ='Form Sa1'!H1378 -> Yes | F3: ='Form Sa1'!I1378 -> Yes
A4: S.No. | B4: Description | C4: Basis/ Calculation | D4: Units | E4: =' Summary Sheet'!E5 -> 2023-24 | F4: =' Summary Sheet'!F5 -> 2025-26
A5: Refinery
A6: A | B6: Production
A7: A.1 | B7: ='Form Sa1'!B45 -> Total Hydrate Alumina Production | C7: Baseline Parameter'! A1(i) | D7: Tonne | E7: ='Baseline Parameter'!E8 -> 565600 | F7: ='Baseline Parameter'!F8 -> 0
A8: A.2 | B8: ='Form Sa1'!B46 -> Total Calcined Alumina Production | C8: Baseline Parameter'! A1(ii) | D8: Tonne | E8: ='Baseline Parameter'!E9 -> 561459 | F8: ='Baseline Parameter'!F9 -> 0
A9: A.3 | B9: Total Special Hydrate Course Production | C9: Baseline Parameter'! A1(iii) | D9: Tonne | E9: ='Baseline Parameter'!E10 -> 0 | F9: ='Baseline Parameter'!F10 -> 0
A10: A.4 | B10: Total Special Hydrate Microfined Production | C10: Baseline Parameter'! A1(iv) | D10: Tonne | E10: ='Baseline Parameter'!E11 -> 0 | F10: ='Baseline Parameter'!F11 -> 0
A11: A.5 | B11: Total Special Hydrate Milled Production | C11: Baseline Parameter'! A1(v) | D11: Tonne | E11: ='Baseline Parameter'!E12 -> 0 | F11: ='Baseline Parameter'!F12 -> 0
A12: A.6 | B12: Total Calcined Alumina Course Production | C12: Baseline Parameter'! A1(vi) | D12: Tonne | E12: ='Baseline Parameter'!E13 -> 0 | F12: ='Baseline Parameter'!F13 -> 0
A13: A.7 | B13: Total Calcined Alumina Microfined Production | C13: Baseline Parameter'! A1(vii) | D13: Tonne | E13: ='Baseline Parameter'!E14 -> 0 | F13: ='Baseline Parameter'!F14 -> 0
A14: A.8 | B14: Total Calcined Alumina Milled Production | C14: Baseline Parameter'! A1(viii) | D14: Tonne | E14: ='Baseline Parameter'!E15 -> 0 | F14: ='Baseline Parameter'!F15 -> 0
A15: A.9 | B15: Total Carbon Black Production | C15: Baseline Parameter'! A1(ix) | D15: Tonne | E15: ='Baseline Parameter'!E16 -> 0 | F15: ='Baseline Parameter'!F16 -> 0
A16: A.10 | B16: Total Carbon Paste Production | C16: Baseline Parameter'! A1(x) | D16: Tonne | E16: ='Baseline Parameter'!E17 -> 236609.49 | F16: ='Baseline Parameter'!F17 -> 0
A17: A.11 | B17: Total zeolite Production | C17: Baseline Parameter'! A1(xi) | D17: Tonne | E17: ='Baseline Parameter'!E18 -> 0 | F17: ='Baseline Parameter'!F18 -> 0
A18: A.12 | B18: Total Production of other By-product | C18: Baseline Parameter'! A1(xii) | D18: Tonne | E18: ='Baseline Parameter'!E19 -> 0 | F18: ='Baseline Parameter'!F19 -> 0
A19: B | B19: Specific Energy Consumption
A20: B.1 | B20: Standard/Calcined Alumina | C20: 'Baseline Parameter'! B1.(i) | D20: Million kcal/Tonne | E20: ='Baseline Parameter'!E43 -> 2.7985109 | F20: ='Baseline Parameter'!F43 -> #DIV/0!
A21: B.2 | B21: Standard Hydrate Alumina | C21: 'Baseline Parameter'! B1.(ii) | D21: Million kcal/Tonne | E21: ='Baseline Parameter'!E44 -> 2.0367461 | F21: ='Baseline Parameter'!F44 -> #DIV/0!
A22: B.3 | B22: Special Hydrate Course | C22: 'Baseline Parameter'! B1.(iii) | D22: Million kcal/Tonne | E22: ='Baseline Parameter'!E45 -> 0 | F22: ='Baseline Parameter'!F45 -> #DIV/0!
A23: B.4 | B23: Special Hydrate Microfined | C23: 'Baseline Parameter'! B1.(iv) | D23: Million kcal/Tonne | E23: ='Baseline Parameter'!E46 -> 0 | F23: ='Baseline Parameter'!F46 -> #DIV/0!
A24: B.5 | B24: Special Hydrate Milled | C24: 'Baseline Parameter'! B1.(v) | D24: Million kcal/Tonne | E24: ='Baseline Parameter'!E47 -> 0 | F24: ='Baseline Parameter'!F47 -> #DIV/0!
A25: B.6 | B25: Special Calcined Alumina Course | C25: 'Baseline Parameter'! B1.(vi) | D25: Million kcal/Tonne | E25: ='Baseline Parameter'!E48 -> 0 | F25: ='Baseline Parameter'!F48 -> #DIV/0!
A26: B.7 | B26: Special Calcined Alumina Microfined | C26: 'Baseline Parameter'! B1.(vii) | D26: Million kcal/Tonne | E26: ='Baseline Parameter'!E49 -> 0 | F26: ='Baseline Parameter'!F49 -> #DIV/0!
A27: B.8 | B27: Special Calcined Alumina Milled | C27: 'Baseline Parameter'! B1.(viii) | D27: Million kcal/Tonne | E27: ='Baseline Parameter'!E50 -> 0 | F27: ='Baseline Parameter'!F50 -> #DIV/0!
A28: C | B28: By Products Energy Consumption
A29: C.1 | B29: Energy Consumption of Carbon Black | C29: Baseline Parameter'! B1.1.(i) | D29: Million kcal | E29: ='Baseline Parameter'!E52 -> 0 | F29: ='Baseline Parameter'!F52 -> #DIV/0!
A30: C.2 | B30: Energy Consumption of Carbon Paste | C30: Baseline Parameter'! B1.1.(ii) | D30: Million kcal | E30: ='Baseline Parameter'!E53 -> 0 | F30: ='Baseline Parameter'!F53 -> #DIV/0!
A31: C.3 | B31: Energy Consumption of Zeolite | C31: Baseline Parameter'! B1.1.(iii) | D31: Million kcal | E31: ='Baseline Parameter'!E54 -> 0 | F31: ='Baseline Parameter'!F54 -> #DIV/0!
A32: C.4 | B32: Energy Consumption of Other By-Product | C32: Baseline Parameter'! B1.1.(iv) | D32: Million kcal | E32: ='Baseline Parameter'!E55 -> 0 | F32: ='Baseline Parameter'!F55 -> #DIV/0!
A33: C.5 | B33: Total Energy Consumption of ByProducts | D33: Million kcal | E33: =SUM(E29:E32) -> 0 | F33: =SUM(F29:F32) -> #DIV/0!
A34: D | B34: Energy Factors
A35: D.1 | B35: Hydrate Alumina into Calcined Alumina | C35: {(B.2)/(B.1)} | D35: Factor | E35: =IFERROR(E21/$E$20,0) -> 0.72779639 | F35: =IFERROR(IF(E20=0,F21/$E$20,E35),0) -> 0.72779639
A36: D.2 | B36: Special Hydrate Course to Calcined Alumina | C36: {(B.3)/(B.1)} | D36: Factor | E36: =IFERROR(E22/$E$20,0) -> 0 | F36: =IFERROR(IF(E21=0,F22/$E$20,E36),0) -> 0
A37: D.3 | B37: Special Hydrate Microfined to Calcined Alumina | C37: {(B.4)/(B.1)} | D37: Factor | E37: =IFERROR(E23/$E$20,0) -> 0 | F37: =IFERROR(IF(E22=0,F23/$E$20,E37),0) -> 0
A38: D.4 | B38: Special Hydrate Milled to Calcined Alumina | C38: {(B.5)/(B.1)} | D38: Factor | E38: =IFERROR(E24/$E$20,0) -> 0 | F38: =IFERROR(IF(E23=0,F24/$E$20,E38),0) -> 0
A39: D.5 | B39: Special Calcined Alumina course to Calcined Alumina | C39: {(B.6)/(B.1)} | D39: Factor | E39: =IFERROR(E25/$E$20,0) -> 0 | F39: =IFERROR(IF(E24=0,F25/$E$20,E39),0) -> 0
A40: D.6 | B40: Special Calcined Alumina Microfined to Calcined Alumina | C40: {(B.7)/(B.1)} | D40: Factor | E40: =IFERROR(E26/$E$20,0) -> 0 | F40: =IFERROR(IF(E25=0,F26/$E$20,E40),0) -> 0
A41: D.7 | B41: Special Calcined Alumina Milled to Calcined Alumina | C41: {(B.8)/(B.1)} | D41: Factor | E41: =IFERROR(E27/$E$20,0) -> 0 | F41: =IFERROR(IF(E26=0,F27/$E$20,E41),0) -> 0
A42: E | B42: Equivalent Product- Calcined Alumina
A43: E.1 | B43: Standard Calcined Alumina | C43: (A.2) | E43: =E8 -> 561459 | F43: =F8 -> 0
A44: E.2 | B44: Standard Hydrate Alumina | C44: {(A.1)*(D.1)} | D44: Tonne | E44: =E7*E35 -> 411641.64 | F44: =F7*F35 -> 0
A45: E.3 | B45: Special Hydrate Course | C45: {(A.3)*(D.2)} | D45: Tonne | E45: =E9*E36 -> 0 | F45: =F9*F36 -> 0
A46: E.4 | B46: Special Hydrate Microfined | C46: {(A.4)*(D.3)} | D46: Tonne | E46: =E10*E37 -> 0 | F46: =F10*F37 -> 0
A47: E.5 | B47: Special Hydrate Milled | C47: {(A.5)*(D.4)} | D47: Tonne | E47: =E11*E38 -> 0 | F47: =F11*F38 -> 0
A48: E.6 | B48: Special Calcined Alumina Course | C48: {(A.6)*(D.5)} | D48: Tonne | E48: =E12*E39 -> 0 | F48: =F12*F39 -> 0
A49: E.7 | B49: Special Calcined Alumina Microfined | C49: {(A.7)*(D.6)} | D49: Tonne | E49: =E13*E40 -> 0 | F49: =F13*F40 -> 0
A50: E.8 | B50: Special Calcined Alumina Milled | C50: {(A.8)*(D.7)} | D50: Tonne | E50: =E14*E41 -> 0 | F50: =F14*F41 -> 0
A51: F | B51: Total Equivalent alumina Production | C51: {(E.1)+(E.2)+(E.3)+(E.4)+(E.5)+(E.6)+(E.7)+(E.8)-(E.2)} or if no calcined alumina {(E.2)+(E.3)+(E.4)+(E.5)+(E.6)+(E.7)+(E.8)} | D51: Tonne | E51: =IF(E43=0,SUM(E44:E50),(SUM(E43:E50)-E44)) -> 561459 | F51: =IF(F43=0,SUM(F44:F50),(SUM(F43:F50)-F44)) -> 0
A53: Smelter
A54: A | B54: Production
A55: A.1 | B55: Total Molten Aluminum Production | C55: 'Baseline Parameter'! A2 (i) | D55: Tonne | E55: ='Baseline Parameter'!E31 -> 410661.74 | F55: ='Baseline Parameter'!F31 -> 0
A56: A.2 | B56: Total Production - Cast House | C56: 'Baseline Parameter'! A2 (ii) | D56: Tonne | E56: ='Baseline Parameter'!E32 -> 381860.33 | F56: ='Baseline Parameter'!F32 -> 0
A57: A.3 | B57: Total Billet Production | C57: 'Baseline Parameter'! A2 (iii) | D57: Tonne | E57: ='Baseline Parameter'!E33 -> 58980.666 | F57: ='Baseline Parameter'!F33 -> 0
A58: A.4 | B58: Total Ingot Production | C58: 'Baseline Parameter'! A2 (iv) | D58: Tonne | E58: ='Baseline Parameter'!E34 -> 210775.16 | F58: ='Baseline Parameter'!F34 -> 0
A59: A.5 | B59: Total Bars production | C59: 'Baseline Parameter'! A2 (v) | D59: Tonne | E59: ='Baseline Parameter'!E35 -> 0 | F59: ='Baseline Parameter'!F35 -> 0
A60: A.6 | B60: Total Primary foundry alloys production | C60: 'Baseline Parameter'! A2 (vi) | D60: Tonne | E60: ='Baseline Parameter'!E36 -> 0 | F60: ='Baseline Parameter'!F36 -> 0
A61: A.7 | B61: Total Wire rod Production | C61: 'Baseline Parameter'! A2 (vii) | D61: Tonne | E61: ='Baseline Parameter'!E37 -> 55481.148 | F61: ='Baseline Parameter'!F37 -> 0
A62: A.8 | B62: Total strips production | C62: 'Baseline Parameter'! A2 (viii) | D62: Tonne | E62: ='Baseline Parameter'!E38 -> 76567.049 | F62: ='Baseline Parameter'!F38 -> 0
A63: A.9 | B63: Other Products | C63: 'Baseline Parameter'! A2 (ix) | D63: Tonne | E63: ='Baseline Parameter'!E39 -> 42078.393 | F63: ='Baseline Parameter'!F39 -> 0
A64: B | B64: Specific Energy Consumption
A65: B.1 | B65: SEC of Molten Aluminum | C65: 'Baseline Parameter'! B2 (i) | D65: Million kcal/Tonne | E65: ='Baseline Parameter'!E58 -> 44.852463 | F65: ='Baseline Parameter'!F58 -> #DIV/0!
A66: B.2 | B66: SEC of Billet | C66: 'Baseline Parameter'! B2 (ii) | D66: Million kcal/Tonne | E66: ='Baseline Parameter'!E59 -> 1.3750584 | F66: ='Baseline Parameter'!F59 -> #DIV/0!
A67: B.3 | B67: SEC of Ingot | C67: 'Baseline Parameter'! B2 (iii) | D67: Million kcal/Tonne | E67: ='Baseline Parameter'!E60 -> 0.10192863 | F67: ='Baseline Parameter'!F60 -> #DIV/0!
A68: B.4 | B68: SEC of Bars | C68: 'Baseline Parameter'! B2 (iv) | D68: Million kcal/Tonne | E68: ='Baseline Parameter'!E61 -> 0 | F68: ='Baseline Parameter'!F61 -> #DIV/0!
A69: B.5 | B69: SEC of Primary Foundary Alloys | C69: 'Baseline Parameter'! B2 (v) | D69: Million kcal/Tonne | E69: ='Baseline Parameter'!E62 -> 0 | F69: ='Baseline Parameter'!F62 -> #DIV/0!
A70: B.6 | B70: SEC of wire Rods | C70: 'Baseline Parameter'! B2 (vi) | D70: Million kcal/Tonne | E70: ='Baseline Parameter'!E63 -> 0.47047072 | F70: ='Baseline Parameter'!F63 -> #DIV/0!
A71: B.7 | B71: SEC of Strips | C71: 'Baseline Parameter'! B2 (vii) | D71: Million kcal/Tonne | E71: ='Baseline Parameter'!E64 -> 4.1726374 | F71: ='Baseline Parameter'!F64 -> #DIV/0!
A72: B.8 | B72: SEC of Other Products (if any) after Molten Aluminum | C72: 'Baseline Parameter'! B2 (viii) | D72: Million kcal/Tonne | E72: ='Baseline Parameter'!E65 -> 2.9233331 | F72: ='Baseline Parameter'!F65 -> #DIV/0!
A73: C | B73: Energy Factors
A74: C.1 | B74: Conversion factor of billet | C74: {(B.2)/(B.1)} | D74: Factor | E74: =IFERROR(E66/$E$65,0) -> 0.030657365 | F74: =IFERROR(IF(E66=0,F66/$E$65,E74),0) -> 0.030657365
A75: C.2 | B75: conversion factor of ingots | C75: {(B.3)/(B.1)} | D75: Factor | E75: =IFERROR(E67/$E$65,0) -> 0.0022725314 | F75: =IFERROR(IF(E67=0,F67/$E$65,E75),0) -> 0.0022725314
A76: C.3 | B76: conversion factor of bars | C76: {(B.4)/(B.1)} | D76: Factor | E76: =IFERROR(E68/$E$65,0) -> 0 | F76: =IFERROR(IF(E68=0,F68/$E$65,E76),0) -> 0
A77: C.4 | B77: conversion factor of primary foundary | C77: {(B.5)/(B.1)} | D77: Factor | E77: =IFERROR(E69/$E$65,0) -> 0 | F77: =IFERROR(IF(E69=0,F69/$E$65,E77),0) -> 0
A78: C.5 | B78: converstion factor of wire rods | C78: {(B.6)/(B.1)} | D78: Factor | E78: =IFERROR(E70/$E$65,0) -> 0.010489295 | F78: =IFERROR(IF(E70=0,F70/$E$65,E78),0) -> 0.010489295
A79: C.6 | B79: conversion factor of Stips | C79: {(B.7)/(B.1)} | D79: Factor | E79: =IFERROR(E71/$E$65,0) -> 0.093030285 | F79: =IFERROR(IF(E71=0,F71/$E$65,E79),0) -> 0.093030285
A80: C.7 | B80: conversion factor of other product | C80: {(B.8)/(B.1)} | D80: Factor | E80: =IFERROR(E72/$E$65,0) -> 0.065176645 | F80: =IFERROR(IF(E72=0,F72/$E$65,E80),0) -> 0.065176645
A81: D | B81: Equivalent product
A82: D.1 | B82: Molten Aluminium Prouction | C82: (A.1) | D82: Tonne | E82: =E55 -> 410661.74 | F82: =F55 -> 0
A83: D.2 | B83: Billet to Equivalent molten aluminum product | C83: {(A.3)*(C.1)} | D83: Tonne | E83: =E57*E74 -> 1808.1918 | F83: =F57*F74 -> 0
A84: D.3 | B84: Ingots to Equivalent molten aluminum product | C84: {(A.4)*(C.2)} | D84: Tonne | E84: =E58*E75 -> 478.99318 | F84: =F58*F75 -> 0
A85: D.4 | B85: Bars to Equivalent molten aluminum product | C85: {(A.5)*(C.3)} | D85: Tonne | E85: =E59*E76 -> 0 | F85: =F59*F76 -> 0
A86: D.5 | B86: Primary foundary to Equivalent molten aluminum product | C86: {(A.6)*(C.4)} | D86: Tonne | E86: =E60*E77 -> 0 | F86: =F60*F77 -> 0
A87: D.6 | B87: Wire rods to Equivalent molten aluminum product | C87: {(A.7)*(C.5)} | D87: Tonne | E87: =E61*E78 -> 581.95814 | F87: =F61*F78 -> 0
A88: D.7 | B88: Strips to Equivalent molten aluminum product | C88: {(A.8)*(C.6)} | D88: Tonne | E88: =E62*E79 -> 7123.0544 | F88: =F62*F79 -> 0
A89: D.8 | B89: Others to Equivalent molten aluminum product | C89: {(A.9)*(C.7)} | D89: Tonne | E89: =E63*E80 -> 2742.5285 | F89: =F63*F80 -> 0
A90: E | B90: Total Equivalent Product | C90: {(D.1)+(D.2)+(D.3)+(D.4)+(D.5)+(D.6)+(D.7)+(D.8)} | D90: Tonne | E90: =SUM(E82:E89) -> 423396.46 | F90: =SUM(F82:F89) -> 0
A91: Intermediary Products (Refinery and Integrated)
A92: F | B92: CO2 emission from Intermediary Product (Refinery)
A93: F.1 | B93: CO2 emission from Import of Hydrated Alumina
A94: F.1.1 | B94: =' Summary Sheet'!B20 -> Total Hydrate Aluminia Import | D94: =' Summary Sheet'!D20 -> Tonne | E94: =' Summary Sheet'!E20 -> 0 | F94: =' Summary Sheet'!F20 -> 0
A95: F.1.2 | B95: Total Net Import Energy for Hydrated Alumina | D95: Million kcal/Annum | E95: =' Summary Sheet'!E48 -> 0 | F95: =' Summary Sheet'!F48 -> #DIV/0!
A96: F.1.3 | B96: Emission factor for process and Power | D96: g CO2/kcal | E96: ='Form Sa1'!H840 -> 0.40228954 | F96: ='Form Sa1'!I840 -> 0
A97: F.1.4 | B97: Total Net Import/Export CO2 for Hydrated Alumina to be added | D97: t CO2 | E97: =E95*E96 -> 0 | F97: =F95*F96 -> #DIV/0!
A98: F.2 | B98: Additional Major Product production due to Export of Hydrated Alumina
A99: F2.1 | B99: Total Export of Hydrated Alumina | D99: Tonne | E99: =' Summary Sheet'!E19 -> 4046.513 | F99: =' Summary Sheet'!F19 -> 0
A100: F2.2 | B100: SEC of Major Product (Calcined Alumina) | D100: Million kcal/Tonne | E100: ='Baseline Parameter'!E43 -> 2.7985109 | F100: ='Baseline Parameter'!F43 -> #DIV/0!
A101: F2.3 | B101: Total Net Export Energy for Hydrated Alumina | D101: Million Kcal/Annum | E101: =' Summary Sheet'!E47 -> 8241.7197 | F101: =' Summary Sheet'!F47 -> #DIV/0!
...

Sheet Baseline Parameter
A1: Form-Sa1 (Base Line Parameters For PAT Scheme)
A2: Sector: Aluminum Sector
B3: SubSector | C3: ='General Information'!G4 -> INTEGRATED
A4: S. No | B4: Particulars | C4: Duration | D4: Unit | E4: =' Summary Sheet'!E4 -> Baseline Year(s) | F4: =' Summary Sheet'!F4 -> Current/Target Year
E5: =' Summary Sheet'!E5 -> 2023-24 | F5: =' Summary Sheet'!F5 -> 2025-26
A6: A | B6: Production and Capacity Utilization
A7: A1 | B7: Refinery Process
A8: i | B8: ='Form Sa1'!B45 -> Total Hydrate Alumina Production | C8: ='Form Sa1'!C45 -> Annual | D8: Tonne | E8: ='Form Sa1'!H45 -> 565600 | F8: ='Form Sa1'!I45 -> 0
A9: ii | B9: ='Form Sa1'!B46 -> Total Calcined Alumina Production | C9: ='Form Sa1'!C46 -> Annual | D9: Tonne | E9: ='Form Sa1'!H46 -> 561459 | F9: ='Form Sa1'!I46-'Form Sa1'!I1358 -> 0
A10: iii | B10: Total Special Hydrate Course Production | C10: Annual | D10: Tonne | E10: ='Form Sa1'!H112 -> 0 | F10: ='Form Sa1'!I112 -> 0 | G10: ='Form Sa1'!K112 -> 0 | H10: ='Form Sa1'!#REF! -> #REF! | I10: ='Form Sa1'!#REF! -> #REF! | J10: ='Form Sa1'!#REF! -> #REF! | K10: ='Form Sa1'!#REF! -> #REF! | L10: ='Form Sa1'!#REF! -> #REF! | M10: ='Form Sa1'!#REF! -> #REF! | N10: ='Form Sa1'!#REF! -> #REF! | O10: ='Form Sa1'!#REF! -> #REF! | ... X10: ='Form Sa1'!#REF! -> #REF! | Y10: ='Form Sa1'!L111 -> 0 | Z10: ='Form Sa1'!M111 -> 0 | AA10: ='Form Sa1'!N111 -> 0 | AB10: ='Form Sa1'!O111 -> 0 | AC10: ='Form Sa1'!P111 -> 0 | AD10: ='Form Sa1'!Q111 -> 0 | AE10: ='Form Sa1'!R111 -> 0 | AF10: ='Form Sa1'!S111 -> 0 | ... IR10: ='Form Sa1'!IE111 -> 0 | IS10: ='Form Sa1'!#REF! -> #REF! | IT10: ='Form Sa1'!#REF! -> #REF! | IU10: ='Form Sa1'!#REF! -> #REF! | IV10: ='Form Sa1'!#REF! -> #REF!
A11: iv | B11: Total Special Hydrate Microfined Production | C11: Annual | D11: Tonne | E11: ='Form Sa1'!H118 -> 0 | F11: ='Form Sa1'!I118 -> 0
A12: v | B12: Total Special Hydrate Milled Production | C12: Annual | D12: Tonne | E12: ='Form Sa1'!H124 -> 0 | F12: ='Form Sa1'!I124 -> 0
A13: vi | B13: Total Calcined Alumina Course Production | C13: Annual | D13: Tonne | E13: ='Form Sa1'!H130 -> 0 | F13: ='Form Sa1'!I130 -> 0
A14: vii | B14: Total Calcined Alumina Microfined Production | C14: Annual | D14: Tonne | E14: ='Form Sa1'!H136 -> 0 | F14: ='Form Sa1'!I136 -> 0
A15: viii | B15: Total Calcined Alumina Milled Production | C15: Annual | D15: Tonne | E15: ='Form Sa1'!H142 -> 0 | F15: ='Form Sa1'!I142 -> 0
A16: ix | B16: Total Carbon Black Production | C16: Annual | D16: Tonne | E16: ='Form Sa1'!H148 -> 0 | F16: ='Form Sa1'!I148 -> 0
A17: x | B17: Total Carbon Paste Production | C17: Annual | D17: Tonne | E17: ='Form Sa1'!H154 -> 236609.49 | F17: ='Form Sa1'!I154 -> 0
A18: xi | B18: Total zeolite Production | C18: Annual | D18: Tonne | E18: ='Form Sa1'!H160 -> 0 | F18: ='Form Sa1'!I160 -> 0
A19: xii | B19: Total Production of other By-product | C19: Annual | D19: Tonne | E19: ='Form Sa1'!H167 -> 0 | F19: ='Form Sa1'!I167 -> 0
A20: A1.1 | B20: Refinery Stocks
A21: viii | B21: Hydrate Alumina Opening Stock | C21: Annual | D21: Tonne | E21: ='Form Sa1'!H66 -> 30580.066 | F21: ='Form Sa1'!I66 -> 0
A22: ix | B22: Hydrate Alumina Closing Stock | C22: Annual | D22: Tonne | E22: ='Form Sa1'!H67 -> 34626.579 | F22: ='Form Sa1'!I67 -> 0
A23: x | B23: Calcined Alumina Opening Stock (Integrated Process) | C23: Annual | D23: Tonne | E23: ='Form Sa1'!H98 -> 44543.327 | F23: ='Form Sa1'!I98 -> 0
A24: xi | B24: Calcined Alumina Closing Stock (Integrated Process) | C24: Annual | D24: Tonne | E24: ='Form Sa1'!H99 -> 49464.495 | F24: ='Form Sa1'!I99 -> 0
A25: xii | B25: Hydrate Alumina exported | C25: Annual | D25: Tonne | E25: ='Form Sa1'!H64 -> 0 | F25: ='Form Sa1'!I64 -> 0
A26: xiii | B26: Hydrate Alumina Imported | C26: Annual | D26: Tonne | E26: ='Form Sa1'!H65 -> 0 | F26: ='Form Sa1'!I65 -> 0
A27: xiv | B27: Calcined Alumina exported (Integrated Process) | C27: Annual | D27: Tonne | E27: ='Form Sa1'!H105 -> 0 | F27: ='Form Sa1'!I105 -> 0
A28: xv | B28: Calcined Alumina imported (Integrated Process) | C28: Annual | D28: Tonne | E28: ='Form Sa1'!H106 -> 244856.09 | F28: ='Form Sa1'!I106+IF(C3="Integrated",'Form Sa1'!I1358,0) -> 0
A30: A2 | B30: Smelter Process
A31: i | B31: ='Form Sa1'!B54 -> Total Molten Aluminium Production | C31: ='Form Sa1'!C54 -> Annual | D31: Tonne | E31: ='Form Sa1'!H54 -> 410661.74 | F31: ='Form Sa1'!I54-'Form Sa1'!I1359 -> 0
A32: ii | B32: ='Form Sa1'!B55 -> Total Production- Cast House | C32: ='Form Sa1'!C55 -> Annual | D32: Tonne | E32: ='Form Sa1'!H55 -> 381860.33 | F32: ='Form Sa1'!I55 -> 0
A33: iii | B33: Total Billet Production | C33: Annual | D33: Tonne | E33: ='Form Sa1'!H396 -> 58980.666 | F33: ='Form Sa1'!I396 -> 0
A34: iv | B34: Total Ingot Production | C34: Annual | D34: Tonne | E34: ='Form Sa1'!H402 -> 210775.16 | F34: ='Form Sa1'!I402 -> 0
A35: v | B35: Total Bars production | C35: Annual | D35: Tonne | E35: ='Form Sa1'!H408 -> 0 | F35: ='Form Sa1'!I408 -> 0
A36: vi | B36: Total Primary foundry alloys production | C36: Annual | D36: Tonne | E36: ='Form Sa1'!H414 -> 0 | F36: ='Form Sa1'!I414 -> 0
A37: vii | B37: Total Wire rod Production | C37: Annual | D37: Tonne | E37: ='Form Sa1'!H420 -> 55481.148 | F37: ='Form Sa1'!I420 -> 0
A38: viii | B38: Total strips production | C38: Annual | D38: Tonne | E38: ='Form Sa1'!H426 -> 76567.049 | F38: ='Form Sa1'!I426 -> 0
A39: ix | B39: Other Products | C39: Annual | D39: Tonne | E39: ='Form Sa1'!H433 -> 42078.393 | F39: ='Form Sa1'!I433 -> 0
A41: B | B41: Calculation of Specific Energy Consumption
A42: B1 | B42: Refinery Process
A43: i | B43: Standard /Calcined Alumina | C43: Annual | D43: Million kcal/Tonne | E43: =('Form Sa1'!H108*E113)/10^6+'Form Sa1'!H107 -> 2.7985109 | F43: =('Form Sa1'!I108*F113)/10^6+'Form Sa1'!I107 -> #DIV/0!
A44: ii | B44: Standard Hydrate Alumina | C44: Annual | D44: Million kcal/Tonne | E44: =('Form Sa1'!H69*E113)/10^6+'Form Sa1'!H68 -> 2.0367461 | F44: =('Form Sa1'!I69*$F$113)/10^6+'Form Sa1'!I68 -> #DIV/0!
A45: iii | B45: Special Hydrate Course | C45: Annual | D45: Million kcal/Tonne | E45: =('Form Sa1'!H114*$E$113)/10^6+'Form Sa1'!H113 -> 0 | F45: =('Form Sa1'!I114*$F$113)/10^6+'Form Sa1'!I113 -> #DIV/0!
A46: iv | B46: Special Hydrate Microfined | C46: Annual | D46: Million kcal/Tonne | E46: =('Form Sa1'!H120*$E$113)/10^6+'Form Sa1'!H119 -> 0 | F46: =('Form Sa1'!I120*$F$113)/10^6+'Form Sa1'!I119 -> #DIV/0!
A47: v | B47: Special Hydrate Milled | C47: Annual | D47: Million kcal/Tonne | E47: =('Form Sa1'!H126*$E$113)/10^6+'Form Sa1'!H125 -> 0 | F47: =('Form Sa1'!I126*$F$113)/10^6+'Form Sa1'!I125 -> #DIV/0!
A48: vi | B48: Special Alumina Course | C48: Annual | D48: Million kcal/Tonne | E48: =('Form Sa1'!H132*$E$113)/10^6+'Form Sa1'!H131 -> 0 | F48: =('Form Sa1'!I132*$F$113)/10^6+'Form Sa1'!I131 -> #DIV/0!
A49: vii | B49: Special Alumina Microfined | C49: Annual | D49: Million kcal/Tonne | E49: =('Form Sa1'!H138*$E$113)/10^6+'Form Sa1'!H137 -> 0 | F49: =('Form Sa1'!I138*$F$113)/10^6+'Form Sa1'!I137 -> #DIV/0!
A50: viii | B50: Special Alumina Milled | C50: Annual | D50: Million kcal/Tonne | E50: =('Form Sa1'!H144*$E$113)/10^6+'Form Sa1'!H143 -> 0 | F50: =('Form Sa1'!I144*$F$113)/10^6+'Form Sa1'!I143 -> #DIV/0! | G50: =('Form Sa1'!K143+('Form Sa1'!K144*G113))/10^6 -> 0 | H50: =('Form Sa1'!#REF!+('Form Sa1'!#REF!*H113))/10^6 -> #REF! | I50: =('Form Sa1'!#REF!+('Form Sa1'!#REF!*I113))/10^6 -> #REF! | J50: =('Form Sa1'!#REF!+('Form Sa1'!#REF!*J113))/10^6 -> #REF! | K50: =('Form Sa1'!#REF!+('Form Sa1'!#REF!*K113))/10^6 -> #REF! | L50: =('Form Sa1'!#REF!+('Form Sa1'!#REF!*L113))/10^6 -> #REF! | M50: =('Form Sa1'!#REF!+('Form Sa1'!#REF!*M113))/10^6 -> #REF! | N50: =('Form Sa1'!#REF!+('Form Sa1'!#REF!*N113))/10^6 -> #REF! | O50: =('Form Sa1'!#REF!+('Form Sa1'!#REF!*O113))/10^6 -> #REF! | ... X50: =('Form Sa1'!#REF!+('Form Sa1'!#REF!*X113))/10^6 -> #REF! | Y50: =('Form Sa1'!L142+('Form Sa1'!L143*Y113))/10^6 -> 0 | Z50: =('Form Sa1'!M142+('Form Sa1'!M143*Z113))/10^6 -> 0 | AA50: =('Form Sa1'!N142+('Form Sa1'!N143*AA113))/10^6 -> 0 | AB50: =('Form Sa1'!O142+('Form Sa1'!O143*AB113))/10^6 -> 0 | AC50: =('Form Sa1'!P142+('Form Sa1'!P143*AC113))/10^6 -> 0 | AD50: =('Form Sa1'!Q142+('Form Sa1'!Q143*AD113))/10^6 -> 0 | AE50: =('Form Sa1'!R142+('Form Sa1'!R143*AE113))/10^6 -> 0 | AF50: =('Form Sa1'!S142+('Form Sa1'!S143*AF113))/10^6 -> 0 | ... IR50: =('Form Sa1'!IE142+('Form Sa1'!IE143*IR113))/10^6 -> 0 | IS50: =('Form Sa1'!#REF!+('Form Sa1'!#REF!*IS113))/10^6 -> #REF! | IT50: =('Form Sa1'!#REF!+('Form Sa1'!#REF!*IT113))/10^6 -> #REF! | IU50: =('Form Sa1'!#REF!+('Form Sa1'!#REF!*IU113))/10^6 -> #REF! | IV50: =('Form Sa1'!#REF!+('Form Sa1'!#REF!*IV113))/10^6 -> #REF!
A51: B1.1 | B51: By Products Energy Consumption
A52: i | B52: Energy Consumption of Carbon Black | C52: Annual | D52: Million kcal | E52: =('Form Sa1'!H149+('Form Sa1'!H150*E113/10^6))*E16 -> 0 | F52: =('Form Sa1'!I149+('Form Sa1'!I150*F113/10^6))*F16 -> #DIV/0!
A53: ii | B53: Energy Consumption of Carbon Paste | C53: Annual | D53: Million kcal | E53: =('Form Sa1'!H155+('Form Sa1'!H156*E113/10^6))*E17 -> 0 | F53: =('Form Sa1'!I155+('Form Sa1'!I156*F113/10^6))*F17 -> #DIV/0! | G53: =('Form Sa1'!K155+('Form Sa1'!K156*G113))*G17/10^6 -> 0 | H53: =('Form Sa1'!#REF!+('Form Sa1'!#REF!*H113))*H17/10^6 -> #REF! | I53: =('Form Sa1'!#REF!+('Form Sa1'!#REF!*I113))*I17/10^6 -> #REF! | J53: =('Form Sa1'!#REF!+('Form Sa1'!#REF!*J113))*J17/10^6 -> #REF! | K53: =('Form Sa1'!#REF!+('Form Sa1'!#REF!*K113))*K17/10^6 -> #REF! | L53: =('Form Sa1'!#REF!+('Form Sa1'!#REF!*L113))*L17/10^6 -> #REF! | M53: =('Form Sa1'!#REF!+('Form Sa1'!#REF!*M113))*M17/10^6 -> #REF! | N53: =('Form Sa1'!#REF!+('Form Sa1'!#REF!*N113))*N17/10^6 -> #REF! | O53: =('Form Sa1'!#REF!+('Form Sa1'!#REF!*O113))*O17/10^6 -> #REF! | ... X53: =('Form Sa1'!#REF!+('Form Sa1'!#REF!*X113))*X17/10^6 -> #REF! | Y53: =('Form Sa1'!L154+('Form Sa1'!L155*Y113))*Y17/10^6 -> 0 | Z53: =('Form Sa1'!M154+('Form Sa1'!M155*Z113))*Z17/10^6 -> 0 | AA53: =('Form Sa1'!N154+('Form Sa1'!N155*AA113))*AA17/10^6 -> 0 | AB53: =('Form Sa1'!O154+('Form Sa1'!O155*AB113))*AB17/10^6 -> 0 | AC53: =('Form Sa1'!P154+('Form Sa1'!P155*AC113))*AC17/10^6 -> 0 | AD53: =('Form Sa1'!Q154+('Form Sa1'!Q155*AD113))*AD17/10^6 -> 0 | AE53: =('Form Sa1'!R154+('Form Sa1'!R155*AE113))*AE17/10^6 -> 0 | AF53: =('Form Sa1'!S154+('Form Sa1'!S155*AF113))*AF17/10^6 -> 0 | ... IR53: =('Form Sa1'!IE154+('Form Sa1'!IE155*IR113))*IR17/10^6 -> 0 | IS53: =('Form Sa1'!#REF!+('Form Sa1'!#REF!*IS113))*IS17/10^6 -> #REF! | IT53: =('Form Sa1'!#REF!+('Form Sa1'!#REF!*IT113))*IT17/10^6 -> #REF! | IU53: =('Form Sa1'!#REF!+('Form Sa1'!#REF!*IU113))*IU17/10^6 -> #REF! | IV53: =('Form Sa1'!#REF!+('Form Sa1'!#REF!*IV113))*IV17/10^6 -> #REF!
A54: iii | B54: Energy Consumption of Zeolite | C54: Annual | D54: Million kcal | E54: =('Form Sa1'!H161+('Form Sa1'!H162*E113/10^6))*E18 -> 0 | F54: =('Form Sa1'!I161+('Form Sa1'!I162*F113/10^6))*F18 -> #DIV/0!
A55: iv | B55: Energy Consumption of Other By-Product | C55: Annual | D55: Million kcal | E55: =('Form Sa1'!H168+('Form Sa1'!H169*E113/10^6))*E19 -> 0 | F55: =('Form Sa1'!I168+('Form Sa1'!I169*F113/10^6))*F19 -> #DIV/0!
A57: B2 | B57: Smelting Process
A58: i | B58: SEC of Molten Aluminum | C58: Annual | D58: Million kcal/Tonne | E58: =('Form Sa1'!H187+('Form Sa1'!H188*E113))/10^6 -> 44.852463 | F58: =('Form Sa1'!I187+('Form Sa1'!I188*F113))/10^6 -> #DIV/0!
A59: ii | B59: SEC of Billet | C59: Annual | D59: Million kcal/Tonne | E59: =('Form Sa1'!H397+'Form Sa1'!H398*E113)/10^6 -> 1.3750584 | F59: =('Form Sa1'!I397+'Form Sa1'!I398*F113)/10^6 -> #DIV/0!
A60: iii | B60: SEC of Ingot | C60: Annual | D60: Million kcal/Tonne | E60: =('Form Sa1'!H403+('Form Sa1'!H404*E113))/1000000 -> 0.10192863 | F60: =('Form Sa1'!I403+('Form Sa1'!I404*F113))/1000000 -> #DIV/0!
A61: iv | B61: SEC of Bars | C61: Annual | D61: Million kcal/Tonne | E61: =('Form Sa1'!H409+('Form Sa1'!H410*E113))/1000000 -> 0 | F61: =('Form Sa1'!I409+('Form Sa1'!I410*F113))/1000000 -> #DIV/0!
A62: v | B62: SEC of Primary Foundary Alloys | C62: Annual | D62: Million kcal/Tonne | E62: =('Form Sa1'!H415+('Form Sa1'!H416*E113))/1000000 -> 0 | F62: =('Form Sa1'!I415+('Form Sa1'!I416*F113))/1000000 -> #DIV/0!
A63: vi | B63: SEC of wire Rods | C63: Annual | D63: Million kcal/Tonne | E63: =('Form Sa1'!H421+('Form Sa1'!H422*E113))/1000000 -> 0.47047072 | F63: =('Form Sa1'!I421+('Form Sa1'!I422*F113))/1000000 -> #DIV/0!
A64: vii | B64: SEC of Strips | C64: Annual | D64: Million kcal/Tonne | E64: =('Form Sa1'!H427+('Form Sa1'!H428*E113))/1000000 -> 4.1726374 | F64: =('Form Sa1'!I427+('Form Sa1'!I428*F113))/1000000 -> #DIV/0!
A65: viii | B65: SEC of Other Products (if any) after Molten Aluminum | C65: Annual | D65: Million kcal/Tonne | E65: =('Form Sa1'!H434+('Form Sa1'!H435*E113))/1000000 -> 2.9233331 | F65: =('Form Sa1'!I434+('Form Sa1'!I435*F113))/1000000 -> #DIV/0!
A66: ix | B66: SEC of Carbon Anode | C66: Annual | D66: Million kcal/Tonne | E66: =(('Form Sa1'!H386*E113)+'Form Sa1'!H387)/10^6 -> 1.2176905 | F66: =(('Form Sa1'!I386*F113)+'Form Sa1'!I387)/10^6 -> #DIV/0!
A68: C | B68: Equivalent product
A69: C1 | B69: Refinery Process
A70: i | B70: Total Equivalent Calcined Alumina Production | C70: Annual | D70: Tonne | E70: ='NF - 4 Product Mix'!E51 -> 561459 | F70: ='NF - 4 Product Mix'!F51 -> 0
A72: C2 | B72: Smelting Process
A73: i | B73: Total Equivalent Molten Aluminum Produced | C73: Annual | E73: ='NF - 4 Product Mix'!E90 -> 423396.46 | F73: ='NF - 4 Product Mix'!F90 -> 0
A75: D | B75: Details of Electricity Consumption
A76: D1 | B76: Electricity from Grid / Other
A77: (i) | B77: Total Electricity Purchased from grid/ Other with out colony/construction power etc | C77: Annual | D77: Lakh kWh | E77: ='Form Sa1'!H717 -> 694.70595 | F77: ='Form Sa1'!I717 -> 0
A78: (ii) | B78: Purchased Electricity from grid (SEB) | C78: Annual | D78: Lakh kWh | E78: ='Form Sa1'!H693 -> 1144.79 | F78: ='Form Sa1'!I693 -> 0
A79: (iii) | B79: Renewable Electricity (Through Wheeling) | C79: Annual | D79: Lakh kWh | E79: ='Form Sa1'!H694 -> 39.123359 | F79: ='Form Sa1'!I694 -> 0
A80: (iv) | B80: Electricity from CPP located outside from plant boundary (Through Wheeling) | C80: Annual | D80: Lakh kWh | E80: ='Form Sa1'!H699 -> 0 | F80: ='Form Sa1'!I699 -> 0
A81: (v) | B81: Plant Connected Load | D81: kW | E81: ='Form Sa1'!H710 -> 1488473 | F81: ='Form Sa1'!I710 -> 0
A82: (vi) | B82: Contract Demand with utility | D82: kVA | E82: ='Form Sa1'!H711 -> 44444.4 | F82: ='Form Sa1'!I711 -> 0
A84: E | B84: Own Generation
A85: E1.1 | B85: Through DG sets
A86: (i) | B86: ='Form Sa1'!B728 -> Install Capacity | D86: Lakh kWh | E86: ='Form Sa1'!H728 -> 0 | F86: ='Form Sa1'!I728 -> 0
A87: (ii) | B87: Gross Unit Generation | C87: Annual | D87: Lakh kWh | E87: ='Form Sa1'!H729 -> 0 | F87: ='Form Sa1'!I729 -> 0
A88: (iii) | B88: Avg. Gross Heat rate of DG Set | D88: kcal/kWh | E88: ='Form Sa1'!H1312 -> 0 | F88: ='Form Sa1'!I1312 -> 0
A89: E.1.2 | B89: Through Steam turbine/ generator
A90: (i) | B90: ='Form Sa1'!B739 -> Install Capacity | D90: MW | E90: ='Form Sa1'!H739 -> 829.58 | F90: ='Form Sa1'!I739 -> 829.58
A91: (ii) | B91: ='Form Sa1'!B740 -> Gross Unit generation | D91: Lakh kWh | E91: ='Form Sa1'!H740 -> 66354.072 | F91: ='Form Sa1'!I740 -> 0
A92: (iii) | B92: Average Gross Heat Rate | D92: kcal/ kWh | E92: ='Form Sa1'!H1313 -> 2564.5708 | F92: ='Form Sa1'!I1313 -> 0
A93: (iv) | B93: Auxiliary Power Consumption | D93: % | E93: ='Form Sa1'!H741 -> 8.33 | F93: ='Form Sa1'!I741 -> 0
A94: (v) | B94: ='Form Sa1'!B743 -> Operating Gross Heat Rate | D94: kcal/kWh | E94: ='Form Sa1'!H1313 -> 2564.5708 | F94: ='Form Sa1'!I743 -> 0
A95: E.1.3 | B95: Through Gas turbine
A96: (i) | B96: ='Form Sa1'!B747 -> Install Capacity | D96: MW | E96: ='Form Sa1'!H747 -> 0 | F96: ='Form Sa1'!I747 -> 0
A97: (ii) | B97: ='Form Sa1'!B748 -> Gross Unit generation | D97: Lakh kWh | E97: ='Form Sa1'!H748 -> 0 | F97: ='Form Sa1'!I748 -> 0
A98: (iii) | B98: Average Gross Heat Rate | D98: kcal/ kWh | E98: ='Form Sa1'!H1314 -> 0 | F98: ='Form Sa1'!I1314 -> 0
A99: (iv) | B99: ='Form Sa1'!B750 -> Auxiliary Power Consumption | D99: % | E99: ='Form Sa1'!H750 -> 0 | F99: ='Form Sa1'!I750 -> 0
A100: (v) | B100: Gross Design Heat Rate | D100: kcal/kWh | E100: ='Form Sa1'!H751 -> 0 | F100: ='Form Sa1'!I751 -> 0
A101: (vi) | B101: ='Form Sa1'!B749 -> Plant Load Factor (PLF) | D101: % | E101: ='Form Sa1'!H749 -> 0 | F101: ='Form Sa1'!I749 -> 0
A102: E.1.4 | B102: Through Co-generation (Extraction cum condensing)
A103: (i) | B103: Install Capacity | D103: MW | E103: ='Form Sa1'!H788 -> 66.4 | F103: ='Form Sa1'!I788 -> 0 | G103: ='Form Sa1'!K788 -> 0 | H103: ='Form Sa1'!#REF! -> #REF! | I103: ='Form Sa1'!#REF! -> #REF! | J103: ='Form Sa1'!#REF! -> #REF! | K103: ='Form Sa1'!#REF! -> #REF! | L103: ='Form Sa1'!#REF! -> #REF! | M103: ='Form Sa1'!#REF! -> #REF! | N103: ='Form Sa1'!#REF! -> #REF! | O103: ='Form Sa1'!#REF! -> #REF! | ... Q103: ='Form Sa1'!#REF! -> #REF! | R103: ='Form Sa1'!L787 -> 0 | S103: ='Form Sa1'!M787 -> 0 | T103: ='Form Sa1'!N787 -> 0 | U103: ='Form Sa1'!O787 -> 0 | V103: ='Form Sa1'!P787 -> 0 | W103: ='Form Sa1'!Q787 -> 0 | X103: ='Form Sa1'!R787 -> 0 | Y103: ='Form Sa1'!S787 -> 0 | ... IS103: ='Form Sa1'!IM787 -> 0 | IT103: ='Form Sa1'!#REF! -> #REF! | IU103: ='Form Sa1'!#REF! -> #REF! | IV103: ='Form Sa1'!#REF! -> #REF!
A104: (ii) | B104: Gross Unit generation | D104: Lakh kWh | E104: ='Form Sa1'!H789 -> 3739.3381 | F104: ='Form Sa1'!I789 -> 0 | G104: ='Form Sa1'!K789 -> 0 | H104: ='Form Sa1'!#REF! -> #REF! | I104: ='Form Sa1'!#REF! -> #REF! | J104: ='Form Sa1'!#REF! -> #REF! | K104: ='Form Sa1'!#REF! -> #REF! | L104: ='Form Sa1'!#REF! -> #REF! | M104: ='Form Sa1'!#REF! -> #REF! | N104: ='Form Sa1'!#REF! -> #REF! | O104: ='Form Sa1'!#REF! -> #REF! | ... Q104: ='Form Sa1'!#REF! -> #REF! | R104: ='Form Sa1'!L788 -> 0 | S104: ='Form Sa1'!M788 -> 0 | T104: ='Form Sa1'!N788 -> 0 | U104: ='Form Sa1'!O788 -> 0 | V104: ='Form Sa1'!P788 -> 0 | W104: ='Form Sa1'!Q788 -> 0 | X104: ='Form Sa1'!R788 -> 0 | Y104: ='Form Sa1'!S788 -> 0 | ... IS104: ='Form Sa1'!IM788 -> 0 | IT104: ='Form Sa1'!#REF! -> #REF! | IU104: ='Form Sa1'!#REF! -> #REF! | IV104: ='Form Sa1'!#REF! -> #REF!
A105: (iii) | B105: Average Gross Heat Rate | D105: kcal/ kWh | E105: ='Form Sa1'!H1315 -> 3636.0936 | F105: ='Form Sa1'!I1315 -> 0 | G105: ='Form Sa1'!K1315 -> 0 | H105: ='Form Sa1'!#REF! -> #REF! | I105: ='Form Sa1'!#REF! -> #REF! | J105: ='Form Sa1'!#REF! -> #REF! | K105: ='Form Sa1'!#REF! -> #REF! | L105: ='Form Sa1'!#REF! -> #REF! | M105: ='Form Sa1'!#REF! -> #REF! | N105: ='Form Sa1'!#REF! -> #REF! | O105: ='Form Sa1'!#REF! -> #REF! | ... Q105: ='Form Sa1'!#REF! -> #REF! | R105: ='Form Sa1'!L1314 -> 0 | S105: ='Form Sa1'!M1314 -> 0 | T105: ='Form Sa1'!N1314 -> 0 | U105: ='Form Sa1'!O1314 -> 0 | V105: ='Form Sa1'!P1314 -> 0 | W105: ='Form Sa1'!Q1314 -> 0 | X105: ='Form Sa1'!R1314 -> 0 | Y105: ='Form Sa1'!S1314 -> 0 | ... IS105: ='Form Sa1'!IM1314 -> 0 | IT105: ='Form Sa1'!#REF! -> #REF! | IU105: ='Form Sa1'!#REF! -> #REF! | IV105: ='Form Sa1'!#REF! -> #REF!
A106: (iv) | B106: Auxiliary Power Consumption | D106: % | E106: ='Form Sa1'!H790 -> 0 | F106: ='Form Sa1'!I790 -> 0 | G106: ='Form Sa1'!K790 -> 0 | H106: ='Form Sa1'!#REF! -> #REF! | I106: ='Form Sa1'!#REF! -> #REF! | J106: ='Form Sa1'!#REF! -> #REF! | K106: ='Form Sa1'!#REF! -> #REF! | L106: ='Form Sa1'!#REF! -> #REF! | M106: ='Form Sa1'!#REF! -> #REF! | N106: ='Form Sa1'!#REF! -> #REF! | O106: ='Form Sa1'!#REF! -> #REF! | ... Q106: ='Form Sa1'!#REF! -> #REF! | R106: ='Form Sa1'!L789 -> 0 | S106: ='Form Sa1'!M789 -> 0 | T106: ='Form Sa1'!N789 -> 0 | U106: ='Form Sa1'!O789 -> 0 | V106: ='Form Sa1'!P789 -> 0 | W106: ='Form Sa1'!Q789 -> 0 | X106: ='Form Sa1'!R789 -> 0 | Y106: ='Form Sa1'!S789 -> 0 | ... IS106: ='Form Sa1'!IM789 -> 0 | IT106: ='Form Sa1'!#REF! -> #REF! | IU106: ='Form Sa1'!#REF! -> #REF! | IV106: ='Form Sa1'!#REF! -> #REF!
A107: (v) | B107: Design Heat Rate | D107: kcal/kWh | E107: ='Form Sa1'!H791 -> 0 | F107: ='Form Sa1'!I791 -> 0 | G107: ='Form Sa1'!K791 -> 0 | H107: ='Form Sa1'!#REF! -> #REF! | I107: ='Form Sa1'!#REF! -> #REF! | J107: ='Form Sa1'!#REF! -> #REF! | K107: ='Form Sa1'!#REF! -> #REF! | L107: ='Form Sa1'!#REF! -> #REF! | M107: ='Form Sa1'!#REF! -> #REF! | N107: ='Form Sa1'!#REF! -> #REF! | O107: ='Form Sa1'!#REF! -> #REF! | ... Q107: ='Form Sa1'!#REF! -> #REF! | R107: ='Form Sa1'!L790 -> 0 | S107: ='Form Sa1'!M790 -> 0 | T107: ='Form Sa1'!N790 -> 0 | U107: ='Form Sa1'!O790 -> 0 | V107: ='Form Sa1'!P790 -> 0 | W107: ='Form Sa1'!Q790 -> 0 | X107: ='Form Sa1'!R790 -> 0 | Y107: ='Form Sa1'!S790 -> 0 | ... IS107: ='Form Sa1'!IM790 -> 0 | IT107: ='Form Sa1'!#REF! -> #REF! | IU107: ='Form Sa1'!#REF! -> #REF! | IV107: ='Form Sa1'!#REF! -> #REF!
...

Sheet Annex Addl Eqp List-Env
A1: List of additional Equipment installed due to Environmental Concern after baseline year
A2: Name of the Unit | E2: ='General Information'!C3 -> HINDALCO INDUSTRIES LIMITED
G3: ='NF - 5 Power Mix'!E4 -> Baseline/Previous Year 2023-24 | J3: ='NF - 5 Power Mix'!F4 -> Assesment year/ Current Year FY 2025-26
A4: Sr No | B4: Equipment Name | C4: Equipment Sr No | D4: Section | E4: Date of Commissioning | F4: Electrical Rated Capacity | G4: Thermal Rated Capacity | H4: Running Load | I4: Running Hours | J4: Electricity Consumption # | K4: Thermal Consumption ## | L4: Source of Data | M4: Remarks
E5: Date | F5: kW | G5: Million kcal/annum | H5: kW | I5: Hours/ Annum | J5: Lakh kWH/ Annum | K5: Million kcal/Annum
A6: 1
A7: 2
A8: 3
A9: 4
A10: 5
A11: 6
A12: 7
A13: 8
A14: 9
A15: 10
A16: 11
A17: 12
... A26: 21
A27: Total | F27: =SUM(F6:F26) -> 0 | G27: =SUM(G6:G26) -> 0 | H27: =SUM(H6:H26) -> 0 | I27: =SUM(I6:I26) -> 0 | J27: =SUM(J6:J26) -> 0 | K27: =SUM(K6:K26) -> 0
A28: # | B28: Equipmenmt wise Energy Meter Reading or Energy Management System Data required in support of the claim
A29: ## | B29: Equipment wise Document related to consumption of Liquid Fuel, Solid Fuel Aleterante Fuel is required in support of the claim

Sheet Annex Project Activites List
A1: List of Equipment and Energy consumed during project activity up to commissining during the Assessment year
A2: Name of the Unit | E2: ='General Information'!C3 -> HINDALCO INDUSTRIES LIMITED
G3: ='NF - 5 Power Mix'!E4 -> Baseline/Previous Year 2023-24 | J3: ='NF - 5 Power Mix'!F4 -> Assesment year/ Current Year FY 2025-26
A4: Sr No | B4: Equipment Name | C4: Equipment Sr No | D4: Section | E4: Project Activity Start Date | F4: Date of Commissioning | G4: Electrical Rated Capacity | H4: Thermal Rated Capacity | I4: Running Load | J4: Running Hours | K4: Electricity Consumption# | L4: Thermal Consumption## | M4: Source of Data | N4: Remarks
E5: Date | F5: Date | G5: kW | H5: Million kcal/annum | I5: kW | J5: Hours/ Annum | K5: Lakh kWH/ Annum | L5: Million kcal/Annum
A6: 1
A7: 2
A8: 3
A9: 4
A10: 5
A11: 6
A12: 7
A13: 8
A14: 9
A15: 10
A16: 11
A17: 12
... A26: 21
A27: Total | G27: =SUM(G6:G26) -> 0 | H27: =SUM(H6:H26) -> 0 | I27: =SUM(I6:I26) -> 0 | J27: =SUM(J6:J26) -> 0 | K27: =SUM(K6:K26) -> 0 | L27: =SUM(L6:L26) -> 0
A28: # | B28: Equipmenmt wise Energy Meter Reading or Energy Management System Data required in support of the claim
A29: ## | B29: Equipment wise Document related to consumption of Liquid Fuel, Solid Fuel Aleterante Fuel is required in support of the claim

Sheet N1-BQ Bauxite Quality
A1: Normalization Factor for Bauxite Quality
A2: Name of the Unit | C2: ='General Information'!C3:G3 -> HINDALCO INDUSTRIES LIMITED
B3: Document Available for Normalisation | D3: Yes/No | E3: ='Form Sa1'!H1373 -> Yes | F3: ='Form Sa1'!I1373 -> Yes
A4: Sr. No | B4: Description | C4: Calculation/Basis | D4: Unit | E4: ='NF - 5 Power Mix'!E4 -> Baseline/Previous Year 2023-24 | F4: ='NF - 5 Power Mix'!F4 -> Assesment year/ Current Year FY 2025-26
A5: 1 | B5: Total Hydrate Alumina Production | C5: Form Sa1'! A1(iii) | D5: t | E5: ='Form Sa1'!H45 -> 565600 | F5: ='Form Sa1'!I45 -> 0
A6: 2 | B6: TAA/THA | C6: Form Sa1'! J(IV) | D6: % | E6: ='Form Sa1'!H1330 -> 39.020229 | F6: ='Form Sa1'!I1330 -> 0
A7: 3 | B7: Moisture | C7: Form Sa1'! J(viii) | D7: % | E7: ='Form Sa1'!H1334 -> 4.5865696 | F7: ='Form Sa1'!I1334 -> 0
A8: 4 | B8: Overall Recovery | C8: Form Sa1'! J(ix) | D8: % | E8: ='Form Sa1'!H1335 -> 93.304124 | F8: ='Form Sa1'!I1335 -> 0
A9: 5 | B9: Wash Water | C9: Form Sa1'! J(x) | D9: t/t of mud | E9: ='Form Sa1'!H1336 -> 0.71 | F9: ='Form Sa1'!I1336 -> 0
A10: 6 | B10: Steam Economy | C10: Form Sa1'! J(xi) | D10: t/t | E10: ='Form Sa1'!H1337 -> 3.03 | F10: ='Form Sa1'!I1337 -> 0
A11: 7 | B11: Fe in Bxt | C11: Form Sa1'! J(xii) | D11: % | E11: ='Form Sa1'!H1338 -> 18.879329 | F11: ='Form Sa1'!I1338 -> 0
A12: 8 | B12: Fe in Mud | C12: Form Sa1'! J(xiii) | D12: % | E12: ='Form Sa1'!H1339 -> 38.358107 | F12: ='Form Sa1'!I1339 -> 0
A13: 9 | B13: Actual Steam Enthalpy | C13: Form Sa1'! J(xiv) | D13: kcal/kg | E13: ='Form Sa1'!H1340 -> 747.01439 | F13: ='Form Sa1'!I1340 -> 0
A14: 10 | B14: Boiler Efficiency | C14: Form Sa1'! e3.6 | D14: Factor | E14: ='Form Sa1'!H688 -> 83.818124 | F14: ='Form Sa1'!I688 -> 0
A16: 11 | B16: Specific Bauxite Factor (SBC) | C16: 1/{(2)% *(100-(3))%*(4)%} | D16: t bxt/t Al | E16: =IFERROR(1/(E6%*(100-E7)%*E8%),0) -> 2.8787227 | F16: =IFERROR((1/(F6%*(100-F7)%*F8%)),0) -> 0
A17: 12 | B17: Mud Factor | C17: Fe2O3 in Bxt/Fe2O3 in Mud - {(7)/(8)} | D17: t mud/t bxt | E17: =IFERROR(E11/E12,0) -> 0.49218615 | F17: =IFERROR((F11/F12),0) -> 0
A18: 13 | B18: Wash Water in tons | C18: {(11)*(100-(3))%*(12)*(5)} | D18: t | E18: =IFERROR(E16*(100-E7)%*E17*E9,0) -> 0.9598361 | F18: =IFERROR((F16*(100-F7)%*F17*F9),0) -> 0
A19: 14 | B19: Excess Moisture | C19: [{(11AY)-(11BY)}*(3)] | D19: t | F19: =IFERROR(((F16-E16)*F7%),0) -> 0
A20: 15 | B20: Excess Wash Water | C20: {(13AY)-(13BY)} | D20: t | F20: =IFERROR((F18-E18),0) -> -0.9598361
A21: 16 | B21: Excess Steam | C21: {(14)+(15)}/(6)} | D21: t/t | F21: =IFERROR(((F19+F20)/F10),0) -> 0
A22: 17 | B22: Notional Energy for moisture | C22: {(16)*(9)*10^3/(10)} | D22: kcal/t | F22: =IFERROR((F21*F13*10^3/F14),0) -> 0
A23: 18 | B23: Notional Energy to be subtracted | C23: {(17)*(1)/10^6} | D23: Million kcal | F23: =IF(AND(E3="Yes", F3="Yes"), (F22*F5/10^6), 0) -> 0

Sheet NF - 2 Fuel Quality CPP & Cogen
A1: Normalized Boiler Efficiency in CPP (unit Wise)
A2: Name of the Unit | E2: ='Form Sa1'!C3 -> HINDALCO INDUSTRIES LIMITED
A3: Sr No | B3: Item | C3: Basis/Calculation | D3: Unit | E3: Unit 1 | G3: Unit 2 | I3: Unit 3 | K3: Unit 4 | M3: Unit 5 | O3: Unit 6 | Q3: Unit 7 | S3: Unit 8 | U3: Unit 9 | W3: Unit 10
E4: BY | F4: AY | G4: BY | H4: AY | I4: BY | J4: AY | K4: BY | L4: AY | M4: BY | N4: AY | O4: BY | P4: AY | Q4: BY | R4: AY | S4: BY | T4: AY | U4: BY | V4: AY | W4: BY | X4: AY
A5: 1 | B5: Unit Capacity | C5: 'Form Sa1 CPP'! {4.a.(i)Cap} | D5: MW | E5: ='Annex CPP'!C82 -> 81.75 | F5: =E5 -> 81.75 | G5: ='Annex CPP'!C83 -> 81.75 | H5: =G5 -> 81.75 | I5: ='Annex CPP'!C84 -> 84 | J5: =I5 -> 84 | K5: ='Annex CPP'!C85 -> 84 | L5: ='Annex CPP'!C10 -> 84 | M5: ='Annex CPP'!C86 -> 76 | N5: =M5 -> 76 | O5: ='Annex CPP'!C87 -> 84 | P5: =O5 -> 84 | Q5: ='Annex CPP'!C88 -> 84 | R5: =Q5 -> 84 | S5: ='Annex CPP'!C89 -> 80.08 | T5: =S5 -> 80.08 | U5: ='Annex CPP'!C90 -> 87 | V5: =U5 -> 87 | W5: ='Annex CPP'!C91 -> 87 | X5: =W5 -> 87
A6: 2 | B6: Total Moisture | C6: Form Sa1 CPP'! {4.a.(i)TM} | D6: % | E6: ='Annex CPP'!E82 -> 14.165522 | F6: ='Annex CPP'!L82 -> 0 | G6: ='Annex CPP'!E83 -> 14.141888 | H6: ='Annex CPP'!L83 -> 0 | I6: ='Annex CPP'!E84 -> 14.450208 | J6: ='Annex CPP'!L84 -> 0 | K6: ='Annex CPP'!E85 -> 14.420619 | L6: ='Annex CPP'!L85 -> 0 | M6: ='Annex CPP'!E86 -> 14.398673 | N6: ='Annex CPP'!L86 -> 0 | O6: ='Annex CPP'!E87 -> 14.184101 | P6: ='Annex CPP'!L87 -> 0 | Q6: ='Annex CPP'!E88 -> 14.25589 | R6: ='Annex CPP'!L88 -> 0 | S6: ='Annex CPP'!E89 -> 14.055037 | T6: ='Annex CPP'!L89 -> 0 | U6: ='Annex CPP'!E90 -> 14.073938 | V6: ='Annex CPP'!L90 -> 0 | W6: ='Annex CPP'!E91 -> 14.007632 | X6: ='Annex CPP'!L91 -> 0
A7: 3 | B7: Ash | C7: Form Sa1 CPP'! {4.a.(i)A} | D7: % | E7: ='Annex CPP'!F82 -> 31.186943 | F7: ='Annex CPP'!M82 -> 0 | G7: ='Annex CPP'!F83 -> 32.164207 | H7: ='Annex CPP'!M83 -> 0 | I7: ='Annex CPP'!F84 -> 32.222178 | J7: ='Annex CPP'!M84 -> 0 | K7: ='Annex CPP'!F85 -> 32.248599 | L7: ='Annex CPP'!M85 -> 0 | M7: ='Annex CPP'!F86 -> 31.746014 | N7: ='Annex CPP'!M86 -> 0 | O7: ='Annex CPP'!F87 -> 32.108795 | P7: ='Annex CPP'!M87 -> 0 | Q7: ='Annex CPP'!F88 -> 31.802063 | R7: ='Annex CPP'!M88 -> 0 | S7: ='Annex CPP'!F89 -> 32.50978 | T7: ='Annex CPP'!M89 -> 0 | U7: ='Annex CPP'!F90 -> 32.539076 | V7: ='Annex CPP'!M90 -> 0 | W7: ='Annex CPP'!F91 -> 32.613681 | X7: ='Annex CPP'!M91 -> 0
A8: 4 | B8: GCV | C8: Form Sa1 CPP'! {4.a.(i)G} | D8: % | E8: ='Annex CPP'!G82 -> 3963.8478 | F8: ='Annex CPP'!N82 -> 0 | G8: ='Annex CPP'!G83 -> 3970.5031 | H8: ='Annex CPP'!N83 -> 0 | I8: ='Annex CPP'!G84 -> 3935.6835 | J8: ='Annex CPP'!N84 -> 0 | K8: ='Annex CPP'!G85 -> 3936.4164 | L8: ='Annex CPP'!N85 -> 0 | M8: ='Annex CPP'!G86 -> 3980.9838 | N8: ='Annex CPP'!N86 -> 0 | O8: ='Annex CPP'!G87 -> 3968.2508 | P8: ='Annex CPP'!N87 -> 0 | Q8: ='Annex CPP'!G88 -> 3989.0295 | R8: ='Annex CPP'!N88 -> 0 | S8: ='Annex CPP'!G89 -> 3940.2849 | T8: ='Annex CPP'!N89 -> 0 | U8: ='Annex CPP'!G90 -> 3934.6397 | V8: ='Annex CPP'!N90 -> 0 | W8: ='Annex CPP'!G91 -> 3935.8551 | X8: ='Annex CPP'!N91 -> 0
A9: 5 | B9: Hydrogen | C9: Form Sa1 CPP'! {4.a.(i)H} | D9: % | E9: ='Annex CPP'!H82 -> 2.320324 | F9: ='Annex CPP'!O82 -> 0 | G9: ='Annex CPP'!H83 -> 2.3276253 | H9: ='Annex CPP'!O83 -> 0 | I9: ='Annex CPP'!H84 -> 2.2895229 | J9: ='Annex CPP'!O84 -> 0 | K9: ='Annex CPP'!H85 -> 2.2905088 | L9: ='Annex CPP'!O85 -> 0 | M9: ='Annex CPP'!H86 -> 2.3236936 | N9: ='Annex CPP'!O86 -> 0 | O9: ='Annex CPP'!H87 -> 2.3269589 | P9: ='Annex CPP'!O87 -> 0 | Q9: ='Annex CPP'!H88 -> 2.3371273 | R9: ='Annex CPP'!O88 -> 0 | S9: ='Annex CPP'!H89 -> 2.3124789 | T9: ='Annex CPP'!O89 -> 0 | U9: ='Annex CPP'!H90 -> 2.3093937 | V9: ='Annex CPP'!O90 -> 0 | W9: ='Annex CPP'!H91 -> 2.3106648 | X9: ='Annex CPP'!O91 -> 0
A10: 6 | B10: % Boiler Efficiency (As per Formulae) | C10: 92.5- {50*[2] +630*([1]+9*[4])}/[3] | D10: % | E10: =IFERROR(92.5-(50*E7+630*(E6+9*E9))/E8,0) -> 86.536133 | F10: =IFERROR(92.5-(50*F7+630*(F6+9*F9))/F8,0) -> 0 | G10: =IFERROR(92.5-(50*G7+630*(G6+9*G9))/G8,0) -> 86.527146 | H10: =IFERROR(92.5-(50*H7+630*(H6+9*H9))/H8,0) -> 0 | I10: =IFERROR(92.5-(50*I7+630*(I6+9*I9))/I8,0) -> 86.479106 | J10: =IFERROR(92.5-(50*J7+630*(J6+9*J9))/J8,0) -> 0 | K10: =IFERROR(92.5-(50*K7+630*(K6+9*K9))/K8,0) -> 86.483207 | L10: =IFERROR(92.5-(50*L7+630*(L6+9*L9))/L8,0) -> 0 | ... X10: =IFERROR(92.5-(50*X7+630*(X6+9*X9))/X8,0) -> 0
A11: 7 | B11: % Decrease in Efficiency from calculated Boiler operating Efficiency from calculated Boiler Design Eff | D11: % | F11: =(F10-E10)*100/F10 -> #DIV/0! | H11: =(H10-G10)*100/H10 -> #DIV/0! | J11: =(J10-I10)*100/J10 -> #DIV/0! | L11: =(L10-K10)*100/L10 -> #DIV/0! | N11: =(N10-M10)*100/N10 -> #DIV/0! | P11: =(P10-O10)*100/P10 -> #DIV/0! | R11: =(R10-Q10)*100/R10 -> #DIV/0! | T11: =(T10-S10)*100/T10 -> #DIV/0! | V11: =(V10-U10)*100/V10 -> #DIV/0! | X11: =(X10-W10)*100/X10 -> #DIV/0!
A12: 8 | B12: Normalised Boiler Efficiency for Unit | D12: % | F12: =F10-F11 -> #DIV/0! | H12: =H10-H11 -> #DIV/0! | J12: =J10-J11 -> #DIV/0! | L12: =L10-L11 -> #DIV/0! | N12: =N10-N11 -> #DIV/0! | P12: =P10-P11 -> #DIV/0! | R12: =R10-R11 -> #DIV/0! | T12: =T10-T11 -> #DIV/0! | V12: =V10-V11 -> #DIV/0! | X12: =X10-X11 -> #DIV/0!
A13: 7 | B13: Actual Design Boiler Efficiency of Unit (As per OEM) | C13: As per Form I | D13: % | F13: ='Annex CPP'!D7 -> 83 | H13: 87.25 | J13: 0 | L13: 0 | N13: 0 | P13: 0 | R13: 0 | T13: 0 | V13: 0 | X13: 0
A14: 8 | B14: Design Turbine Heat Rate of Unit (As per OEM) | C14: As per Form I | D14: kcal/kWh | F14: ='Annex CPP'!E7 -> 2224 | H14: 2045 | J14: 0 | L14: 0 | N14: 0 | P14: 0 | R14: 0 | T14: 0 | V14: 0 | X14: 0
A15: 9 | B15: Final Unit Design Heat Rate of Unit (As per OEM) | C15: [7]/[6] | D15: kcal/kWh | F15: ='Annex CPP'!F7 -> 2679.5181 | H15: 2343.8395 | J15: 0 | L15: 0 | N15: 0 | P15: 0 | R15: 0 | T15: 0 | V15: 0 | X15: 0
A16: 10 | B16: % Decrease in Efficiency from calculated Boiler operating Efficiency from calculated Boiler Design Eff | C16: ([8]D-[8]O)/[8]D | D16: % | F16: =(F10-E10)*100/F10 -> #DIV/0! | H16: =(H10-G10)*100/H10 -> #DIV/0! | J16: =(J10-I10)*100/J10 -> #DIV/0! | L16: =(L10-K10)*100/L10 -> #DIV/0! | N16: =(N10-M10)*100/N10 -> #DIV/0! | P16: =(P10-O10)*100/P10 -> #DIV/0! | R16: =(R10-Q10)*100/R10 -> #DIV/0! | T16: =(T10-S10)*100/T10 -> #DIV/0! | V16: =(V10-U10)*100/V10 -> #DIV/0! | X16: =(X10-W10)*100/X10 -> #DIV/0!
A17: 11 | B17: Degradation/Upgradation of Actual Boiler Design Efficiency | C17: [6]D*[9]D/100 | D17: % | F17: =F13*F16/100 -> #DIV/0! | H17: =H13*H16/100 -> #DIV/0! | J17: =J13*J16/100 -> #DIV/0! | L17: =L13*L16/100 -> #DIV/0! | N17: =N13*N16/100 -> #DIV/0! | P17: =P13*P16/100 -> #DIV/0! | R17: =R13*R16/100 -> #DIV/0! | T17: =T13*T16/100 -> #DIV/0! | V17: =V13*V16/100 -> #DIV/0! | X17: =X13*X16/100 -> #DIV/0!
A18: 12 | B18: Normalised Boiler Efficiency Design for Unit | C18: [6]D-[10]D | D18: % | F18: =F13-F17 -> #DIV/0! | H18: =H13-H17 -> #DIV/0! | J18: =J13-J17 -> #DIV/0! | L18: =L13-L17 -> #DIV/0! | N18: =N13-N17 -> #DIV/0! | P18: =P13-P17 -> #DIV/0! | R18: =R13-R17 -> #DIV/0! | T18: =T13-T17 -> #DIV/0! | V18: =V13-V17 -> #DIV/0! | X18: =X13-X17 -> #DIV/0!
A19: 7 | B19: Boiler Efficiency for Station in Baseline Year | C19: {(1u#1)*(6U#1)}+{(1u#2)*(6U#2)}+{(1u#3)*(6U#3)}+{(1u#4)*(6U#4)}+{(1u#5)*(6U#5)}+{(1u#6)*(6U#6)}+{(1u#7)*(6U#7)}+{(1u#8)*(6U#8)}+{(1u#9)*(6U#9)}+{(1u#10)*(6U#10)}]/[(1u#1)+(1u#2)+(1u#3)+(1u#4)+(1u#5)+(1u#6)+(1u#7)+(1u#8)+(1u#9)+(1u#10)] | D19: % | E19: =IFERROR((E5*E10+G5*G10+I5*I10+K5*K10+M5*M10+O5*O10+Q5*Q10+S5*S10+U5*U10+W5*W10)/(E5+G5+I5+K5+M5+O5+Q5+S5+U5+W5),0) -> 86.511643
A20: 8 | B20: Boiler Efficiency for Station in Assesment year | C20: {(1u#1)*(6U#1)}+{(1u#2)*(6U#2)}+{(1u#3)*(6U#3)}+{(1u#4)*(6U#4)}+{(1u#5)*(6U#5)}+{(1u#6)*(6U#6)}+{(1u#7)*(6U#7)}+{(1u#8)*(6U#8)}+{(1u#9)*(6U#9)}+{(1u#10)*(6U#10)}]/[(1u#1)+(1u#2)+(1u#3)+(1u#4)+(1u#5)+(1u#6)+(1u#7)+(1u#8)+(1u#9)+(1u#10)] | D20: % | E20: =IFERROR(((F5*F10+H5*H10+J5*J10+L5*L10+N5*N10+P5*P10+R5*R10+T5*T10+V5*V10+X5*X10)/(F5+H5+J5+L5+N5+P5+R5+T5+V5+X5)),0) -> 0
A21: A | B21: Normalization Factor for Fuel Quality in CPP
A22: Document Available for Normalisation | D22: Yes/No | E22: ='Form Sa1'!H1375 -> Yes | F22: ='Form Sa1'!I1375 -> Yes
A23: S.No. | B23: Description | C23: Basis/ Calculation | D23: Units | E23: ='NF - 5 Power Mix'!E4 -> Baseline/Previous Year 2023-24 | F23: ='NF - 5 Power Mix'!F4 -> Assesment year/ Current Year FY 2025-26
A24: 1 | B24: CPP Generation | C24: Form Sa1 CPP'! (2b Gr.Gn.) | D24: Lakh kWh | E24: ='Annex CPP'!G35 -> 66354.072 | F24: ='Annex CPP'!O35 -> 0
A25: 2 | B25: Actual CPP Heat Rate | C25: Baseline Parameter!E.1.2.3 | D25: kcal/kWh | E25: ='Baseline Parameter'!E92 -> 2564.5708 | F25: ='Baseline Parameter'!F92 -> 0
A26: 3 | B26: Boiler Efficiency | C26: (7) & (8) | D26: % | E26: =E19 -> 86.511643 | F26: =E20 -> 0
A27: 4 | B27: CPP Heat Rate due to Fuel Quality in AY | C27: (A2)BY x [(A3)BY/(A3)AY] | D27: kcal/kWh | F27: =IF(F26=0, 0, E25*E26/F26) -> 0
A28: 5 | B28: Difference CPP Heat rate from BY to AY | C28: (A4)AY-(A4)BY | D28: kcal/kWh | F28: =IF(F27=0, 0, F27-$E$25) -> 0
A29: 6 | B29: Energy to be subtracted w.r.t. Fuel Quality | C29: (A5)AY x (A1)AY/10 | D29: Million kcal | F29: =F28*F24/10 -> 0
A30: B | B30: Normalization Factor for Fuel Quality in C0-GEN
A31: 1 | B31: Ash | C31: Form Sa1'! i(ii) | D31: % | E31: ='Form Sa1'!H1322 -> 39.140737 | F31: ='Form Sa1'!I1322 -> 0
A32: 2 | B32: Moisture | C32: Form Sa1'! i(iv) | D32: % | E32: ='Form Sa1'!H1324 -> 12.234135 | F32: ='Form Sa1'!I1324 -> 0
A33: 3 | B33: Hydrogen | C33: Form Sa1'! i(i1i) | D33: % | E33: ='Form Sa1'!H1323 -> 2.0332142 | F33: ='Form Sa1'!I1323 -> 0
A34: 4 | B34: GCV | C34: Form Sa1'! i(i) | D34: kcal/kg | E34: ='Form Sa1'!H1321 -> 3482.7822 | F34: ='Form Sa1'!I1321 -> 0
A35: 5 | B35: Boiler Efficiency | C35: 92.5- [{50 x (3) + 630x ((4)+ 9x (5))} / (6)] | D35: % | E35: =IF(E34=0, 0, 92.5-(50*E31+630*(E32+9*E33))/E34) -> 86.414961 | F35: =IF(F34=0, 0, 92.5-(50*F31+630*(F32+9*F33))/F34) -> 0
A36: 6 | B36: Steam Generation at Boiler 1-5 | C36: Form Sa1'! (e 1.4) | D36: Tonne | E36: ='Form Sa1'!H560 -> 1060213.2 | F36: ='Form Sa1'!I560 -> 0
A37: 7 | B37: Steam Generation at Boiler 6-10 | C37: Form Sa1'! (e 3.1) | D37: Tonne | E37: ='Form Sa1'!H683 -> 2153635.7 | F37: ='Form Sa1'!I683 -> 0
A38: 8 | B38: Specific Energy Consumption for Steam Generation in Cogen Boiler 1-5 | C38: Form Sa1'! (e 1.9) | D38: kcal/kg of Steam | E38: ='Form Sa1'!H563 -> 830.24284 | F38: ='Form Sa1'!I563 -> 0
A39: 9 | B39: Specific Energy Consumption for Steam Generation in Process Boiler 6-10 | C39: Form Sa1'! (e 3.4) | D39: kcal/kg of Steam | E39: ='Form Sa1'!H686 -> 791.82448 | F39: ='Form Sa1'!I686 -> 0
A40: 10 | B40: Weighted Percentage of Coal Energy Used in steam Generation (Process Boiler) | C40: Form Sa1'! (e 1.10) | D40: Factor | E40: ='Form Sa1'!H564 -> 0.99520673 | F40: ='Form Sa1'!I564 -> 0
A41: 11 | B41: Weighted Percentage of Coal Energy Used in steam Generation (Co-Gen Boilers) | C41: Form Sa1'! (e 3.5) | D41: Factor | E41: ='Form Sa1'!H687 -> 0.9836419 | F41: ='Form Sa1'!I687 -> 0
A42: 12 | B42: Weighted Average Specific Steam Consumption | C42: Annual-[{(B8)*(B6)+((B9)*(B7)}/{(B6)+(B7)}] | D42: kcal/kg of Steam | E42: =IFERROR((E38*E36+E39*E37)/(E36+E37),0) -> 804.49827 | F42: =IFERROR((F38*F36+F39*F37)/(F36+F37),0) -> 0
A43: 13 | B43: Normalised Specific Energy Consumption for Steam Generation | C43: [(B12 BY)* (B5 BY)/(B5 AY)] | D43: kcal/kg of Steam | F43: =IFERROR(E42*(E35/F35),0) -> 0
A44: 14 | B44: Difference Specific Steam from BY to AY | C44: [(B13 AY)-(B12 BY)] | D44: kcal/kg of Steam | F44: =F43-E42 -> -804.49827
A45: 15 | B45: Energy to be subtracted w.r.t. Fuel Quality in Co-Gen | C45: [[(B14)*{(B6)*(B10)+(B7)*(B11)}]/1000] | D45: Million kCal | F45: =IF(AND(E22="yes",F22="yes"),(F44*(F36*F40+F37*F41))/1000,0) -> 0
A47: 16 | B47: Total Notional energy for Coal Quality deterioration to be subratced w.r.t fuel quality | C47: [(B15)+(A6)] | D47: Million kcal | F47: =IF(AND(E22="Yes",F22="Yes"),IF((F45+F29)<0,0,(F45+F29)),0) -> 0

Sheet NF - 3 PLF
A1: Normalization Factor for Unit Load Factor
A2: Name of Unit | G2: ='Form Sa1'!C3 -> HINDALCO INDUSTRIES LIMITED
A3: Document Available for Normalisation | D3: Yes/No | E3: ='Form Sa1'!H1376 -> Yes | F3: ='Form Sa1'!I1376 -> Yes
A4: Sr No | B4: Item | C4: Calculation/Basis | D4: Unit | E4: Unit 1 | G4: Unit 2 | I4: Unit 3 | K4: Unit 4 | M4: Unit 5 | O4: Unit 6 | Q4: Unit 7 | S4: Unit 8 | U4: Unit 9 | W4: Unit 10
E5: BY | F5: AY | G5: BY | H5: AY | I5: BY | J5: AY | K5: BY | L5: AY | M5: BY | N5: AY | O5: BY | P5: AY | Q5: BY | R5: AY | S5: BY | T5: AY | U5: BY | V5: AY | W5: BY | X5: AY
A6: 1 | B6: Unit Capacity | C6: Form Sa1 CPP'! 1a(i) Cap | D6: MW | E6: ='Annex CPP'!C7 -> 81.75 | F6: =E6 -> 81.75 | G6: ='Annex CPP'!C8 -> 81.75 | H6: =G6 -> 81.75 | I6: ='Annex CPP'!C9 -> 84 | J6: =I6 -> 84 | K6: ='Annex CPP'!C10 -> 84 | L6: =K6 -> 84 | M6: ='Annex CPP'!C11 -> 76 | N6: =M6 -> 76 | O6: ='Annex CPP'!C12 -> 84 | P6: =O6 -> 84 | Q6: ='Annex CPP'!C13 -> 84 | R6: =Q6 -> 84 | S6: ='Annex CPP'!C14 -> 80.08 | T6: =S6 -> 80.08 | U6: ='Annex CPP'!C15 -> 87 | V6: =U6 -> 87 | W6: ='Annex CPP'!C16 -> 87 | X6: =W6 -> 87
A7: 2 | B7: Gross Unit Generation | C7: Form Sa1 CPP'! 2a (i) Gr.Gn | D7: Lakh Unit | E7: ='Annex CPP'!G25 -> 6802.5805 | F7: ='Annex CPP'!O25 -> 0 | G7: ='Annex CPP'!G26 -> 6421.7318 | H7: ='Annex CPP'!O26 -> 0 | I7: ='Annex CPP'!G27 -> 6821.2779 | J7: ='Annex CPP'!O27 -> 0 | K7: ='Annex CPP'!G28 -> 7266.1325 | L7: ='Annex CPP'!O28 -> 0 | M7: ='Annex CPP'!G29 -> 6228.8947 | N7: ='Annex CPP'!O29 -> 0 | O7: ='Annex CPP'!G30 -> 5809.0445 | P7: ='Annex CPP'!O30 -> 0 | Q7: ='Annex CPP'!G31 -> 6900.649 | R7: ='Annex CPP'!O31 -> 0 | S7: ='Annex CPP'!G32 -> 6946.3376 | T7: ='Annex CPP'!O32 -> 0 | U7: ='Annex CPP'!G33 -> 7268.8998 | V7: ='Annex CPP'!O33 -> 0 | W7: ='Annex CPP'!G34 -> 5888.5238 | X7: ='Annex CPP'!O34 -> 0
A8: 3 | B8: Design Turbine Heat Rate @ 100% Load (OEM) | C8: Form Sa1 CPP'! 1a(i) THR-OEM | D8: kcal/kwh | E8: ='Annex CPP'!E7 -> 2224 | F8: =E8 -> 2224 | G8: ='Annex CPP'!E8 -> 2224 | H8: =G8 -> 2224 | I8: ='Annex CPP'!E9 -> 2112 | J8: =I8 -> 2112 | K8: ='Annex CPP'!E10 -> 2112 | L8: =K8 -> 2112 | M8: ='Annex CPP'!E11 -> 2127 | N8: =M8 -> 2127 | O8: ='Annex CPP'!E12 -> 2170 | P8: =O8 -> 2170 | Q8: ='Annex CPP'!E13 -> 2170 | R8: =Q8 -> 2170 | S8: ='Annex CPP'!E14 -> 2216 | T8: =S8 -> 2216 | U8: ='Annex CPP'!E15 -> 2162 | V8: =U8 -> 2162 | W8: ='Annex CPP'!E16 -> 2162 | X8: =W8 -> 2162
